Workbook

Sheet Legend
B1: Yo | E1: Big Board Color Grades | F1: NIL + Scholarship Package
E2: P4 Starter | F2: NIL + Scholarship
E3: G5 Starter | F3: NIL + Scholarship
E4: G5 Spot Starter | F4: Scholarship
E5: G5 Backup | F5: Walk On

Sheet Offensive Big Board
A1: =sum(H1,R1,AB1,AL1,AV1,BF1) -> 424 | B1: =SUM(H2,R2,AB2,AL2,AV2,BF2) -> 208 | H1: =count(H3:H1000) -> 43 | R1: =count(R3:R1000) -> 69 | AB1: =count(AB3:AB1000) -> 189 | AL1: =count(AL3:AL1000) -> 36 | AV1: =count(AV3:AV1000) -> 48 | BF1: =count(BF3:BF1000) -> 39
A2: QB | H2: =COUNTIF(J3:J1000, "Y") -> 36 | K2: RB | R2: =COUNTIF(T3:T1000, "Y") -> 23 | U2: WR | AB2: =COUNTIF(AD3:AD1000, "Y") -> 91 | AE2: TE | AL2: =COUNTIF(AN3:AN1000, "Y") -> 21 | AO2: OT | AV2: =COUNTIF(AX3:AX1000, "Y") -> 23 | AY2: IOL | BF2: =COUNTIF(BH3:BH1000, "Y") -> 14
A3: ='QB Formula'!A3&", "&'QB Formula'!B3 -> Brendan Sorsby, Cincinnati | H3: =if('QB Formula'!P3 = 0, " ", 'QB Formula'!P3) -> 5.4921429 | I3: ='QB Formula'!B3 -> Cincinnati | J3: ='QB Formula'!C3 -> Y | K3: ='RB Formula'!A3&", "&'RB Formula'!B3 -> Miles Davis, Utah State | R3: =if('RB Formula'!R3 = 0, " ", 'RB Formula'!S3) -> 5.6583333 | S3: ='RB Formula'!B3 -> Utah State | T3: ='RB Formula'!C3 -> N | U3: ='WR Formula'!A3&", "&'WR Formula'!B3 -> Braden Pegan, Utah State | AB3: =if('WR Formula'!N3 = 0, " ", 'WR Formula'!P3) -> 5.5571429 | AC3: ='WR Formula'!B3 -> Utah State | AD3: ='WR Formula'!C3 -> Y | AE3: ='TE Formula'!A3&", "&'TE Formula'!B3 -> Brody Foley, Tulsa | AL3: =if('TE Formula'!P3 = 0, " ", 'TE Formula'!R3) -> 4.6055556 | AM3: ='TE Formula'!B3 -> Tulsa | AN3: ='TE Formula'!C3 -> Y | AO3: ='OT Formula'!A3&", "&'OT Formula'!B3 -> Spencer Fano, Utah | AV3: =if('OT Formula'!N3 = 0, " ", 'OT Formula'!O3) -> 5.4633333 | AW3: ='OT Formula'!B3 -> Utah | AX3: ='OT Formula'!C3 -> N | AY3: ='IOL Formula'!A3&", "&'IOL Formula'!B3 -> Ryan Berger, Oregon State | BF3: =if('IOL Formula'!N3 = 0, " ", 'IOL Formula'!O3) -> 5.7 | BG3: ='IOL Formula'!B3 -> Oregon State | BH3: ='IOL Formula'!C3 -> N
A4: ='QB Formula'!A4&", "&'QB Formula'!B4 -> Dylan Raiola, Nebraska | H4: =if('QB Formula'!P4 = 0, " ", 'QB Formula'!P4) -> 5.355 | I4: ='QB Formula'!B4 -> Nebraska | J4: ='QB Formula'!C4 -> Y | K4: ='RB Formula'!A4&", "&'RB Formula'!B4 -> Cam Scott, Jacksonville State | R4: =if('RB Formula'!R4 = 0, " ", 'RB Formula'!S4) -> 5.3375 | S4: ='RB Formula'!B4 -> Jacksonville State | T4: ='RB Formula'!C4 -> N | U4: ='WR Formula'!A4&", "&'WR Formula'!B4 -> Jaceon Doss, Towson | AB4: =if('WR Formula'!N4 = 0, " ", 'WR Formula'!P4) -> 5.4 | AC4: ='WR Formula'!B4 -> Towson | AD4: ='WR Formula'!C4 -> N | AE4: ='TE Formula'!A4&", "&'TE Formula'!B4 -> Hayden Hansen, Florida | AL4: =if('TE Formula'!P4 = 0, " ", 'TE Formula'!R4) -> 4.5722222 | AM4: ='TE Formula'!B4 -> Florida | AN4: ='TE Formula'!C4 -> Y | AO4: ='OT Formula'!A4&", "&'OT Formula'!B4 -> Deandre Marshall, UTSA | AV4: =if('OT Formula'!N4 = 0, " ", 'OT Formula'!O4) -> 5.25 | AW4: ='OT Formula'!B4 -> UTSA | AX4: ='OT Formula'!C4 -> N | AY4: ='IOL Formula'!A4&", "&'IOL Formula'!B4 -> Johnny Dickson III, North Texas | BF4: =if('IOL Formula'!N4 = 0, " ", 'IOL Formula'!O4) -> 5.2333333 | BG4: ='IOL Formula'!B4 -> North Texas | BH4: ='IOL Formula'!C4 -> N
A5: ='QB Formula'!A5&", "&'QB Formula'!B5 -> DJ Lagway, Florida | H5: =if('QB Formula'!P5 = 0, " ", 'QB Formula'!P5) -> 5.2671429 | I5: ='QB Formula'!B5 -> Florida | J5: ='QB Formula'!C5 -> Y | K5: ='RB Formula'!A5&", "&'RB Formula'!B5 -> Xai'Shaun Edwards, Houston Christian | R5: =if('RB Formula'!R5 = 0, " ", 'RB Formula'!S5) -> 5.3375 | S5: ='RB Formula'!B5 -> Houston Christian | T5: ='RB Formula'!C5 -> Y | U5: ='WR Formula'!A5&", "&'WR Formula'!B5 -> Tyran Warren, Alcorn State | AB5: =if('WR Formula'!N5 = 0, " ", 'WR Formula'!P5) -> 5.3428571 | AC5: ='WR Formula'!B5 -> Alcorn State | AD5: ='WR Formula'!C5 -> N | AE5: ='TE Formula'!A5&", "&'TE Formula'!B5 -> Dallen Bentley, Utah | AL5: =if('TE Formula'!P5 = 0, " ", 'TE Formula'!R5) -> 4.5444444 | AM5: ='TE Formula'!B5 -> Utah | AN5: ='TE Formula'!C5 -> N | AO5: ='OT Formula'!A5&", "&'OT Formula'!B5 -> Caleb Lomu, Utah | AV5: =if('OT Formula'!N5 = 0, " ", 'OT Formula'!O5) -> 5.21 | AW5: ='OT Formula'!B5 -> Utah | AX5: ='OT Formula'!C5 -> N | AY5: ='IOL Formula'!A5&", "&'IOL Formula'!B5 -> Joep Engbers, Liberty | BF5: =if('IOL Formula'!N5 = 0, " ", 'IOL Formula'!O5) -> 5.2333333 | BG5: ='IOL Formula'!B5 -> Liberty | BH5: ='IOL Formula'!C5 -> N
A6: ='QB Formula'!A6&", "&'QB Formula'!B6 -> Drew Mestemaker, North Texas | H6: =if('QB Formula'!P6 = 0, " ", 'QB Formula'!P6) -> 5.2357143 | I6: ='QB Formula'!B6 -> North Texas | J6: ='QB Formula'!C6 -> Y | K6: ='RB Formula'!A6&", "&'RB Formula'!B6 -> Nykahi Davenport, USF | R6: =if('RB Formula'!R6 = 0, " ", 'RB Formula'!S6) -> 5.3375 | S6: ='RB Formula'!B6 -> USF | T6: ='RB Formula'!C6 -> N | U6: ='WR Formula'!A6&", "&'WR Formula'!B6 -> Jordan Garrison, Cal Poly | AB6: =if('WR Formula'!N6 = 0, " ", 'WR Formula'!P6) -> 5.2428571 | AC6: ='WR Formula'!B6 -> Cal Poly | AD6: ='WR Formula'!C6 -> N | AE6: ='TE Formula'!A6&", "&'TE Formula'!B6 -> Jett Carpenter, Nevada | AL6: =if('TE Formula'!P6 = 0, " ", 'TE Formula'!R6) -> 4.5055556 | AM6: ='TE Formula'!B6 -> Nevada | AN6: ='TE Formula'!C6 -> Y | AO6: ='OT Formula'!A6&", "&'OT Formula'!B6 -> Brayden Walton, Fresno State | AV6: =if('OT Formula'!N6 = 0, " ", 'OT Formula'!O6) -> 5.0433333 | AW6: ='OT Formula'!B6 -> Fresno State | AX6: ='OT Formula'!C6 -> N | AY6: ='IOL Formula'!A6&", "&'IOL Formula'!B6 -> Malachi Breland, Memphis | BF6: =if('IOL Formula'!N6 = 0, " ", 'IOL Formula'!O6) -> 5.1866667 | BG6: ='IOL Formula'!B6 -> Memphis | BH6: ='IOL Formula'!C6 -> N
A7: ='QB Formula'!A7&", "&'QB Formula'!B7 -> Jaden Craig, Harvard | H7: =if('QB Formula'!P7 = 0, " ", 'QB Formula'!P7) -> 5.1892857 | I7: ='QB Formula'!B7 -> Harvard | J7: ='QB Formula'!C7 -> Y | K7: ='RB Formula'!A7&", "&'RB Formula'!B7 -> Jimmyll Williams, Elon | R7: =if('RB Formula'!R7 = 0, " ", 'RB Formula'!S7) -> 5.3375 | S7: ='RB Formula'!B7 -> Elon | T7: ='RB Formula'!C7 -> Y | U7: ='WR Formula'!A7&", "&'WR Formula'!B7 -> Aidan Mizell, Florida | AB7: =if('WR Formula'!N7 = 0, " ", 'WR Formula'!P7) -> 5.2 | AC7: ='WR Formula'!B7 -> Florida | AD7: ='WR Formula'!C7 -> Y | AE7: ='TE Formula'!A7&", "&'TE Formula'!B7 -> Lacota Dippre, James Madison | AL7: =if('TE Formula'!P7 = 0, " ", 'TE Formula'!R7) -> 4.4222222 | AM7: ='TE Formula'!B7 -> James Madison | AN7: ='TE Formula'!C7 -> N | AO7: ='OT Formula'!A7&", "&'OT Formula'!B7 -> Grant Seagren, Oklahoma State | AV7: =if('OT Formula'!N7 = 0, " ", 'OT Formula'!O7) -> 5.0433333 | AW7: ='OT Formula'!B7 -> Oklahoma State | AX7: ='OT Formula'!C7 -> Y | AY7: ='IOL Formula'!A7&", "&'IOL Formula'!B7 -> Wes King, Wyoming | BF7: =if('IOL Formula'!N7 = 0, " ", 'IOL Formula'!O7) -> 5.1866667 | BG7: ='IOL Formula'!B7 -> Wyoming | BH7: ='IOL Formula'!C7 -> N
A8: ='QB Formula'!A8&", "&'QB Formula'!B8 -> Hauss Hejny, Oklahoma State | H8: =if('QB Formula'!P8 = 0, " ", 'QB Formula'!P8) -> 4.9971429 | I8: ='QB Formula'!B8 -> Oklahoma State | J8: ='QB Formula'!C8 -> N | K8: ='RB Formula'!A8&", "&'RB Formula'!B8 -> Dason Brooks, Idaho State | R8: =if('RB Formula'!R8 = 0, " ", 'RB Formula'!S8) -> 5.2791667 | S8: ='RB Formula'!B8 -> Idaho State | T8: ='RB Formula'!C8 -> N | U8: ='WR Formula'!A8&", "&'WR Formula'!B8 -> Donte Lee Jr., Liberty | AB8: =if('WR Formula'!N8 = 0, " ", 'WR Formula'!P8) -> 5.1857143 | AC8: ='WR Formula'!B8 -> Liberty | AD8: ='WR Formula'!C8 -> Y | AE8: ='TE Formula'!A8&", "&'TE Formula'!B8 -> Darrin Fugitt, Lindenwood | AL8: =if('TE Formula'!P8 = 0, " ", 'TE Formula'!R8) -> 4.4222222 | AM8: ='TE Formula'!B8 -> Lindenwood | AN8: ='TE Formula'!C8 -> Y | AO8: ='OT Formula'!A8&", "&'OT Formula'!B8 -> Miles McVay, North Carolina | AV8: =if('OT Formula'!N8 = 0, " ", 'OT Formula'!O8) -> 4.9966667 | AW8: ='OT Formula'!B8 -> North Carolina | AX8: ='OT Formula'!C8 -> Y | AY8: ='IOL Formula'!A8&", "&'IOL Formula'!B8 -> Aaron Fenimore, Liberty | BF8: =if('IOL Formula'!N8 = 0, " ", 'IOL Formula'!O8) -> 5.0233333 | BG8: ='IOL Formula'!B8 -> Liberty | BH8: ='IOL Formula'!C8 -> N
A9: ='QB Formula'!A9&", "&'QB Formula'!B9 -> Josh Hoover, TCU | H9: =if('QB Formula'!P9 = 0, " ", 'QB Formula'!P9) -> 4.9921429 | I9: ='QB Formula'!B9 -> TCU | J9: ='QB Formula'!C9 -> Y | K9: ='RB Formula'!A9&", "&'RB Formula'!B9 -> Landen Chambers, Cental Arkansas | R9: =if('RB Formula'!R9 = 0, " ", 'RB Formula'!S9) -> 5.2791667 | S9: ='RB Formula'!B9 -> Cental Arkansas | T9: ='RB Formula'!C9 -> Y | U9: ='WR Formula'!A9&", "&'WR Formula'!B9 -> AJ Wilson, UTSA | AB9: =if('WR Formula'!N9 = 0, " ", 'WR Formula'!P9) -> 5.1857143 | AC9: ='WR Formula'!B9 -> UTSA | AD9: ='WR Formula'!C9 -> N | AE9: ='TE Formula'!A9&", "&'TE Formula'!B9 -> Randy Pittman Jr, Florida State | AL9: =if('TE Formula'!P9 = 0, " ", 'TE Formula'!R9) -> 4.4222222 | AM9: ='TE Formula'!B9 -> Florida State | AN9: ='TE Formula'!C9 -> Y | AO9: ='OT Formula'!A9&", "&'OT Formula'!B9 -> Nate Hale, San Jose State | AV9: =if('OT Formula'!N9 = 0, " ", 'OT Formula'!O9) -> 4.8333333 | AW9: ='OT Formula'!B9 -> San Jose State | AX9: ='OT Formula'!C9 -> Y | AY9: ='IOL Formula'!A9&", "&'IOL Formula'!B9 -> Xavier Allen, Bucknell | BF9: =if('IOL Formula'!N9 = 0, " ", 'IOL Formula'!O9) -> 5.0233333 | BG9: ='IOL Formula'!B9 -> Bucknell | BH9: ='IOL Formula'!C9 -> Y
A10: ='QB Formula'!A10&", "&'QB Formula'!B10 -> Jax Leatherwood, SEMO | H10: =if('QB Formula'!P10 = 0, " ", 'QB Formula'!P10) -> 4.7957143 | I10: ='QB Formula'!B10 -> SEMO | J10: ='QB Formula'!C10 -> Y | K10: ='RB Formula'!A10&", "&'RB Formula'!B10 -> Nick Osho, Indiana State | R10: =if('RB Formula'!R10 = 0, " ", 'RB Formula'!S10) -> 5.2791667 | S10: ='RB Formula'!B10 -> Indiana State | T10: ='RB Formula'!C10 -> Y | U10: ='WR Formula'!A10&", "&'WR Formula'!B10 -> Jalen Jones, Alabama State | AB10: =if('WR Formula'!N10 = 0, " ", 'WR Formula'!P10) -> 5.1857143 | AC10: ='WR Formula'!B10 -> Alabama State | AD10: ='WR Formula'!C10 -> N | AE10: ='TE Formula'!A10&", "&'TE Formula'!B10 -> Ismael Smith Flores, UTRGV | AL10: =if('TE Formula'!P10 = 0, " ", 'TE Formula'!R10) -> 4.3 | AM10: ='TE Formula'!B10 -> UTRGV | AN10: ='TE Formula'!C10 -> Y | AO10: ='OT Formula'!A10&", "&'OT Formula'!B10 -> Henry Tabansi, Buffalo | AV10: =if('OT Formula'!N10 = 0, " ", 'OT Formula'!O10) -> 4.7866667 | AW10: ='OT Formula'!B10 -> Buffalo | AX10: ='OT Formula'!C10 -> N | AY10: ='IOL Formula'!A10&", "&'IOL Formula'!B10 -> Nathan Elu, Oregon State | BF10: =if('IOL Formula'!N10 = 0, " ", 'IOL Formula'!O10) -> 4.9766667 | BG10: ='IOL Formula'!B10 -> Oregon State | BH10: ='IOL Formula'!C10 -> N
A11: ='QB Formula'!A11&", "&'QB Formula'!B11 -> Colton Joseph, Old Dominion | H11: =if('QB Formula'!P11 = 0, " ", 'QB Formula'!P11) -> 4.7771429 | I11: ='QB Formula'!B11 -> Old Dominion | J11: ='QB Formula'!C11 -> Y | K11: ='RB Formula'!A11&", "&'RB Formula'!B11 -> Carson Groseck, Gardner-Webb | R11: =if('RB Formula'!R11 = 0, " ", 'RB Formula'!S11) -> 5.0166667 | S11: ='RB Formula'!B11 -> Gardner-Webb | T11: ='RB Formula'!C11 -> Y | U11: ='WR Formula'!A11&", "&'WR Formula'!B11 -> Nick Marsh, Michigan State | AB11: =if('WR Formula'!N11 = 0, " ", 'WR Formula'!P11) -> 5.1857143 | AC11: ='WR Formula'!B11 -> Michigan State | AD11: ='WR Formula'!C11 -> Y | AE11: ='TE Formula'!A11&", "&'TE Formula'!B11 -> Kristian Ingman, Portland State | AL11: =if('TE Formula'!P11 = 0, " ", 'TE Formula'!R11) -> 4.2833333 | AM11: ='TE Formula'!B11 -> Portland State | AN11: ='TE Formula'!C11 -> N | AO11: ='OT Formula'!A11&", "&'OT Formula'!B11 -> Rex Johnsen, Wyoming | AV11: =if('OT Formula'!N11 = 0, " ", 'OT Formula'!O11) -> 4.7866667 | AW11: ='OT Formula'!B11 -> Wyoming | AX11: ='OT Formula'!C11 -> N | AY11: ='IOL Formula'!A11&", "&'IOL Formula'!B11 -> Michael Mokofisi, Utah | BF11: =if('IOL Formula'!N11 = 0, " ", 'IOL Formula'!O11) -> 4.97 | BG11: ='IOL Formula'!B11 -> Utah | BH11: ='IOL Formula'!C11 -> N
A12: ='QB Formula'!A12&", "&'QB Formula'!B12 -> Devon Dampier, Utah | H12: =if('QB Formula'!P12 = 0, " ", 'QB Formula'!P12) -> 4.5742857 | I12: ='QB Formula'!B12 -> Utah | J12: ='QB Formula'!C12 -> N | K12: ='RB Formula'!A12&", "&'RB Formula'!B12 -> Justin Montgomery, Presbyterian | R12: =if('RB Formula'!R12 = 0, " ", 'RB Formula'!S12) -> 5.0166667 | S12: ='RB Formula'!B12 -> Presbyterian | T12: ='RB Formula'!C12 -> Y | U12: ='WR Formula'!A12&", "&'WR Formula'!B12 -> Larenzo Fenner, South Dakota | AB12: =if('WR Formula'!N12 = 0, " ", 'WR Formula'!P12) -> 5.1142857 | AC12: ='WR Formula'!B12 -> South Dakota | AD12: ='WR Formula'!C12 -> N | AE12: ='TE Formula'!A12&", "&'TE Formula'!B12 -> Jayvontay Conner, East Carolina | AL12: =if('TE Formula'!P12 = 0, " ", 'TE Formula'!R12) -> 4.2277778 | AM12: ='TE Formula'!B12 -> East Carolina | AN12: ='TE Formula'!C12 -> Y | AO12: ='OT Formula'!A12&", "&'OT Formula'!B12 -> Ethan Green, Cincinnati | AV12: =if('OT Formula'!N12 = 0, " ", 'OT Formula'!O12) -> 4.7866667 | AW12: ='OT Formula'!B12 -> Cincinnati | AX12: ='OT Formula'!C12 -> Y | AY12: ='IOL Formula'!A12&", "&'IOL Formula'!B12 -> Dylan Sikorski, Oregon State | BF12: =if('IOL Formula'!N12 = 0, " ", 'IOL Formula'!O12) -> 4.8133333 | BG12: ='IOL Formula'!B12 -> Oregon State | BH12: ='IOL Formula'!C12 -> Y
A13: ='QB Formula'!A13&", "&'QB Formula'!B13 -> Byrd Ficklin, Utah | H13: =if('QB Formula'!P13 = 0, " ", 'QB Formula'!P13) -> 4.5392857 | I13: ='QB Formula'!B13 -> Utah | J13: ='QB Formula'!C13 -> N | K13: ='RB Formula'!A13&", "&'RB Formula'!B13 -> Ofa Mataele, Western Michigan | R13: =if('RB Formula'!R13 = 0, " ", 'RB Formula'!S13) -> 4.9583333 | S13: ='RB Formula'!B13 -> Western Michigan | T13: ='RB Formula'!C13 -> N | U13: ='WR Formula'!A13&", "&'WR Formula'!B13 -> Jayshon Platt, FAU | AB13: =if('WR Formula'!N13 = 0, " ", 'WR Formula'!P13) -> 5.0428571 | AC13: ='WR Formula'!B13 -> FAU | AD13: ='WR Formula'!C13 -> Y | AE13: ='TE Formula'!A13&", "&'TE Formula'!B13 -> Mason Williams, Ohio | AL13: =if('TE Formula'!P13 = 0, " ", 'TE Formula'!R13) -> 4.2277778 | AM13: ='TE Formula'!B13 -> Ohio | AN13: ='TE Formula'!C13 -> N | AO13: ='OT Formula'!A13&", "&'OT Formula'!B13 -> Reese Baker, Tulane | AV13: =if('OT Formula'!N13 = 0, " ", 'OT Formula'!O13) -> 4.7433333 | AW13: ='OT Formula'!B13 -> Tulane | AX13: ='OT Formula'!C13 -> N | AY13: ='IOL Formula'!A13&", "&'IOL Formula'!B13 -> Cayden Sweatt, App State | BF13: =if('IOL Formula'!N13 = 0, " ", 'IOL Formula'!O13) -> 4.7033333 | BG13: ='IOL Formula'!B13 -> App State | BH13: ='IOL Formula'!C13 -> N
A14: ='QB Formula'!A14&", "&'QB Formula'!B14 -> Grant Jordan, UMass | H14: =if('QB Formula'!P14 = 0, " ", 'QB Formula'!P14) -> 4.5021429 | I14: ='QB Formula'!B14 -> UMass | J14: ='QB Formula'!C14 -> Y | K14: ='RB Formula'!A14&", "&'RB Formula'!B14 -> LJ Phillips, South Dakota | R14: =if('RB Formula'!R14 = 0, " ", 'RB Formula'!S14) -> 4.9583333 | S14: ='RB Formula'!B14 -> South Dakota | T14: ='RB Formula'!C14 -> Y | U14: ='WR Formula'!A14&", "&'WR Formula'!B14 -> Ernest Campbell, Sacramento State | AB14: =if('WR Formula'!N14 = 0, " ", 'WR Formula'!P14) -> 5.0285714 | AC14: ='WR Formula'!B14 -> Sacramento State | AD14: ='WR Formula'!C14 -> Y | AE14: ='TE Formula'!A14&", "&'TE Formula'!B14 -> Levi Linowes, Brown | AL14: =if('TE Formula'!P14 = 0, " ", 'TE Formula'!R14) -> 4.0611111 | AM14: ='TE Formula'!B14 -> Brown | AN14: ='TE Formula'!C14 -> N | AO14: ='OT Formula'!A14&", "&'OT Formula'!B14 -> Netinho Olivieri, Penn | AV14: =if('OT Formula'!N14 = 0, " ", 'OT Formula'!O14) -> 4.7433333 | AW14: ='OT Formula'!B14 -> Penn | AX14: ='OT Formula'!C14 -> Y | AY14: ='IOL Formula'!A14&", "&'IOL Formula'!B14 -> Shalik Hubbard, Monmouth | BF14: =if('IOL Formula'!N14 = 0, " ", 'IOL Formula'!O14) -> 4.7033333 | BG14: ='IOL Formula'!B14 -> Monmouth | BH14: ='IOL Formula'!C14 -> Y
... A31: ='QB Formula'!A31&", "&'QB Formula'!B31 -> Amari Odom, Kennesaw State | H31: =if('QB Formula'!P31 = 0, " ", 'QB Formula'!P31) -> 4.04309 | I31: ='QB Formula'!B31 -> Kennesaw State | J31: ='QB Formula'!C31 -> N | K31: ='RB Formula'!A31&", "&'RB Formula'!B31 -> Clay Thevenin, Louisiana Tech | R31: =if('RB Formula'!R31 = 0, " ", 'RB Formula'!S31) -> 4.375 | S31: ='RB Formula'!B31 -> Louisiana Tech | T31: ='RB Formula'!C31 -> N | U31: ='WR Formula'!A31&", "&'WR Formula'!B31 -> Yannick Smith, ECU | AB31: =if('WR Formula'!N31 = 0, " ", 'WR Formula'!P31) -> 4.7571429 | AC31: ='WR Formula'!B31 -> ECU | AD31: ='WR Formula'!C31 -> Y | AE31: ='TE Formula'!A31&", "&'TE Formula'!B31 -> Fisher Clements, Northern Colorado | AL31: =if('TE Formula'!P31 = 0, " ", 'TE Formula'!R31) -> 3.5888889 | AM31: ='TE Formula'!B31 -> Northern Colorado | AN31: ='TE Formula'!C31 -> Y | AO31: ='OT Formula'!A31&", "&'OT Formula'!B31 -> Everett Small, Eastern Michigan | AV31: =if('OT Formula'!N31 = 0, " ", 'OT Formula'!O31) -> 4.2766667 | AW31: ='OT Formula'!B31 -> Eastern Michigan | AX31: ='OT Formula'!C31 -> N | AY31: ='IOL Formula'!A31&", "&'IOL Formula'!B31 -> Malachi Preciado, South Alabama | BF31: =if('IOL Formula'!N31 = 0, " ", 'IOL Formula'!O31) -> 3.98 | BG31: ='IOL Formula'!B31 -> South Alabama | BH31: ='IOL Formula'!C31 -> Y
A32: ='QB Formula'!A32&", "&'QB Formula'!B32 -> Coulter Cleland, Davidson | H32: =if('QB Formula'!P32 = 0, " ", 'QB Formula'!P32) -> 4.0171429 | J32: ='QB Formula'!C32 -> Y | K32: ='RB Formula'!A32&", "&'RB Formula'!B32 -> Terron Kellman, Wyoming | R32: =if('RB Formula'!R32 = 0, " ", 'RB Formula'!S32) -> 4.375 | S32: ='RB Formula'!B32 -> Wyoming | T32: ='RB Formula'!C32 -> Y | U32: ='WR Formula'!A32&", "&'WR Formula'!B32 -> Omarion Miller, Colorado | AB32: =if('WR Formula'!N32 = 0, " ", 'WR Formula'!P32) -> 4.7571429 | AC32: ='WR Formula'!B32 -> Colorado | AD32: ='WR Formula'!C32 -> Y | AE32: ='TE Formula'!A32&", "&'TE Formula'!B32 -> Marcus Middleton, Monmouth | AL32: =if('TE Formula'!P32 = 0, " ", 'TE Formula'!R32) -> 3.55 | AM32: ='TE Formula'!B32 -> Monmouth | AN32: ='TE Formula'!C32 -> N | AO32: ='OT Formula'!A32&", "&'OT Formula'!B32 -> Ashton Tripp, Washington State | AV32: =if('OT Formula'!N32 = 0, " ", 'OT Formula'!O32) -> 4.2766667 | AW32: ='OT Formula'!B32 -> Washington State | AX32: ='OT Formula'!C32 -> N | AY32: ='IOL Formula'!A32&", "&'IOL Formula'!B32 -> Steven Demboski, Delaware | BF32: =if('IOL Formula'!N32 = 0, " ", 'IOL Formula'!O32) -> 3.9333333 | BG32: ='IOL Formula'!B32 -> Delaware | BH32: ='IOL Formula'!C32 -> N
A33: ='QB Formula'!A33&", "&'QB Formula'!B33 -> Nick Josifek, Idaho | H33: =if('QB Formula'!P33 = 0, " ", 'QB Formula'!P33) -> 3.8771429 | J33: ='QB Formula'!C33 -> Y | K33: ='RB Formula'!A33&", "&'RB Formula'!B33 -> Wayne Knight, James Madison | R33: =if('RB Formula'!R33 = 0, " ", 'RB Formula'!S33) -> 4.375 | S33: ='RB Formula'!B33 -> James Madison | T33: ='RB Formula'!C33 -> N | U33: ='WR Formula'!A33&", "&'WR Formula'!B33 -> Tony Freeman, Washington State | AB33: =if('WR Formula'!N33 = 0, " ", 'WR Formula'!P33) -> 4.7428571 | AC33: ='WR Formula'!B33 -> Washington State | AD33: ='WR Formula'!C33 -> Y | AE33: ='TE Formula'!A33&", "&'TE Formula'!B33 -> Eli Finley, Louisiana Tech | AL33: =if('TE Formula'!P33 = 0, " ", 'TE Formula'!R33) -> 3.3111111 | AM33: ='TE Formula'!B33 -> Louisiana Tech | AN33: ='TE Formula'!C33 -> N | AO33: ='OT Formula'!A33&", "&'OT Formula'!B33 -> Johnnie Brown III, Georgia Southern | AV33: =if('OT Formula'!N33 = 0, " ", 'OT Formula'!O33) -> 4.2766667 | AW33: ='OT Formula'!B33 -> Georgia Southern | AX33: ='OT Formula'!C33 -> N | AY33: ='IOL Formula'!A33&", "&'IOL Formula'!B33 -> Joseph Harbert, San Jose State | BF33: =if('IOL Formula'!N33 = 0, " ", 'IOL Formula'!O33) -> 3.7233333 | BG33: ='IOL Formula'!B33 -> San Jose State | BH33: ='IOL Formula'!C33 -> N
A34: ='QB Formula'!A34&", "&'QB Formula'!B34 -> Harrison Burch, Kentucky Wesleyan | H34: =if('QB Formula'!P34 = 0, " ", 'QB Formula'!P34) -> 3.8771429 | J34: ='QB Formula'!C34 -> Y | K34: ='RB Formula'!A34&", "&'RB Formula'!B34 -> Lucky Sutton, San Diego State | R34: =if('RB Formula'!R34 = 0, " ", 'RB Formula'!S34) -> 4.375 | S34: ='RB Formula'!B34 -> San Diego State | T34: ='RB Formula'!C34 -> N | U34: ='WR Formula'!A34&", "&'WR Formula'!B34 -> Jared Richardson, UPenn | AB34: =if('WR Formula'!N34 = 0, " ", 'WR Formula'!P34) -> 4.6857143 | AC34: ='WR Formula'!B34 -> UPenn | AD34: ='WR Formula'!C34 -> Y | AE34: ='TE Formula'!A34&", "&'TE Formula'!B34 -> Hyatt Timosciek, Tenessee Martin | AL34: =if('TE Formula'!P34 = 0, " ", 'TE Formula'!R34) -> 3.3111111 | AM34: ='TE Formula'!B34 -> Tenessee Martin | AN34: ='TE Formula'!C34 -> Y | AO34: ='OT Formula'!A34&", "&'OT Formula'!B34 -> Riley McGehee, Arkansas State | AV34: =if('OT Formula'!N34 = 0, " ", 'OT Formula'!O34) -> 4.2766667 | AW34: ='OT Formula'!B34 -> Arkansas State | AX34: ='OT Formula'!C34 -> N | AY34: ='IOL Formula'!A34&", "&'IOL Formula'!B34 -> Jack Leyrer, Stanford | BF34: =if('IOL Formula'!N34 = 0, " ", 'IOL Formula'!O34) -> 3.7233333 | BG34: ='IOL Formula'!B34 -> Stanford | BH34: ='IOL Formula'!C34 -> Y
A35: ='QB Formula'!A35&", "&'QB Formula'!B35 -> Nicco Marchiol, West Virginia | H35: =if('QB Formula'!P35 = 0, " ", 'QB Formula'!P35) -> 3.8771429 | J35: ='QB Formula'!C35 -> Y | K35: ='RB Formula'!A35&", "&'RB Formula'!B35 -> Nick Herman, Drake | R35: =if('RB Formula'!R35 = 0, " ", 'RB Formula'!S35) -> 4.375 | S35: ='RB Formula'!B35 -> Drake | T35: ='RB Formula'!C35 -> N | U35: ='WR Formula'!A35&", "&'WR Formula'!B35 -> Kyan Mason, Akron | AB35: =if('WR Formula'!N35 = 0, " ", 'WR Formula'!P35) -> 4.6714286 | AC35: ='WR Formula'!B35 -> Akron | AD35: ='WR Formula'!C35 -> N | AE35: ='TE Formula'!A35&", "&'TE Formula'!B35 -> Dylan Magazu, Elon | AL35: =if('TE Formula'!P35 = 0, " ", 'TE Formula'!R35) -> 3.2555556 | AM35: ='TE Formula'!B35 -> Elon | AN35: ='TE Formula'!C35 -> N | AO35: ='OT Formula'!A35&", "&'OT Formula'!B35 -> Eric Smith, Miami OH | AV35: =if('OT Formula'!N35 = 0, " ", 'OT Formula'!O35) -> 4.0666667 | AW35: ='OT Formula'!B35 -> Miami OH | AX35: ='OT Formula'!C35 -> N | AY35: ='IOL Formula'!A35&", "&'IOL Formula'!B35 -> Carter Sweazie, James Madison | BF35: =if('IOL Formula'!N35 = 0, " ", 'IOL Formula'!O35) -> 3.6066667 | BG35: ='IOL Formula'!B35 -> James Madison | BH35: ='IOL Formula'!C35 -> N
A36: ='QB Formula'!A36&", "&'QB Formula'!B36 -> Davin Wydner, West Georgia | H36: =if('QB Formula'!P36 = 0, " ", 'QB Formula'!P36) -> 3.7959471 | J36: ='QB Formula'!C36 -> Y | K36: ='RB Formula'!A36&", "&'RB Formula'!B36 -> Sutton Smith, Memphis | R36: =if('RB Formula'!R36 = 0, " ", 'RB Formula'!S36) -> 4.375 | S36: ='RB Formula'!B36 -> Memphis | T36: ='RB Formula'!C36 -> N | U36: ='WR Formula'!A36&", "&'WR Formula'!B36 -> Kyri Shoals, San Jose State | AB36: =if('WR Formula'!N36 = 0, " ", 'WR Formula'!P36) -> 4.6285714 | AC36: ='WR Formula'!B36 -> San Jose State | AD36: ='WR Formula'!C36 -> Y | AE36: ='TE Formula'!A36&", "&'TE Formula'!B36 -> Ryder Kurtz, Cornell | AL36: =if('TE Formula'!P36 = 0, " ", 'TE Formula'!R36) -> 3.1611111 | AM36: ='TE Formula'!B36 -> Cornell | AN36: ='TE Formula'!C36 -> N | AO36: ='OT Formula'!A36&", "&'OT Formula'!B36 -> Hayes Creel, Southern Miss | AV36: =if('OT Formula'!N36 = 0, " ", 'OT Formula'!O36) -> 4.0666667 | AW36: ='OT Formula'!B36 -> Southern Miss | AX36: ='OT Formula'!C36 -> N | AY36: ='IOL Formula'!A36&", "&'IOL Formula'!B36 -> Nate Bledsoe, Rice | BF36: =if('IOL Formula'!N36 = 0, " ", 'IOL Formula'!O36) -> 3.5966667 | BG36: ='IOL Formula'!B36 -> Rice | BH36: ='IOL Formula'!C36 -> N
A37: ='QB Formula'!A37&", "&'QB Formula'!B37 -> Drew Devillier, Rice | H37: =if('QB Formula'!P37 = 0, " ", 'QB Formula'!P37) -> 3.7809471 | J37: ='QB Formula'!C37 -> Y | K37: ='RB Formula'!A37&", "&'RB Formula'!B37 -> Joshua Dye, Southern Utah | R37: =if('RB Formula'!R37 = 0, " ", 'RB Formula'!S37) -> 4.375 | S37: ='RB Formula'!B37 -> Southern Utah | T37: ='RB Formula'!C37 -> Y | U37: ='WR Formula'!A37&", "&'WR Formula'!B37 -> Nik McMillan, Buffalo | AB37: =if('WR Formula'!N37 = 0, " ", 'WR Formula'!P37) -> 4.6 | AC37: ='WR Formula'!B37 -> Buffalo | AD37: ='WR Formula'!C37 -> Y | AE37: ='TE Formula'!A37&", "&'TE Formula'!B37 -> Sean McElwain, William and Mary | AL37: =if('TE Formula'!P37 = 0, " ", 'TE Formula'!R37) -> 2.9833333 | AM37: ='TE Formula'!B37 -> William and Mary | AN37: ='TE Formula'!C37 -> N | AO37: ='OT Formula'!A37&", "&'OT Formula'!B37 -> Daughtry Richardson, FAU | AV37: =if('OT Formula'!N37 = 0, " ", 'OT Formula'!O37) -> 4.0666667 | AW37: ='OT Formula'!B37 -> FAU | AX37: ='OT Formula'!C37 -> Y | AY37: ='IOL Formula'!A37&", "&'IOL Formula'!B37 -> Tristian Smith, Arkansas State | BF37: =if('IOL Formula'!N37 = 0, " ", 'IOL Formula'!O37) -> 3.3933333 | BG37: ='IOL Formula'!B37 -> Arkansas State | BH37: ='IOL Formula'!C37 -> N
A38: ='QB Formula'!A38&", "&'QB Formula'!B38 -> Brandon Tennison, UTSA | H38: =if('QB Formula'!P38 = 0, " ", 'QB Formula'!P38) -> 3.7009471 | J38: ='QB Formula'!C38 -> N | K38: ='RB Formula'!A38&", "&'RB Formula'!B38 -> Carter Vargas, UC Davis | R38: =if('RB Formula'!R38 = 0, " ", 'RB Formula'!S38) -> 4.375 | S38: ='RB Formula'!B38 -> UC Davis | T38: ='RB Formula'!C38 -> Y | U38: ='WR Formula'!A38&", "&'WR Formula'!B38 -> Omari Hayes, Tulane | AB38: =if('WR Formula'!N38 = 0, " ", 'WR Formula'!P38) -> 4.6 | AC38: ='WR Formula'!B38 -> Tulane | AD38: ='WR Formula'!C38 -> N | AE38: ='TE Formula'!A38&", "&'TE Formula'!B38 -> Gavin Harris, New Mexico State | AL38: =if('TE Formula'!P38 = 0, " ", 'TE Formula'!R38) -> 2.8111111 | AM38: ='TE Formula'!B38 -> New Mexico State | AN38: ='TE Formula'!C38 -> Y | AO38: ='OT Formula'!A38&", "&'OT Formula'!B38 -> Evan Malcore, NIU | AV38: =if('OT Formula'!N38 = 0, " ", 'OT Formula'!O38) -> 4.0633333 | AW38: ='OT Formula'!B38 -> NIU | AX38: ='OT Formula'!C38 -> Y | AY38: ='IOL Formula'!A38&", "&'IOL Formula'!B38 -> Kadin Lynch, William & Mary | BF38: =if('IOL Formula'!N38 = 0, " ", 'IOL Formula'!O38) -> 3.3033333 | BG38: ='IOL Formula'!B38 -> William & Mary | BH38: ='IOL Formula'!C38 -> Y
A39: ='QB Formula'!A39&", "&'QB Formula'!B39 -> Liam O'Brien, Penn | H39: =if('QB Formula'!P39 = 0, " ", 'QB Formula'!P39) -> 3.6857143 | J39: ='QB Formula'!C39 -> Y | K39: ='RB Formula'!A39&", "&'RB Formula'!B39 -> Landan Harris, Sam Houston | R39: =if('RB Formula'!R39 = 0, " ", 'RB Formula'!S39) -> 4.3166667 | S39: ='RB Formula'!B39 -> Sam Houston | T39: ='RB Formula'!C39 -> N | U39: ='WR Formula'!A39&", "&'WR Formula'!B39 -> Darren Morris, Southern | AB39: =if('WR Formula'!N39 = 0, " ", 'WR Formula'!P39) -> 4.6 | AC39: ='WR Formula'!B39 -> Southern | AD39: ='WR Formula'!C39 -> Y | AE39: ='TE Formula'!A39&", "&'TE Formula'!B39 -> Nader Chirchi, UConn | AL39: =if('TE Formula'!P39 = 0, " ", 'TE Formula'!R39) | AM39: ='TE Formula'!B39 -> UConn | AN39: ='TE Formula'!C39 -> N | AO39: ='OT Formula'!A39&", "&'OT Formula'!B39 -> Mark Robinson, UTEP | AV39: =if('OT Formula'!N39 = 0, " ", 'OT Formula'!O39) -> 4.0633333 | AW39: ='OT Formula'!B39 -> UTEP | AX39: ='OT Formula'!C39 -> Y | AY39: ='IOL Formula'!A39&", "&'IOL Formula'!B39 -> Aitor Urionabarrenechea, Colorado State | BF39: =if('IOL Formula'!N39 = 0, " ", 'IOL Formula'!O39) -> 3.2366667 | BG39: ='IOL Formula'!B39 -> Colorado State | BH39: ='IOL Formula'!C39 -> Y
A40: ='QB Formula'!A40&", "&'QB Formula'!B40 -> Jared Lockhart, Jackson State | H40: =if('QB Formula'!P40 = 0, " ", 'QB Formula'!P40) -> 3.68309 | J40: ='QB Formula'!C40 -> N | K40: ='RB Formula'!A40&", "&'RB Formula'!B40 -> Will Henderson III, UTSA | R40: =if('RB Formula'!R40 = 0, " ", 'RB Formula'!S40) -> 4.3166667 | S40: ='RB Formula'!B40 -> UTSA | T40: ='RB Formula'!C40 -> N | U40: ='WR Formula'!A40&", "&'WR Formula'!B40 -> Kareem Burke, Arkansas Pine Bluff | AB40: =if('WR Formula'!N40 = 0, " ", 'WR Formula'!P40) -> 4.5714286 | AC40: ='WR Formula'!B40 -> Arkansas Pine Bluff | AD40: ='WR Formula'!C40 -> Y | AE40: ='TE Formula'!A40&", "&'TE Formula'!B40 -> Bryan Henry, Abilene Christian | AL40: =if('TE Formula'!P40 = 0, " ", 'TE Formula'!R40) | AM40: ='TE Formula'!B40 -> Abilene Christian | AN40: ='TE Formula'!C40 -> N | AO40: ='OT Formula'!A40&", "&'OT Formula'!B40 -> Brandon Sneh, UAB | AV40: =if('OT Formula'!N40 = 0, " ", 'OT Formula'!O40) -> 4.02 | AW40: ='OT Formula'!B40 -> UAB | AX40: ='OT Formula'!C40 -> Y | AY40: ='IOL Formula'!A40&", "&'IOL Formula'!B40 -> Patrick Valent, Rice | BF40: =if('IOL Formula'!N40 = 0, " ", 'IOL Formula'!O40) -> 3.1833333 | BG40: ='IOL Formula'!B40 -> Rice | BH40: ='IOL Formula'!C40 -> N
A41: ='QB Formula'!A41&", "&'QB Formula'!B41 -> Carson Camp, Southeastern Louisiana | H41: =if('QB Formula'!P41 = 0, " ", 'QB Formula'!P41) -> 3.6314286 | J41: ='QB Formula'!C41 -> Y | K41: ='RB Formula'!A41&", "&'RB Formula'!B41 -> Eli Gillman, Montana | R41: =if('RB Formula'!R41 = 0, " ", 'RB Formula'!S41) -> 4.3166667 | S41: ='RB Formula'!B41 -> Montana | T41: ='RB Formula'!C41 -> N | U41: ='WR Formula'!A41&", "&'WR Formula'!B41 -> Nico Brown, Yale | AB41: =if('WR Formula'!N41 = 0, " ", 'WR Formula'!P41) -> 4.5571429 | AC41: ='WR Formula'!B41 -> Yale | AD41: ='WR Formula'!C41 -> Y | AE41: ='TE Formula'!A41&", "&'TE Formula'!B41 -> Peyton Strickland, New Hampshire | AL41: =if('TE Formula'!P41 = 0, " ", 'TE Formula'!R41) | AM41: ='TE Formula'!B41 -> New Hampshire | AN41: ='TE Formula'!C41 -> Y | AO41: ='OT Formula'!A41&", "&'OT Formula'!B41 -> Derek Osman, Harvard | AV41: =if('OT Formula'!N41 = 0, " ", 'OT Formula'!O41) -> 4.02 | AW41: ='OT Formula'!B41 -> Harvard | AX41: ='OT Formula'!C41 -> Y | AY41: ='IOL Formula'!A41&", "&'IOL Formula'!B41 -> Adam Lepkowski, UAB | BF41: =if('IOL Formula'!N41 = 0, " ", 'IOL Formula'!O41) -> 2.9266667 | BG41: ='IOL Formula'!B41 -> UAB | BH41: ='IOL Formula'!C41 -> N
A42: ='QB Formula'!A42&", "&'QB Formula'!B42 -> Brayden Fowler-Nicolosi, Colorado State | H42: =if('QB Formula'!P42 = 0, " ", 'QB Formula'!P42) -> 3.5788043 | J42: ='QB Formula'!C42 -> Y | K42: ='RB Formula'!A42&", "&'RB Formula'!B42 -> Sawyer Seidl, North Dakota | R42: =if('RB Formula'!R42 = 0, " ", 'RB Formula'!S42) -> 4.3166667 | S42: ='RB Formula'!B42 -> North Dakota | T42: ='RB Formula'!C42 -> Y | U42: ='WR Formula'!A42&", "&'WR Formula'!B42 -> Chris Marshall, Boise State | AB42: =if('WR Formula'!N42 = 0, " ", 'WR Formula'!P42) -> 4.5571429 | AC42: ='WR Formula'!B42 -> Boise State | AD42: ='WR Formula'!C42 -> N | AE42: ='TE Formula'!A42&", "&'TE Formula'!B42 -> , | AL42: =if('TE Formula'!P42 = 0, " ", 'TE Formula'!R42) | AM42: ='TE Formula'!B42 | AN42: ='TE Formula'!C42 | AO42: ='OT Formula'!A42&", "&'OT Formula'!B42 -> Maasai King, Akron | AV42: =if('OT Formula'!N42 = 0, " ", 'OT Formula'!O42) -> 4.02 | AW42: ='OT Formula'!B42 -> Akron | AX42: ='OT Formula'!C42 -> Y | AY42: ='IOL Formula'!A42&", "&'IOL Formula'!B42 -> Vincent Fiacable, FAU | BF42: =if('IOL Formula'!N42 = 0, " ", 'IOL Formula'!O42) | BG42: ='IOL Formula'!B42 -> FAU | BH42: ='IOL Formula'!C42 -> N
A43: ='QB Formula'!A43&", "&'QB Formula'!B43 -> Johnny Weber, SEMO | H43: =if('QB Formula'!P43 = 0, " ", 'QB Formula'!P43) -> 3.4285714 | J43: ='QB Formula'!C43 -> N | K43: ='RB Formula'!A43&", "&'RB Formula'!B43 -> Scottre Humphrey, New Mexico | R43: =if('RB Formula'!R43 = 0, " ", 'RB Formula'!S43) -> 4.0833333 | S43: ='RB Formula'!B43 -> New Mexico | T43: ='RB Formula'!C43 -> N | U43: ='WR Formula'!A43&", "&'WR Formula'!B43 -> Sam Milligan, Bucknell | AB43: =if('WR Formula'!N43 = 0, " ", 'WR Formula'!P43) -> 4.5285714 | AC43: ='WR Formula'!B43 -> Bucknell | AD43: ='WR Formula'!C43 -> N | AE43: ='TE Formula'!A43&", "&'TE Formula'!B43 -> , | AL43: =if('TE Formula'!P43 = 0, " ", 'TE Formula'!R43) | AM43: ='TE Formula'!B43 | AN43: ='TE Formula'!C43 | AO43: ='OT Formula'!A43&", "&'OT Formula'!B43 -> Reggie Jackson, Jacksonville State | AV43: =if('OT Formula'!N43 = 0, " ", 'OT Formula'!O43) -> 4.0166667 | AW43: ='OT Formula'!B43 -> Jacksonville State | AX43: ='OT Formula'!C43 -> Y | AY43: ='IOL Formula'!A43&", "&'IOL Formula'!B43 -> Zach Greenberg, James Madison | BF43: =if('IOL Formula'!N43 = 0, " ", 'IOL Formula'!O43) | BG43: ='IOL Formula'!B43 -> James Madison | BH43: ='IOL Formula'!C43 -> N
... A53: ='QB Formula'!A53&", "&'QB Formula'!B53 -> , | H53: =if('QB Formula'!P53 = 0, " ", 'QB Formula'!P53) | J53: ='QB Formula'!C53 | K53: ='RB Formula'!A53&", "&'RB Formula'!B53 -> Marlon Gunn, East Carolina | R53: =if('RB Formula'!R53 = 0, " ", 'RB Formula'!S53) -> 3.9958333 | S53: ='RB Formula'!B53 -> East Carolina | T53: ='RB Formula'!C53 -> N | U53: ='WR Formula'!A53&", "&'WR Formula'!B53 -> Beau Sparks, Texas State | AB53: =if('WR Formula'!N53 = 0, " ", 'WR Formula'!P53) -> 4.4 | AC53: ='WR Formula'!B53 -> Texas State | AD53: ='WR Formula'!C53 -> N | AE53: ='TE Formula'!A53&", "&'TE Formula'!B53 -> , | AL53: =if('TE Formula'!P53 = 0, " ", 'TE Formula'!R53) | AM53: ='TE Formula'!B53 | AN53: ='TE Formula'!C53 | AO53: ='OT Formula'!A53&", "&'OT Formula'!B53 -> Greg Nunnery, Southern Miss | AV53: =if('OT Formula'!N53 = 0, " ", 'OT Formula'!O53) | AW53: ='OT Formula'!B53 -> Southern Miss | AX53: ='OT Formula'!C53 -> N | AY53: ='IOL Formula'!A53&", "&'IOL Formula'!B53 -> , | BF53: =if('IOL Formula'!N53 = 0, " ", 'IOL Formula'!O53) | BG53: ='IOL Formula'!B53 | BH53: ='IOL Formula'!C53
A54: ='QB Formula'!A54&", "&'QB Formula'!B54 -> , | H54: =if('QB Formula'!P54 = 0, " ", 'QB Formula'!P54) | J54: ='QB Formula'!C54 | K54: ='RB Formula'!A54&", "&'RB Formula'!B54 -> Kaden Shields-Dutton, Florida Atlantic | R54: =if('RB Formula'!R54 = 0, " ", 'RB Formula'!S54) -> 3.9958333 | S54: ='RB Formula'!B54 -> Florida Atlantic | T54: ='RB Formula'!C54 -> N | U54: ='WR Formula'!A54&", "&'WR Formula'!B54 -> Tommy McIntosh, Central Michigan | AB54: =if('WR Formula'!N54 = 0, " ", 'WR Formula'!P54) -> 4.4 | AC54: ='WR Formula'!B54 -> Central Michigan | AD54: ='WR Formula'!C54 -> N | AE54: ='TE Formula'!A54&", "&'TE Formula'!B54 -> , | AL54: =if('TE Formula'!P54 = 0, " ", 'TE Formula'!R54) | AN54: ='TE Formula'!C54 | AO54: ='OT Formula'!A54&", "&'OT Formula'!B54 -> Jack Foster, Nevada | AV54: =if('OT Formula'!N54 = 0, " ", 'OT Formula'!O54) | AW54: ='OT Formula'!B54 -> Nevada | AX54: ='OT Formula'!C54 -> N | AY54: ='IOL Formula'!A54&", "&'IOL Formula'!B54 -> , | BF54: =if('IOL Formula'!N54 = 0, " ", 'IOL Formula'!O54) | BG54: ='IOL Formula'!B54 | BH54: ='IOL Formula'!C54
A55: ='QB Formula'!A55&", "&'QB Formula'!B55 -> , | H55: =if('QB Formula'!P55 = 0, " ", 'QB Formula'!P55) | J55: ='QB Formula'!C55 | K55: ='RB Formula'!A55&", "&'RB Formula'!B55 -> Bryan Jackson, USC | R55: =if('RB Formula'!R55 = 0, " ", 'RB Formula'!S55) -> 3.9958333 | S55: ='RB Formula'!B55 -> USC | T55: ='RB Formula'!C55 -> Y | U55: ='WR Formula'!A55&", "&'WR Formula'!B55 -> Larry Simmons, Utah | AB55: =if('WR Formula'!N55 = 0, " ", 'WR Formula'!P55) -> 4.4 | AC55: ='WR Formula'!B55 -> Utah | AD55: ='WR Formula'!C55 -> N | AE55: ='TE Formula'!A55&", "&'TE Formula'!B55 -> , | AL55: =if('TE Formula'!P55 = 0, " ", 'TE Formula'!R55) | AN55: ='TE Formula'!C55 | AO55: ='OT Formula'!A55&", "&'OT Formula'!B55 -> Sully Burns, Texas State | AV55: =if('OT Formula'!N55 = 0, " ", 'OT Formula'!O55) | AW55: ='OT Formula'!B55 -> Texas State | AX55: ='OT Formula'!C55 -> N | AY55: ='IOL Formula'!A55&", "&'IOL Formula'!B55 -> , | BF55: =if('IOL Formula'!N55 = 0, " ", 'IOL Formula'!O55) | BG55: ='IOL Formula'!B55 | BH55: ='IOL Formula'!C55
A56: ='QB Formula'!A56&", "&'QB Formula'!B56 -> , | H56: =if('QB Formula'!P56 = 0, " ", 'QB Formula'!P56) | J56: ='QB Formula'!C56 | K56: ='RB Formula'!A56&", "&'RB Formula'!B56 -> Jordan Gant, Akron | R56: =if('RB Formula'!R56 = 0, " ", 'RB Formula'!S56) -> 3.7916667 | S56: ='RB Formula'!B56 -> Akron | T56: ='RB Formula'!C56 -> N | U56: ='WR Formula'!A56&", "&'WR Formula'!B56 -> Danny Scudero, San Jose State | AB56: =if('WR Formula'!N56 = 0, " ", 'WR Formula'!P56) -> 4.3571429 | AC56: ='WR Formula'!B56 -> San Jose State | AD56: ='WR Formula'!C56 -> Y | AE56: ='TE Formula'!A56&", "&'TE Formula'!B56 -> , | AL56: =if('TE Formula'!P56 = 0, " ", 'TE Formula'!R56) | AN56: ='TE Formula'!C56 | AO56: ='OT Formula'!A56&", "&'OT Formula'!B56 -> Nikola Milovac, Kennesaw State | AV56: =if('OT Formula'!N56 = 0, " ", 'OT Formula'!O56) | AW56: ='OT Formula'!B56 -> Kennesaw State | AX56: ='OT Formula'!C56 -> N | AY56: ='IOL Formula'!A56&", "&'IOL Formula'!B56 -> , | BF56: =if('IOL Formula'!N56 = 0, " ", 'IOL Formula'!O56) | BG56: ='IOL Formula'!B56 | BH56: ='IOL Formula'!C56
A57: ='QB Formula'!A57&", "&'QB Formula'!B57 -> , | H57: =if('QB Formula'!P57 = 0, " ", 'QB Formula'!P57) | J57: ='QB Formula'!C57 | K57: ='RB Formula'!A57&", "&'RB Formula'!B57 -> Anthony Carrie, FIU | R57: =if('RB Formula'!R57 = 0, " ", 'RB Formula'!S57) -> 3.7333333 | S57: ='RB Formula'!B57 -> FIU | T57: ='RB Formula'!C57 -> N | U57: ='WR Formula'!A57&", "&'WR Formula'!B57 -> Jeremiah Koger, USF | AB57: =if('WR Formula'!N57 = 0, " ", 'WR Formula'!P57) -> 4.3285714 | AC57: ='WR Formula'!B57 -> USF | AD57: ='WR Formula'!C57 -> N | AE57: ='TE Formula'!A57&", "&'TE Formula'!B57 -> , | AL57: =if('TE Formula'!P57 = 0, " ", 'TE Formula'!R57) | AN57: ='TE Formula'!C57 | AO57: ='OT Formula'!A57&", "&'OT Formula'!B57 -> Tyler Lawrence, New Mexico | AV57: =if('OT Formula'!N57 = 0, " ", 'OT Formula'!O57) | AW57: ='OT Formula'!B57 -> New Mexico | AX57: ='OT Formula'!C57 -> N | AY57: ='IOL Formula'!A57&", "&'IOL Formula'!B57 -> , | BF57: =if('IOL Formula'!N57 = 0, " ", 'IOL Formula'!O57) | BG57: ='IOL Formula'!B57 | BH57: ='IOL Formula'!C57
A58: ='QB Formula'!A58&", "&'QB Formula'!B58 -> , | H58: =if('QB Formula'!P58 = 0, " ", 'QB Formula'!P58) | J58: ='QB Formula'!C58 | K58: ='RB Formula'!A58&", "&'RB Formula'!B58 -> Kente Edwards, Lafayette | R58: =if('RB Formula'!R58 = 0, " ", 'RB Formula'!S58) -> 3.7333333 | S58: ='RB Formula'!B58 -> Lafayette | T58: ='RB Formula'!C58 -> Y | U58: ='WR Formula'!A58&", "&'WR Formula'!B58 -> Malik Knight, Western Carolina | AB58: =if('WR Formula'!N58 = 0, " ", 'WR Formula'!P58) -> 4.3285714 | AC58: ='WR Formula'!B58 -> Western Carolina | AD58: ='WR Formula'!C58 -> Y | AE58: ='TE Formula'!A58&", "&'TE Formula'!B58 -> , | AL58: =if('TE Formula'!P58 = 0, " ", 'TE Formula'!R58) | AN58: ='TE Formula'!C58 | AO58: ='OT Formula'!A58&", "&'OT Formula'!B58 -> Joseph Simmons, James Madison | AV58: =if('OT Formula'!N58 = 0, " ", 'OT Formula'!O58) | AW58: ='OT Formula'!B58 -> James Madison | AX58: ='OT Formula'!C58 -> N | AY58: ='IOL Formula'!A58&", "&'IOL Formula'!B58 -> , | BF58: =if('IOL Formula'!N58 = 0, " ", 'IOL Formula'!O58) | BG58: ='IOL Formula'!B58 | BH58: ='IOL Formula'!C58
A59: ='QB Formula'!A59&", "&'QB Formula'!B59 -> , | H59: =if('QB Formula'!P59 = 0, " ", 'QB Formula'!P59) | J59: ='QB Formula'!C59 | K59: ='RB Formula'!A59&", "&'RB Formula'!B59 -> Ja'Vin Simpkins, Coastal Carolina | R59: =if('RB Formula'!R59 = 0, " ", 'RB Formula'!S59) -> 3.7333333 | S59: ='RB Formula'!B59 -> Coastal Carolina | T59: ='RB Formula'!C59 -> N | U59: ='WR Formula'!A59&", "&'WR Formula'!B59 -> Xayvion Noland, UTRGV | AB59: =if('WR Formula'!N59 = 0, " ", 'WR Formula'!P59) -> 4.3142857 | AC59: ='WR Formula'!B59 -> UTRGV | AD59: ='WR Formula'!C59 -> Y | AE59: ='TE Formula'!A59&", "&'TE Formula'!B59 -> , | AL59: =if('TE Formula'!P59 = 0, " ", 'TE Formula'!R59) | AN59: ='TE Formula'!C59 | AO59: ='OT Formula'!A59&", "&'OT Formula'!B59 -> Austin Boyd, UNLV | AV59: =if('OT Formula'!N59 = 0, " ", 'OT Formula'!O59) | AW59: ='OT Formula'!B59 -> UNLV | AX59: ='OT Formula'!C59 -> N | AY59: ='IOL Formula'!A59&", "&'IOL Formula'!B59 -> , | BF59: =if('IOL Formula'!N59 = 0, " ", 'IOL Formula'!O59) | BG59: ='IOL Formula'!B59 | BH59: ='IOL Formula'!C59
A60: ='QB Formula'!A60&", "&'QB Formula'!B60 -> , | H60: =if('QB Formula'!P60 = 0, " ", 'QB Formula'!P60) | J60: ='QB Formula'!C60 | K60: ='RB Formula'!A60&", "&'RB Formula'!B60 -> Jordan Fisher, UC Davis | R60: =if('RB Formula'!R60 = 0, " ", 'RB Formula'!S60) -> 3.7333333 | S60: ='RB Formula'!B60 -> UC Davis | T60: ='RB Formula'!C60 -> N | U60: ='WR Formula'!A60&", "&'WR Formula'!B60 -> Brock Spalding, ECU | AB60: =if('WR Formula'!N60 = 0, " ", 'WR Formula'!P60) -> 4.2571429 | AC60: ='WR Formula'!B60 -> ECU | AD60: ='WR Formula'!C60 -> N | AE60: ='TE Formula'!A60&", "&'TE Formula'!B60 -> , | AL60: =if('TE Formula'!P60 = 0, " ", 'TE Formula'!R60) | AN60: ='TE Formula'!C60 | AO60: ='OT Formula'!A60&", "&'OT Formula'!B60 -> Noah Rosahac, Delaware | AV60: =if('OT Formula'!N60 = 0, " ", 'OT Formula'!O60) | AW60: ='OT Formula'!B60 -> Delaware | AX60: ='OT Formula'!C60 -> N | AY60: ='IOL Formula'!A60&", "&'IOL Formula'!B60 -> , | BF60: =if('IOL Formula'!N60 = 0, " ", 'IOL Formula'!O60) | BG60: ='IOL Formula'!B60 | BH60: ='IOL Formula'!C60
A61: ='QB Formula'!A61&", "&'QB Formula'!B61 -> , | H61: =if('QB Formula'!P61 = 0, " ", 'QB Formula'!P61) | J61: ='QB Formula'!C61 | K61: ='RB Formula'!A61&", "&'RB Formula'!B61 -> Rovaughn Banks Jr, Abilene Christian | R61: =if('RB Formula'!R61 = 0, " ", 'RB Formula'!S61) -> 3.7333333 | S61: ='RB Formula'!B61 -> Abilene Christian | T61: ='RB Formula'!C61 -> N | U61: ='WR Formula'!A61&", "&'WR Formula'!B61 -> Jordan Napier, San Diego State | AB61: =if('WR Formula'!N61 = 0, " ", 'WR Formula'!P61) -> 4.2571429 | AC61: ='WR Formula'!B61 -> San Diego State | AD61: ='WR Formula'!C61 -> N | AE61: ='TE Formula'!A61&", "&'TE Formula'!B61 -> , | AL61: =if('TE Formula'!P61 = 0, " ", 'TE Formula'!R61) | AN61: ='TE Formula'!C61 | AO61: ='OT Formula'!A61&", "&'OT Formula'!B61 -> Zach Cochnauer, Nevada | AV61: =if('OT Formula'!N61 = 0, " ", 'OT Formula'!O61) | AW61: ='OT Formula'!B61 -> Nevada | AX61: ='OT Formula'!C61 -> N | AY61: ='IOL Formula'!A61&", "&'IOL Formula'!B61 -> , | BF61: =if('IOL Formula'!N61 = 0, " ", 'IOL Formula'!O61) | BG61: ='IOL Formula'!B61 | BH61: ='IOL Formula'!C61
A62: ='QB Formula'!A62&", "&'QB Formula'!B62 -> , | H62: =if('QB Formula'!P62 = 0, " ", 'QB Formula'!P62) | J62: ='QB Formula'!C62 | K62: ='RB Formula'!A62&", "&'RB Formula'!B62 -> TJ Thomas Jr., Elon | R62: =if('RB Formula'!R62 = 0, " ", 'RB Formula'!S62) -> 3.5 | S62: ='RB Formula'!B62 -> Elon | T62: ='RB Formula'!C62 -> N | U62: ='WR Formula'!A62&", "&'WR Formula'!B62 -> Kam Perry, Miami OH | AB62: =if('WR Formula'!N62 = 0, " ", 'WR Formula'!P62) -> 4.2428571 | AC62: ='WR Formula'!B62 -> Miami OH | AD62: ='WR Formula'!C62 -> Y | AE62: ='TE Formula'!A62&", "&'TE Formula'!B62 -> , | AL62: =if('TE Formula'!P62 = 0, " ", 'TE Formula'!R62) | AN62: ='TE Formula'!C62 | AO62: ='OT Formula'!A62&", "&'OT Formula'!B62 -> , | AV62: =if('OT Formula'!N62 = 0, " ", 'OT Formula'!O62) | AW62: ='OT Formula'!B62 | AX62: ='OT Formula'!C62 | AY62: ='IOL Formula'!A62&", "&'IOL Formula'!B62 -> , | BF62: =if('IOL Formula'!N62 = 0, " ", 'IOL Formula'!O62) | BG62: ='IOL Formula'!B62 | BH62: ='IOL Formula'!C62
A63: ='QB Formula'!A63&", "&'QB Formula'!B63 -> , | H63: =if('QB Formula'!P63 = 0, " ", 'QB Formula'!P63) | J63: ='QB Formula'!C63 | K63: ='RB Formula'!A63&", "&'RB Formula'!B63 -> Trequan Jones, Old Dominion | R63: =if('RB Formula'!R63 = 0, " ", 'RB Formula'!S63) -> 3.4708333 | S63: ='RB Formula'!B63 -> Old Dominion | T63: ='RB Formula'!C63 -> Y | U63: ='WR Formula'!A63&", "&'WR Formula'!B63 -> Landon Ellis, James Madison | AB63: =if('WR Formula'!N63 = 0, " ", 'WR Formula'!P63) -> 4.2428571 | AC63: ='WR Formula'!B63 -> James Madison | AD63: ='WR Formula'!C63 -> N | AE63: ='TE Formula'!A63&", "&'TE Formula'!B63 -> , | AL63: =if('TE Formula'!P63 = 0, " ", 'TE Formula'!R63) | AN63: ='TE Formula'!C63 | AO63: ='OT Formula'!A63&", "&'OT Formula'!B63 -> , | AV63: =if('OT Formula'!N63 = 0, " ", 'OT Formula'!O63) | AW63: ='OT Formula'!B63 | AX63: ='OT Formula'!C63 | AY63: ='IOL Formula'!A63&", "&'IOL Formula'!B63 -> , | BF63: =if('IOL Formula'!N63 = 0, " ", 'IOL Formula'!O63) | BG63: ='IOL Formula'!B63 | BH63: ='IOL Formula'!C63
A64: ='QB Formula'!A64&", "&'QB Formula'!B64 -> , | H64: =if('QB Formula'!P64 = 0, " ", 'QB Formula'!P64) | J64: ='QB Formula'!C64 | K64: ='RB Formula'!A64&", "&'RB Formula'!B64 -> Lamar Spurling, Buffalo | R64: =if('RB Formula'!R64 = 0, " ", 'RB Formula'!S64) -> 3.4125 | S64: ='RB Formula'!B64 -> Buffalo | T64: ='RB Formula'!C64 -> N | U64: ='WR Formula'!A64&", "&'WR Formula'!B64 -> Chris Dawn Jr, Texas State | AB64: =if('WR Formula'!N64 = 0, " ", 'WR Formula'!P64) -> 4.2428571 | AC64: ='WR Formula'!B64 -> Texas State | AD64: ='WR Formula'!C64 -> N | AE64: ='TE Formula'!A64&", "&'TE Formula'!B64 -> , | AL64: =if('TE Formula'!P64 = 0, " ", 'TE Formula'!R64) | AN64: ='TE Formula'!C64 | AO64: ='OT Formula'!A64&", "&'OT Formula'!B64 -> , | AV64: =if('OT Formula'!N64 = 0, " ", 'OT Formula'!O64) | AW64: ='OT Formula'!B64 | AX64: ='OT Formula'!C64 | AY64: ='IOL Formula'!A64&", "&'IOL Formula'!B64 -> , | BF64: =if('IOL Formula'!N64 = 0, " ", 'IOL Formula'!O64) | BG64: ='IOL Formula'!B64 | BH64: ='IOL Formula'!C64
A65: ='QB Formula'!A65&", "&'QB Formula'!B65 -> , | H65: =if('QB Formula'!P65 = 0, " ", 'QB Formula'!P65) | J65: ='QB Formula'!C65 | K65: ='RB Formula'!A65&", "&'RB Formula'!B65 -> Gerald Modest, Wofford | R65: =if('RB Formula'!R65 = 0, " ", 'RB Formula'!S65) -> 3.4125 | S65: ='RB Formula'!B65 -> Wofford | T65: ='RB Formula'!C65 -> Y | U65: ='WR Formula'!A65&", "&'WR Formula'!B65 -> Moussa Barry, Western Kentucky | AB65: =if('WR Formula'!N65 = 0, " ", 'WR Formula'!P65) -> 4.2428571 | AC65: ='WR Formula'!B65 -> Western Kentucky | AD65: ='WR Formula'!C65 -> N | AE65: ='TE Formula'!A65&", "&'TE Formula'!B65 -> , | AL65: =if('TE Formula'!P65 = 0, " ", 'TE Formula'!R65) | AN65: ='TE Formula'!C65 | AO65: ='OT Formula'!A65&", "&'OT Formula'!B65 -> , | AV65: =if('OT Formula'!N65 = 0, " ", 'OT Formula'!O65) | AW65: ='OT Formula'!B65 | AX65: ='OT Formula'!C65 | AY65: ='IOL Formula'!A65&", "&'IOL Formula'!B65 -> , | BF65: =if('IOL Formula'!N65 = 0, " ", 'IOL Formula'!O65) | BG65: ='IOL Formula'!B65 | BH65: ='IOL Formula'!C65
... A188: ='QB Formula'!A188&", "&'QB Formula'!B188 -> , | H188: =if('QB Formula'!P188 = 0, " ", 'QB Formula'!P188) | J188: ='QB Formula'!C188 | K188: ='RB Formula'!A188&", "&'RB Formula'!B188 -> , | R188: =if('RB Formula'!R188 = 0, " ", 'RB Formula'!S188) | S188: ='RB Formula'!B188 | T188: ='RB Formula'!C188 | U188: ='WR Formula'!A188&", "&'WR Formula'!B188 -> Preston Bird, Samford | AB188: =if('WR Formula'!N188 = 0, " ", 'WR Formula'!P188) -> 2.8142857 | AC188: ='WR Formula'!B188 -> Samford | AD188: ='WR Formula'!C188 -> N | AE188: ='TE Formula'!A188&", "&'TE Formula'!B188 -> , | AL188: =if('TE Formula'!P188 = 0, " ", 'TE Formula'!R188) | AN188: ='TE Formula'!C188 | AO188: ='OT Formula'!A188&", "&'OT Formula'!B188 -> , | AV188: =if('OT Formula'!N188 = 0, " ", 'OT Formula'!O188) | AW188: ='OT Formula'!B188 | AX188: ='OT Formula'!C188 | AY188: ='IOL Formula'!A188&", "&'IOL Formula'!B188 -> , | BF188: =if('IOL Formula'!N188 = 0, " ", 'IOL Formula'!O188) | BG188: ='IOL Formula'!B188 | BH188: ='IOL Formula'!C188
A189: ='QB Formula'!A189&", "&'QB Formula'!B189 -> , | H189: =if('QB Formula'!P189 = 0, " ", 'QB Formula'!P189) | J189: ='QB Formula'!C189 | K189: ='RB Formula'!A189&", "&'RB Formula'!B189 -> , | R189: =if('RB Formula'!R189 = 0, " ", 'RB Formula'!S189) | S189: ='RB Formula'!B189 | T189: ='RB Formula'!C189 | U189: ='WR Formula'!A189&", "&'WR Formula'!B189 -> Troy Worrell, Fordham | AB189: =if('WR Formula'!N189 = 0, " ", 'WR Formula'!P189) -> 2.8142857 | AD189: ='WR Formula'!C189 -> N | AE189: ='TE Formula'!A189&", "&'TE Formula'!B189 -> , | AL189: =if('TE Formula'!P189 = 0, " ", 'TE Formula'!R189) | AN189: ='TE Formula'!C189 | AO189: ='OT Formula'!A189&", "&'OT Formula'!B189 -> , | AV189: =if('OT Formula'!N189 = 0, " ", 'OT Formula'!O189) | AW189: ='OT Formula'!B189 | AX189: ='OT Formula'!C189 | AY189: ='IOL Formula'!A189&", "&'IOL Formula'!B189 -> , | BF189: =if('IOL Formula'!N189 = 0, " ", 'IOL Formula'!O189) | BG189: ='IOL Formula'!B189 | BH189: ='IOL Formula'!C189
A190: ='QB Formula'!A190&", "&'QB Formula'!B190 -> , | H190: =if('QB Formula'!P190 = 0, " ", 'QB Formula'!P190) | J190: ='QB Formula'!C190 | K190: ='RB Formula'!A190&", "&'RB Formula'!B190 -> , | R190: =if('RB Formula'!R190 = 0, " ", 'RB Formula'!S190) | S190: ='RB Formula'!B190 | T190: ='RB Formula'!C190 | U190: ='WR Formula'!A190&", "&'WR Formula'!B190 -> Vinson Davis III, Southern Illinois | AB190: =if('WR Formula'!N190 = 0, " ", 'WR Formula'!P190) -> 2.8142857 | AD190: ='WR Formula'!C190 -> N | AE190: ='TE Formula'!A190&", "&'TE Formula'!B190 -> , | AL190: =if('TE Formula'!P190 = 0, " ", 'TE Formula'!R190) | AN190: ='TE Formula'!C190 | AO190: ='OT Formula'!A190&", "&'OT Formula'!B190 -> , | AV190: =if('OT Formula'!N190 = 0, " ", 'OT Formula'!O190) | AW190: ='OT Formula'!B190 | AX190: ='OT Formula'!C190 | AY190: ='IOL Formula'!A190&", "&'IOL Formula'!B190 -> , | BF190: =if('IOL Formula'!N190 = 0, " ", 'IOL Formula'!O190) | BG190: ='IOL Formula'!B190 | BH190: ='IOL Formula'!C190
A191: ='QB Formula'!A191&", "&'QB Formula'!B191 -> , | H191: =if('QB Formula'!P191 = 0, " ", 'QB Formula'!P191) | J191: ='QB Formula'!C191 | K191: ='RB Formula'!A191&", "&'RB Formula'!B191 -> , | R191: =if('RB Formula'!R191 = 0, " ", 'RB Formula'!S191) | S191: ='RB Formula'!B191 | T191: ='RB Formula'!C191 | U191: ='WR Formula'!A191&", "&'WR Formula'!B191 -> Greg Gaines III, Rhode Island | AB191: =if('WR Formula'!N191 = 0, " ", 'WR Formula'!P191) -> 2.6857143 | AD191: ='WR Formula'!C191 -> Y | AE191: ='TE Formula'!A191&", "&'TE Formula'!B191 -> , | AL191: =if('TE Formula'!P191 = 0, " ", 'TE Formula'!R191) | AN191: ='TE Formula'!C191 | AO191: ='OT Formula'!A191&", "&'OT Formula'!B191 -> , | AV191: =if('OT Formula'!N191 = 0, " ", 'OT Formula'!O191) | AW191: ='OT Formula'!B191 | AX191: ='OT Formula'!C191 | AY191: ='IOL Formula'!A191&", "&'IOL Formula'!B191 -> , | BF191: =if('IOL Formula'!N191 = 0, " ", 'IOL Formula'!O191) | BG191: ='IOL Formula'!B191 | BH191: ='IOL Formula'!C191
A192: ='QB Formula'!A192&", "&'QB Formula'!B192 -> , | H192: =if('QB Formula'!P192 = 0, " ", 'QB Formula'!P192) | J192: ='QB Formula'!C192 | K192: ='RB Formula'!A192&", "&'RB Formula'!B192 -> , | R192: =if('RB Formula'!R192 = 0, " ", 'RB Formula'!S192) | S192: ='RB Formula'!B192 | T192: ='RB Formula'!C192 | U192: ='WR Formula'!A192&", "&'WR Formula'!B192 -> Dallas Dudley, Abilene Christian | AB192: =if('WR Formula'!N192 = 0, " ", 'WR Formula'!P192) | AD192: ='WR Formula'!C192 -> N | AE192: ='TE Formula'!A192&", "&'TE Formula'!B192 -> , | AL192: =if('TE Formula'!P192 = 0, " ", 'TE Formula'!R192) | AN192: ='TE Formula'!C192 | AO192: ='OT Formula'!A192&", "&'OT Formula'!B192 -> , | AV192: =if('OT Formula'!N192 = 0, " ", 'OT Formula'!O192) | AW192: ='OT Formula'!B192 | AX192: ='OT Formula'!C192 | AY192: ='IOL Formula'!A192&", "&'IOL Formula'!B192 -> , | BF192: =if('IOL Formula'!N192 = 0, " ", 'IOL Formula'!O192) | BG192: ='IOL Formula'!B192 | BH192: ='IOL Formula'!C192
A193: ='QB Formula'!A193&", "&'QB Formula'!B193 -> , | H193: =if('QB Formula'!P193 = 0, " ", 'QB Formula'!P193) | J193: ='QB Formula'!C193 | K193: ='RB Formula'!A193&", "&'RB Formula'!B193 -> , | R193: =if('RB Formula'!R193 = 0, " ", 'RB Formula'!S193) | S193: ='RB Formula'!B193 | T193: ='RB Formula'!C193 | U193: ='WR Formula'!A193&", "&'WR Formula'!B193 -> Jaden Robinson, Austin Peay | AB193: =if('WR Formula'!N193 = 0, " ", 'WR Formula'!P193) | AD193: ='WR Formula'!C193 -> N | AE193: ='TE Formula'!A193&", "&'TE Formula'!B193 -> , | AL193: =if('TE Formula'!P193 = 0, " ", 'TE Formula'!R193) | AN193: ='TE Formula'!C193 | AO193: ='OT Formula'!A193&", "&'OT Formula'!B193 -> , | AV193: =if('OT Formula'!N193 = 0, " ", 'OT Formula'!O193) | AW193: ='OT Formula'!B193 | AX193: ='OT Formula'!C193 | AY193: ='IOL Formula'!A193&", "&'IOL Formula'!B193 -> , | BF193: =if('IOL Formula'!N193 = 0, " ", 'IOL Formula'!O193) | BG193: ='IOL Formula'!B193 | BH193: ='IOL Formula'!C193
A194: ='QB Formula'!A194&", "&'QB Formula'!B194 -> , | H194: =if('QB Formula'!P194 = 0, " ", 'QB Formula'!P194) | J194: ='QB Formula'!C194 | K194: ='RB Formula'!A194&", "&'RB Formula'!B194 -> , | R194: =if('RB Formula'!R194 = 0, " ", 'RB Formula'!S194) | S194: ='RB Formula'!B194 | T194: ='RB Formula'!C194 | U194: ='WR Formula'!A194&", "&'WR Formula'!B194 -> Tucker Holloway, Virginia Tech | AB194: =if('WR Formula'!N194 = 0, " ", 'WR Formula'!P194) | AD194: ='WR Formula'!C194 -> Y | AE194: ='TE Formula'!A194&", "&'TE Formula'!B194 -> , | AL194: =if('TE Formula'!P194 = 0, " ", 'TE Formula'!R194) | AN194: ='TE Formula'!C194 | AO194: ='OT Formula'!A194&", "&'OT Formula'!B194 -> , | AV194: =if('OT Formula'!N194 = 0, " ", 'OT Formula'!O194) | AW194: ='OT Formula'!B194 | AX194: ='OT Formula'!C194 | AY194: ='IOL Formula'!A194&", "&'IOL Formula'!B194 -> , | BF194: =if('IOL Formula'!N194 = 0, " ", 'IOL Formula'!O194) | BG194: ='IOL Formula'!B194 | BH194: ='IOL Formula'!C194
A195: ='QB Formula'!A195&", "&'QB Formula'!B195 -> , | H195: =if('QB Formula'!P195 = 0, " ", 'QB Formula'!P195) | J195: ='QB Formula'!C195 | K195: ='RB Formula'!A195&", "&'RB Formula'!B195 -> , | R195: =if('RB Formula'!R195 = 0, " ", 'RB Formula'!S195) | S195: ='RB Formula'!B195 | T195: ='RB Formula'!C195 | U195: ='WR Formula'!A195&", "&'WR Formula'!B195 -> Landon Sides, North Texas | AB195: =if('WR Formula'!N195 = 0, " ", 'WR Formula'!P195) | AD195: ='WR Formula'!C195 -> N | AE195: ='TE Formula'!A195&", "&'TE Formula'!B195 -> , | AL195: =if('TE Formula'!P195 = 0, " ", 'TE Formula'!R195) | AN195: ='TE Formula'!C195 | AO195: ='OT Formula'!A195&", "&'OT Formula'!B195 -> , | AV195: =if('OT Formula'!N195 = 0, " ", 'OT Formula'!O195) | AW195: ='OT Formula'!B195 | AX195: ='OT Formula'!C195 | AY195: ='IOL Formula'!A195&", "&'IOL Formula'!B195 -> , | BF195: =if('IOL Formula'!N195 = 0, " ", 'IOL Formula'!O195) | BG195: ='IOL Formula'!B195 | BH195: ='IOL Formula'!C195
A196: ='QB Formula'!A196&", "&'QB Formula'!B196 -> , | H196: =if('QB Formula'!P196 = 0, " ", 'QB Formula'!P196) | J196: ='QB Formula'!C196 | K196: ='RB Formula'!A196&", "&'RB Formula'!B196 -> , | R196: =if('RB Formula'!R196 = 0, " ", 'RB Formula'!S196) | S196: ='RB Formula'!B196 | T196: ='RB Formula'!C196 | U196: ='WR Formula'!A196&", "&'WR Formula'!B196 -> Jayvonne Dillard, North Carolina A&T | AB196: =if('WR Formula'!N196 = 0, " ", 'WR Formula'!P196) | AD196: ='WR Formula'!C196 -> N | AE196: ='TE Formula'!A196&", "&'TE Formula'!B196 -> , | AL196: =if('TE Formula'!P196 = 0, " ", 'TE Formula'!R196) | AN196: ='TE Formula'!C196 | AO196: ='OT Formula'!A196&", "&'OT Formula'!B196 -> , | AV196: =if('OT Formula'!N196 = 0, " ", 'OT Formula'!O196) | AW196: ='OT Formula'!B196 | AX196: ='OT Formula'!C196 | AY196: ='IOL Formula'!A196&", "&'IOL Formula'!B196 -> , | BF196: =if('IOL Formula'!N196 = 0, " ", 'IOL Formula'!O196) | BG196: ='IOL Formula'!B196 | BH196: ='IOL Formula'!C196
A197: ='QB Formula'!A197&", "&'QB Formula'!B197 -> , | H197: =if('QB Formula'!P197 = 0, " ", 'QB Formula'!P197) | J197: ='QB Formula'!C197 | K197: ='RB Formula'!A197&", "&'RB Formula'!B197 -> , | R197: =if('RB Formula'!R197 = 0, " ", 'RB Formula'!S197) | S197: ='RB Formula'!B197 | T197: ='RB Formula'!C197 | U197: ='WR Formula'!A197&", "&'WR Formula'!B197 -> Tavahri Groves, Albany | AB197: =if('WR Formula'!N197 = 0, " ", 'WR Formula'!P197) | AD197: ='WR Formula'!C197 -> N | AE197: ='TE Formula'!A197&", "&'TE Formula'!B197 -> , | AL197: =if('TE Formula'!P197 = 0, " ", 'TE Formula'!R197) | AN197: ='TE Formula'!C197 | AO197: ='OT Formula'!A197&", "&'OT Formula'!B197 -> , | AV197: =if('OT Formula'!N197 = 0, " ", 'OT Formula'!O197) | AW197: ='OT Formula'!B197 | AX197: ='OT Formula'!C197 | AY197: ='IOL Formula'!A197&", "&'IOL Formula'!B197 -> , | BF197: =if('IOL Formula'!N197 = 0, " ", 'IOL Formula'!O197) | BG197: ='IOL Formula'!B197 | BH197: ='IOL Formula'!C197
A198: ='QB Formula'!A198&", "&'QB Formula'!B198 -> , | H198: =if('QB Formula'!P198 = 0, " ", 'QB Formula'!P198) | J198: ='QB Formula'!C198 | K198: ='RB Formula'!A198&", "&'RB Formula'!B198 -> , | R198: =if('RB Formula'!R198 = 0, " ", 'RB Formula'!S198) | S198: ='RB Formula'!B198 | T198: ='RB Formula'!C198 | U198: ='WR Formula'!A198&", "&'WR Formula'!B198 -> Landyn Backey, Elon | AB198: =if('WR Formula'!N198 = 0, " ", 'WR Formula'!P198) | AD198: ='WR Formula'!C198 -> N | AE198: ='TE Formula'!A198&", "&'TE Formula'!B198 -> , | AL198: =if('TE Formula'!P198 = 0, " ", 'TE Formula'!R198) | AN198: ='TE Formula'!C198 | AO198: ='OT Formula'!A198&", "&'OT Formula'!B198 -> , | AV198: =if('OT Formula'!N198 = 0, " ", 'OT Formula'!O198) | AW198: ='OT Formula'!B198 | AX198: ='OT Formula'!C198 | AY198: ='IOL Formula'!A198&", "&'IOL Formula'!B198 -> , | BF198: =if('IOL Formula'!N198 = 0, " ", 'IOL Formula'!O198) | BG198: ='IOL Formula'!B198 | BH198: ='IOL Formula'!C198
A199: ='QB Formula'!A199&", "&'QB Formula'!B199 -> , | H199: =if('QB Formula'!P199 = 0, " ", 'QB Formula'!P199) | J199: ='QB Formula'!C199 | K199: ='RB Formula'!A199&", "&'RB Formula'!B199 -> , | R199: =if('RB Formula'!R199 = 0, " ", 'RB Formula'!S199) | S199: ='RB Formula'!B199 | T199: ='RB Formula'!C199 | U199: ='WR Formula'!A199&", "&'WR Formula'!B199 -> Cam'ron Lacy, Middle Tennessee | AB199: =if('WR Formula'!N199 = 0, " ", 'WR Formula'!P199) | AD199: ='WR Formula'!C199 -> N | AE199: ='TE Formula'!A199&", "&'TE Formula'!B199 -> , | AL199: =if('TE Formula'!P199 = 0, " ", 'TE Formula'!R199) | AN199: ='TE Formula'!C199 | AO199: ='OT Formula'!A199&", "&'OT Formula'!B199 -> , | AV199: =if('OT Formula'!N199 = 0, " ", 'OT Formula'!O199) | AW199: ='OT Formula'!B199 | AX199: ='OT Formula'!C199 | AY199: ='IOL Formula'!A199&", "&'IOL Formula'!B199 -> , | BF199: =if('IOL Formula'!N199 = 0, " ", 'IOL Formula'!O199) | BG199: ='IOL Formula'!B199 | BH199: ='IOL Formula'!C199
A200: ='QB Formula'!A200&", "&'QB Formula'!B200 -> , | H200: =if('QB Formula'!P200 = 0, " ", 'QB Formula'!P200) | J200: ='QB Formula'!C200 | K200: ='RB Formula'!A200&", "&'RB Formula'!B200 -> , | R200: =if('RB Formula'!R200 = 0, " ", 'RB Formula'!S200) | S200: ='RB Formula'!B200 | T200: ='RB Formula'!C200 | U200: ='WR Formula'!A200&", "&'WR Formula'!B200 -> PJ Johnson III, New Mexico State | AB200: =if('WR Formula'!N200 = 0, " ", 'WR Formula'!P200) | AD200: ='WR Formula'!C200 -> N | AE200: ='TE Formula'!A200&", "&'TE Formula'!B200 -> , | AL200: =if('TE Formula'!P200 = 0, " ", 'TE Formula'!R200) | AN200: ='TE Formula'!C200 | AO200: ='OT Formula'!A200&", "&'OT Formula'!B200 -> , | AV200: =if('OT Formula'!N200 = 0, " ", 'OT Formula'!O200) | AW200: ='OT Formula'!B200 | AX200: ='OT Formula'!C200 | AY200: ='IOL Formula'!A200&", "&'IOL Formula'!B200 -> , | BF200: =if('IOL Formula'!N200 = 0, " ", 'IOL Formula'!O200) | BG200: ='IOL Formula'!B200 | BH200: ='IOL Formula'!C200
... A293: ='QB Formula'!A293&", "&'QB Formula'!B293 -> , | H293: =if('QB Formula'!P293 = 0, " ", 'QB Formula'!P293) | J293: ='QB Formula'!C293 | K293: ='RB Formula'!A293&", "&'RB Formula'!B293 -> , | R293: =if('RB Formula'!R293 = 0, " ", 'RB Formula'!S293) | S293: ='RB Formula'!B293 | T293: ='RB Formula'!C293 | U293: ='WR Formula'!A293&", "&'WR Formula'!B293 -> , | AB293: =if('WR Formula'!N293 = 0, " ", 'WR Formula'!P293) | AD293: ='WR Formula'!C293 | AE293: ='TE Formula'!A293&", "&'TE Formula'!B293 -> , | AL293: =if('TE Formula'!P293 = 0, " ", 'TE Formula'!R293) | AN293: ='TE Formula'!C293 | AO293: ='OT Formula'!A293&", "&'OT Formula'!B293 -> , | AV293: =if('OT Formula'!N293 = 0, " ", 'OT Formula'!O293) | AW293: ='OT Formula'!B293 | AX293: ='OT Formula'!C293 | AY293: ='IOL Formula'!A293&", "&'IOL Formula'!B293 -> , | BF293: =if('IOL Formula'!N293 = 0, " ", 'IOL Formula'!O293) | BG293: ='IOL Formula'!B293 | BH293: ='IOL Formula'!C293
A294: ='QB Formula'!A294&", "&'QB Formula'!B294 -> , | H294: =if('QB Formula'!P294 = 0, " ", 'QB Formula'!P294) | J294: ='QB Formula'!C294 | K294: ='RB Formula'!A294&", "&'RB Formula'!B294 -> , | R294: =if('RB Formula'!R294 = 0, " ", 'RB Formula'!S294) | S294: ='RB Formula'!B294 | T294: =if('RB Formula'!S294 = 0, " ", 'RB Formula'!T294) | U294: ='WR Formula'!A294&", "&'WR Formula'!B294 -> , | AB294: =if('WR Formula'!N294 = 0, " ", 'WR Formula'!P294) | AD294: ='WR Formula'!C294 | AE294: ='TE Formula'!A294&", "&'TE Formula'!B294 -> , | AL294: =if('TE Formula'!P294 = 0, " ", 'TE Formula'!R294) | AN294: ='TE Formula'!C294 | AO294: ='OT Formula'!A294&", "&'OT Formula'!B294 -> , | AV294: =if('OT Formula'!N294 = 0, " ", 'OT Formula'!O294) | AW294: ='OT Formula'!B294 | AX294: ='OT Formula'!C294 | AY294: ='IOL Formula'!A294&", "&'IOL Formula'!B294 -> , | BF294: =if('IOL Formula'!N294 = 0, " ", 'IOL Formula'!O294) | BG294: ='IOL Formula'!B294 | BH294: ='IOL Formula'!C294
A295: ='QB Formula'!A295&", "&'QB Formula'!B295 -> , | H295: =if('QB Formula'!P295 = 0, " ", 'QB Formula'!P295) | J295: ='QB Formula'!C295 | K295: ='RB Formula'!A295&", "&'RB Formula'!B295 -> , | R295: =if('RB Formula'!R295 = 0, " ", 'RB Formula'!S295) | S295: ='RB Formula'!B295 | T295: =if('RB Formula'!S295 = 0, " ", 'RB Formula'!T295) | U295: ='WR Formula'!A295&", "&'WR Formula'!B295 -> , | AB295: =if('WR Formula'!N295 = 0, " ", 'WR Formula'!P295) | AD295: ='WR Formula'!C295 | AE295: ='TE Formula'!A295&", "&'TE Formula'!B295 -> , | AL295: =if('TE Formula'!P295 = 0, " ", 'TE Formula'!R295) | AN295: ='TE Formula'!C295 | AO295: ='OT Formula'!A295&", "&'OT Formula'!B295 -> , | AV295: =if('OT Formula'!N295 = 0, " ", 'OT Formula'!O295) | AW295: ='OT Formula'!B295 | AX295: ='OT Formula'!C295 | AY295: ='IOL Formula'!A295&", "&'IOL Formula'!B295 -> , | BF295: =if('IOL Formula'!N295 = 0, " ", 'IOL Formula'!O295) | BG295: ='IOL Formula'!B295 | BH295: ='IOL Formula'!C295
A296: ='QB Formula'!A296&", "&'QB Formula'!B296 -> , | H296: =if('QB Formula'!P296 = 0, " ", 'QB Formula'!P296) | J296: ='QB Formula'!C296 | K296: ='RB Formula'!A296&", "&'RB Formula'!B296 -> , | R296: =if('RB Formula'!R296 = 0, " ", 'RB Formula'!S296) | S296: ='RB Formula'!B296 | T296: =if('RB Formula'!S296 = 0, " ", 'RB Formula'!T296) | U296: ='WR Formula'!A296&", "&'WR Formula'!B296 -> , | AB296: =if('WR Formula'!N296 = 0, " ", 'WR Formula'!P296) | AD296: ='WR Formula'!C296 | AE296: ='TE Formula'!A296&", "&'TE Formula'!B296 -> , | AL296: =if('TE Formula'!P296 = 0, " ", 'TE Formula'!R296) | AN296: ='TE Formula'!C296 | AO296: ='OT Formula'!A296&", "&'OT Formula'!B296 -> , | AV296: =if('OT Formula'!N296 = 0, " ", 'OT Formula'!O296) | AW296: ='OT Formula'!B296 | AX296: ='OT Formula'!C296 | AY296: ='IOL Formula'!A296&", "&'IOL Formula'!B296 -> , | BF296: =if('IOL Formula'!N296 = 0, " ", 'IOL Formula'!O296) | BG296: ='IOL Formula'!B296 | BH296: ='IOL Formula'!C296
A297: ='QB Formula'!A297&", "&'QB Formula'!B297 -> , | H297: =if('QB Formula'!P297 = 0, " ", 'QB Formula'!P297) | J297: ='QB Formula'!C297 | K297: ='RB Formula'!A297&", "&'RB Formula'!B297 -> , | R297: =if('RB Formula'!R297 = 0, " ", 'RB Formula'!S297) | S297: ='RB Formula'!B297 | T297: =if('RB Formula'!S297 = 0, " ", 'RB Formula'!T297) | U297: ='WR Formula'!A297&", "&'WR Formula'!B297 -> , | AB297: =if('WR Formula'!N297 = 0, " ", 'WR Formula'!P297) | AD297: ='WR Formula'!C297 | AE297: ='TE Formula'!A297&", "&'TE Formula'!B297 -> , | AL297: =if('TE Formula'!P297 = 0, " ", 'TE Formula'!R297) | AN297: ='TE Formula'!C297 | AO297: ='OT Formula'!A297&", "&'OT Formula'!B297 -> , | AV297: =if('OT Formula'!N297 = 0, " ", 'OT Formula'!O297) | AW297: ='OT Formula'!B297 | AX297: ='OT Formula'!C297 | AY297: ='IOL Formula'!A297&", "&'IOL Formula'!B297 -> , | BF297: =if('IOL Formula'!N297 = 0, " ", 'IOL Formula'!O297) | BG297: ='IOL Formula'!B297 | BH297: ='IOL Formula'!C297
A298: ='QB Formula'!A298&", "&'QB Formula'!B298 -> , | H298: =if('QB Formula'!P298 = 0, " ", 'QB Formula'!P298) | J298: ='QB Formula'!C298 | K298: ='RB Formula'!A298&", "&'RB Formula'!B298 -> , | R298: =if('RB Formula'!R298 = 0, " ", 'RB Formula'!S298) | S298: ='RB Formula'!B298 | T298: =if('RB Formula'!S298 = 0, " ", 'RB Formula'!T298) | U298: ='WR Formula'!A298&", "&'WR Formula'!B298 -> , | AB298: =if('WR Formula'!N298 = 0, " ", 'WR Formula'!P298) | AD298: ='WR Formula'!C298 | AE298: ='TE Formula'!A298&", "&'TE Formula'!B298 -> , | AL298: =if('TE Formula'!P298 = 0, " ", 'TE Formula'!R298) | AN298: ='TE Formula'!C298 | AO298: ='OT Formula'!A298&", "&'OT Formula'!B298 -> , | AV298: =if('OT Formula'!N298 = 0, " ", 'OT Formula'!O298) | AW298: ='OT Formula'!B298 | AX298: ='OT Formula'!C298 | AY298: ='IOL Formula'!A298&", "&'IOL Formula'!B298 -> , | BF298: =if('IOL Formula'!N298 = 0, " ", 'IOL Formula'!O298) | BG298: ='IOL Formula'!B298 | BH298: ='IOL Formula'!C298
A299: ='QB Formula'!A299&", "&'QB Formula'!B299 -> , | H299: =if('QB Formula'!P299 = 0, " ", 'QB Formula'!P299) | J299: ='QB Formula'!C299 | K299: ='RB Formula'!A299&", "&'RB Formula'!B299 -> , | R299: =if('RB Formula'!R299 = 0, " ", 'RB Formula'!S299) | S299: ='RB Formula'!B299 | T299: =if('RB Formula'!S299 = 0, " ", 'RB Formula'!T299) | U299: ='WR Formula'!A299&", "&'WR Formula'!B299 -> , | AB299: =if('WR Formula'!N299 = 0, " ", 'WR Formula'!P299) | AD299: ='WR Formula'!C299 | AE299: ='TE Formula'!A299&", "&'TE Formula'!B299 -> , | AL299: =if('TE Formula'!P299 = 0, " ", 'TE Formula'!R299) | AN299: ='TE Formula'!C299 | AO299: ='OT Formula'!A299&", "&'OT Formula'!B299 -> , | AV299: =if('OT Formula'!N299 = 0, " ", 'OT Formula'!O299) | AW299: ='OT Formula'!B299 | AX299: ='OT Formula'!C299 | AY299: ='IOL Formula'!A299&", "&'IOL Formula'!B299 -> , | BF299: =if('IOL Formula'!N299 = 0, " ", 'IOL Formula'!O299) | BG299: ='IOL Formula'!B299 | BH299: ='IOL Formula'!C299
A300: ='QB Formula'!A300&", "&'QB Formula'!B300 -> , | H300: =if('QB Formula'!P300 = 0, " ", 'QB Formula'!P300) | J300: ='QB Formula'!C300 | K300: ='RB Formula'!A300&", "&'RB Formula'!B300 -> , | R300: =if('RB Formula'!R300 = 0, " ", 'RB Formula'!S300) | S300: ='RB Formula'!B300 | T300: =if('RB Formula'!S300 = 0, " ", 'RB Formula'!T300) | U300: ='WR Formula'!A300&", "&'WR Formula'!B300 -> , | AB300: =if('WR Formula'!N300 = 0, " ", 'WR Formula'!P300) | AD300: ='WR Formula'!C300 | AE300: ='TE Formula'!A300&", "&'TE Formula'!B300 -> , | AL300: =if('TE Formula'!P300 = 0, " ", 'TE Formula'!R300) | AN300: ='TE Formula'!C300 | AO300: ='OT Formula'!A300&", "&'OT Formula'!B300 -> , | AV300: =if('OT Formula'!N300 = 0, " ", 'OT Formula'!O300) | AW300: ='OT Formula'!B300 | AX300: ='OT Formula'!C300 | AY300: ='IOL Formula'!A300&", "&'IOL Formula'!B300 -> , | BF300: =if('IOL Formula'!N300 = 0, " ", 'IOL Formula'!O300) | BG300: ='IOL Formula'!B300 | BH300: ='IOL Formula'!C300
A301: ='QB Formula'!A301&", "&'QB Formula'!B301 -> , | H301: =if('QB Formula'!P301 = 0, " ", 'QB Formula'!P301) | J301: ='QB Formula'!C301 | K301: ='RB Formula'!A301&", "&'RB Formula'!B301 -> , | R301: =if('RB Formula'!R301 = 0, " ", 'RB Formula'!S301) | S301: ='RB Formula'!B301 | T301: =if('RB Formula'!S301 = 0, " ", 'RB Formula'!T301) | U301: ='WR Formula'!A301&", "&'WR Formula'!B301 -> , | AB301: =if('WR Formula'!N301 = 0, " ", 'WR Formula'!P301) | AD301: ='WR Formula'!C301 | AE301: ='TE Formula'!A301&", "&'TE Formula'!B301 -> , | AL301: =if('TE Formula'!P301 = 0, " ", 'TE Formula'!R301) | AN301: ='TE Formula'!C301 | AO301: ='OT Formula'!A301&", "&'OT Formula'!B301 -> , | AV301: =if('OT Formula'!N301 = 0, " ", 'OT Formula'!O301) | AW301: ='OT Formula'!B301 | AX301: ='OT Formula'!C301 | AY301: ='IOL Formula'!A301&", "&'IOL Formula'!B301 -> , | BF301: =if('IOL Formula'!N301 = 0, " ", 'IOL Formula'!O301) | BG301: ='IOL Formula'!B301 | BH301: ='IOL Formula'!C301
A302: ='QB Formula'!A302&", "&'QB Formula'!B302 -> , | H302: =if('QB Formula'!P302 = 0, " ", 'QB Formula'!P302) | J302: ='QB Formula'!C302 | K302: ='RB Formula'!A302&", "&'RB Formula'!B302 -> , | R302: =if('RB Formula'!R302 = 0, " ", 'RB Formula'!S302) | S302: ='RB Formula'!B302 | T302: =if('RB Formula'!S302 = 0, " ", 'RB Formula'!T302) | U302: ='WR Formula'!A302&", "&'WR Formula'!B302 -> , | AB302: =if('WR Formula'!N302 = 0, " ", 'WR Formula'!P302) | AD302: ='WR Formula'!C302 | AE302: ='TE Formula'!A302&", "&'TE Formula'!B302 -> , | AL302: =if('TE Formula'!P302 = 0, " ", 'TE Formula'!R302) | AN302: ='TE Formula'!C302 | AO302: ='OT Formula'!A302&", "&'OT Formula'!B302 -> , | AV302: =if('OT Formula'!N302 = 0, " ", 'OT Formula'!O302) | AW302: ='OT Formula'!B302 | AX302: ='OT Formula'!C302 | AY302: ='IOL Formula'!A302&", "&'IOL Formula'!B302 -> , | BF302: =if('IOL Formula'!N302 = 0, " ", 'IOL Formula'!O302) | BG302: ='IOL Formula'!B302 | BH302: ='IOL Formula'!C302
A303: ='QB Formula'!A303&", "&'QB Formula'!B303 -> , | H303: =if('QB Formula'!P303 = 0, " ", 'QB Formula'!P303) | J303: ='QB Formula'!C303 | K303: ='RB Formula'!A303&", "&'RB Formula'!B303 -> , | R303: =if('RB Formula'!R303 = 0, " ", 'RB Formula'!S303) | S303: ='RB Formula'!B303 | T303: =if('RB Formula'!S303 = 0, " ", 'RB Formula'!T303) | U303: ='WR Formula'!A303&", "&'WR Formula'!B303 -> , | AB303: =if('WR Formula'!N303 = 0, " ", 'WR Formula'!P303) | AD303: ='WR Formula'!C303 | AE303: ='TE Formula'!A303&", "&'TE Formula'!B303 -> , | AL303: =if('TE Formula'!P303 = 0, " ", 'TE Formula'!R303) | AN303: ='TE Formula'!C303 | AO303: ='OT Formula'!A303&", "&'OT Formula'!B303 -> , | AV303: =if('OT Formula'!N303 = 0, " ", 'OT Formula'!O303) | AW303: ='OT Formula'!B303 | AX303: ='OT Formula'!C303 | AY303: ='IOL Formula'!A303&", "&'IOL Formula'!B303 -> , | BF303: =if('IOL Formula'!N303 = 0, " ", 'IOL Formula'!O303) | BG303: ='IOL Formula'!B303 | BH303: ='IOL Formula'!C303
A304: ='QB Formula'!A304&", "&'QB Formula'!B304 -> , | H304: =if('QB Formula'!P304 = 0, " ", 'QB Formula'!P304) | J304: ='QB Formula'!C304 | K304: ='RB Formula'!A304&", "&'RB Formula'!B304 -> , | R304: =if('RB Formula'!R304 = 0, " ", 'RB Formula'!S304) | S304: ='RB Formula'!B304 | T304: =if('RB Formula'!S304 = 0, " ", 'RB Formula'!T304) | U304: ='WR Formula'!A304&", "&'WR Formula'!B304 -> , | AB304: =if('WR Formula'!N304 = 0, " ", 'WR Formula'!P304) | AD304: ='WR Formula'!C304 | AE304: ='TE Formula'!A304&", "&'TE Formula'!B304 -> , | AL304: =if('TE Formula'!P304 = 0, " ", 'TE Formula'!R304) | AN304: ='TE Formula'!C304 | AO304: ='OT Formula'!A304&", "&'OT Formula'!B304 -> , | AV304: =if('OT Formula'!N304 = 0, " ", 'OT Formula'!O304) | AW304: ='OT Formula'!B304 | AX304: ='OT Formula'!C304 | AY304: ='IOL Formula'!A304&", "&'IOL Formula'!B304 -> , | BF304: =if('IOL Formula'!N304 = 0, " ", 'IOL Formula'!O304) | BG304: ='IOL Formula'!B304 | BH304: ='IOL Formula'!C304
A305: ='QB Formula'!A305&", "&'QB Formula'!B305 -> , | H305: =if('QB Formula'!P305 = 0, " ", 'QB Formula'!P305) | J305: ='QB Formula'!C305 | K305: ='RB Formula'!A305&", "&'RB Formula'!B305 -> , | R305: =if('RB Formula'!R305 = 0, " ", 'RB Formula'!S305) | S305: ='RB Formula'!B305 | T305: =if('RB Formula'!S305 = 0, " ", 'RB Formula'!T305) | U305: ='WR Formula'!A305&", "&'WR Formula'!B305 -> , | AB305: =if('WR Formula'!N305 = 0, " ", 'WR Formula'!P305) | AD305: ='WR Formula'!C305 | AE305: ='TE Formula'!A305&", "&'TE Formula'!B305 -> , | AL305: =if('TE Formula'!P305 = 0, " ", 'TE Formula'!R305) | AN305: ='TE Formula'!C305 | AO305: ='OT Formula'!A305&", "&'OT Formula'!B305 -> , | AV305: =if('OT Formula'!N305 = 0, " ", 'OT Formula'!O305) | AW305: ='OT Formula'!B305 | AX305: ='OT Formula'!C305 | AY305: ='IOL Formula'!A305&", "&'IOL Formula'!B305 -> , | BF305: =if('IOL Formula'!N305 = 0, " ", 'IOL Formula'!O305) | BG305: ='IOL Formula'!B305 | BH305: ='IOL Formula'!C305
... A1000: ='QB Formula'!A1000&", "&'QB Formula'!B1000 -> , | H1000: =if('QB Formula'!P1000 = 0, " ", 'QB Formula'!P1000) | J1000: ='QB Formula'!C1000 | K1000: ='RB Formula'!A1000&", "&'RB Formula'!B1000 -> , | R1000: =if('RB Formula'!R1000 = 0, " ", 'RB Formula'!S1000) | S1000: ='RB Formula'!B1000 | T1000: =if('RB Formula'!S1000 = 0, " ", 'RB Formula'!T1000) | U1000: ='WR Formula'!A1000&", "&'WR Formula'!B1000 -> , | AB1000: =if('WR Formula'!N1000 = 0, " ", 'WR Formula'!P1000) | AD1000: ='WR Formula'!C1000 | AE1000: ='TE Formula'!A1000&", "&'TE Formula'!B1000 -> , | AL1000: =if('TE Formula'!P1000 = 0, " ", 'TE Formula'!R1000) | AN1000: ='TE Formula'!C1000 | AO1000: ='OT Formula'!A1000&", "&'OT Formula'!B1000 -> , | AV1000: =if('OT Formula'!N1000 = 0, " ", 'OT Formula'!O1000) | AW1000: ='OT Formula'!B1000 | AX1000: ='OT Formula'!C1000 | AY1000: ='IOL Formula'!A1000&", "&'IOL Formula'!B1000 -> , | BF1000: =if('IOL Formula'!N1000 = 0, " ", 'IOL Formula'!O1000) | BG1000: ='IOL Formula'!B1000 | BH1000: ='IOL Formula'!C1000

Sheet QB
A1: Name | B1: COLLEGE | C1: TRANSFER PORTAL | D1: TIER | E1: SCHEME FIT | G1: ARCHETYPE | I1: Arm Strength | J1: Gets Past First Read | K1: Success over MOF | L1: Success towards Field Sideline | M1: Pocket Mobility | N1: Elusiveness Behind LOS | O1: Open Field Speed | P1: GRADE | Q1: DIFFERENTIAL | R1: AA Grade | T1: Grade | U1: Grade | V1: Grade | W1: Grade | X1: Grade | Y1: Grade | Z1: Grade | AD1: Grade | AF1: Grade | AH1: Grade | AJ1: Grade | AL1: Grade | AN1: Grade | AP1: Grade
A2: Brandon Tennison | B2: UTSA | C2: N | D2: =ifs(P2 = 0, "",P2<3.25, "G5 Backup QB", P2<3.75, "G5 Spot Starting QB",P2 < 4.25, "G5 Starter QB",P2 < 4.5, "P4 Spot Starting QB", P2 >= 4.5, "P4 Starter QB" ) -> G5 Spot Starting QB | E2: =If(T2>4.2, "Vertical Passing, ","Short/Intermediate, ")&if(U2>4.2, "Full-Field Progression Offense", "Half-Field Progression") -> Short/Intermediate, Half-Field Progression | G2: =IFS(AND(Q2<-1, T2<4), "Chain Mover w/Arm or Leg", AND(T2>5, Z2>5), "Elite Athlete at QB", AND(T2>5, X2<2.5), "Statue In Pocket Passer", AND(T2>5, X2<4), "Pocket Passer", AND(P2<4, Q2>1), "Chain Mover w/Arm", AND(T2>3, Z2>3), "Functional Athlete at QB") -> Functional Athlete at QB | I2: Ball Dips, Any Platform | J2: Telegraphs Reads Post Snap | K2: Timing Is Off | L2: Anticipates Throw, Ball Is In Defender's Reach | M2: Can Move Around But Doesn't Always Anticipate Pressure | N2: Moves But Easily Chased By Defenders | O2: Gets Yard In Open Space | P2: =iferror((sum(T2:W2)*1.1+sum(X2:Z2)*0.9)/7,0) -> 3.7009471 | Q2: =(sum(T2:W2)-sum(X2:Z2)*1.3) -> -4.1967 | T2: =iferror(XLOOKUP(I2, $AC$2:$AC$6,$AD$2:$AD$6), 0) -> 4.2 | U2: =iferror(XLOOKUP(J2, $AE$2:$AE$6,$AF$2:$AF$6), 0) -> 2.8 | V2: =iferror(XLOOKUP(K2, $AG$2:$AG$6,$AH$2:$AH$6), 0) -> 2.3333 | W2: =iferror(XLOOKUP(L2, $AI$2:$AI$6,$AJ$2:$AJ$6), 0) -> 3.5 | X2: =iferror(XLOOKUP(M2, $AK$2:$AK$6,$AL$2:$AL$6), 0) -> 5.6 | Y2: =iferror(XLOOKUP(N2, $AM$2:$AM$6,$AN$2:$AN$6), 0) -> 4 | Z2: =iferror(XLOOKUP(O2, $AO$2:$AO$6,$AP$2:$AP$6), 0) -> 3.5 | AC2: Any Throw, Any Platform | AD2: 7 | AE2: Consistently Works Thru Full-Field Reads | AF2: 7 | AG2: Consistent Seam Beater | AH2: 7 | AI2: No Velocity Dip On Field Side Throws | AJ2: 7 | AK2: Quick Twitch, Anticipates, Escapes Tight Pocket | AL2: 7 | AM2: Makes Defenders Miss/Anticipatory Vision | AN2: 6 | AO2: Final Gear at 3rd Level | AP2: 7
A3: Brayden Fowler-Nicolosi | B3: Colorado State | C3: Y | D3: =ifs(P3 = 0, "",P3<3.25, "G5 Backup QB", P3<3.75, "G5 Spot Starting QB",P3 < 4.25, "G5 Starter QB",P3 < 4.5, "P4 Spot Starting QB", P3 >= 4.5, "P4 Starter QB" ) -> G5 Spot Starting QB | E3: =If(T3>4.2, "Vertical Passing, ","Short/Intermediate, ")&if(U3>4.2, "Full-Field Progression Offense", "Half-Field Progression") -> Vertical Passing, Half-Field Progression | G3: =IFS(AND(Q3<-1, T3<4), "Chain Mover w/Arm or Leg", AND(T3>5, Z3>5), "Elite Athlete at QB", AND(T3>5, X3<2.5), "Statue In Pocket Passer", AND(T3>5, X3<4), "Pocket Passer", AND(P3<4, Q3>1), "Chain Mover w/Arm", AND(T3>3, Z3>3), "Functional Athlete at QB") -> Pocket Passer | I3: Any Throw, Firm Base | J3: Telegraphs Reads Post Snap | K3: Timing Is Off | L3: Frequently Hits Hole Shots | M3: Throws Thru Pressure | N3: Resorts to Throwaway/Expects To Get Hit | O3: Gets Yard In Open Space | P3: =iferror((sum(T3:W3)*1.1+sum(X3:Z3)*0.9)/7,0) -> 3.5788043 | Q3: =(sum(T3:W3)-sum(X3:Z3)*1.3) -> 5.1933 | T3: =iferror(XLOOKUP(I3, $AC$2:$AC$6,$AD$2:$AD$6), 0) -> 5.6 | U3: =iferror(XLOOKUP(J3, $AE$2:$AE$6,$AF$2:$AF$6), 0) -> 2.8 | V3: =iferror(XLOOKUP(K3, $AG$2:$AG$6,$AH$2:$AH$6), 0) -> 2.3333 | W3: =iferror(XLOOKUP(L3, $AI$2:$AI$6,$AJ$2:$AJ$6), 0) -> 5.25 | X3: =iferror(XLOOKUP(M3, $AK$2:$AK$6,$AL$2:$AL$6), 0) -> 2.8 | Y3: =iferror(XLOOKUP(N3, $AM$2:$AM$6,$AN$2:$AN$6), 0) -> 2 | Z3: =iferror(XLOOKUP(O3, $AO$2:$AO$6,$AP$2:$AP$6), 0) -> 3.5 | AC3: Any Throw, Firm Base | AD3: 5.6 | AE3: Will Occasionally Get To 3rd Read | AF3: 5.6 | AG3: Can Hit, Struggles In Tight Windows | AH3: 4.6 | AI3: Frequently Hits Hole Shots | AJ3: 5.25 | AK3: Can Move Around But Doesn't Always Anticipate Pressure | AL3: 5.6 | AM3: Moves But Easily Chased By Defenders | AN3: 4 | AO3: Good Space Eater | AP3: 5.25
A4: Hauss Hejny | B4: Oklahoma State | C4: N | D4: =ifs(P4 = 0, "",P4<3.25, "G5 Backup QB", P4<3.75, "G5 Spot Starting QB",P4 < 4.25, "G5 Starter QB",P4 < 4.5, "P4 Spot Starting QB", P4 >= 4.5, "P4 Starter QB" ) -> P4 Starter QB | E4: =If(T4>4.2, "Vertical Passing, ","Short/Intermediate, ")&if(U4>4.2, "Full-Field Progression Offense", "Half-Field Progression") -> Vertical Passing, Half-Field Progression | G4: =IFS(AND(Q4<-1, T4<4), "Chain Mover w/Arm or Leg", AND(T4>5, Z4>5), "Elite Athlete at QB", AND(T4>5, X4<2.5), "Statue In Pocket Passer", AND(T4>5, X4<4), "Pocket Passer", AND(P4<4, Q4>1), "Chain Mover w/Arm", AND(T4>3, Z4>3), "Functional Athlete at QB") -> Elite Athlete at QB | I4: Any Throw, Firm Base | J4: Correctly Deciphers Half Field Reads | K4: Can Hit, Struggles In Tight Windows | L4: Frequently Hits Hole Shots | M4: Can Move Around But Doesn't Always Anticipate Pressure | N4: Moves But Easily Chased By Defenders | O4: Good Space Eater | P4: =iferror((sum(T4:W4)*1.1+sum(X4:Z4)*0.9)/7,0) -> 4.9971429 | Q4: =(sum(T4:W4)-sum(X4:Z4)*1.3) -> 0.345 | T4: =iferror(XLOOKUP(I4, $AC$2:$AC$6,$AD$2:$AD$6), 0) -> 5.6 | U4: =iferror(XLOOKUP(J4, $AE$2:$AE$6,$AF$2:$AF$6), 0) -> 4.2 | V4: =iferror(XLOOKUP(K4, $AG$2:$AG$6,$AH$2:$AH$6), 0) -> 4.6 | W4: =iferror(XLOOKUP(L4, $AI$2:$AI$6,$AJ$2:$AJ$6), 0) -> 5.25 | X4: =iferror(XLOOKUP(M4, $AK$2:$AK$6,$AL$2:$AL$6), 0) -> 5.6 | Y4: =iferror(XLOOKUP(N4, $AM$2:$AM$6,$AN$2:$AN$6), 0) -> 4 | Z4: =iferror(XLOOKUP(O4, $AO$2:$AO$6,$AP$2:$AP$6), 0) -> 5.25 | AC4: Ball Dips, Any Platform | AD4: 4.2 | AE4: Correctly Deciphers Half Field Reads | AF4: 4.2 | AG4: Timing Is Off | AH4: 2.3333 | AI4: Anticipates Throw, Ball Is In Defender's Reach | AJ4: 3.5 | AK4: Likely to Bail From Clean Pocket | AL4: 4.2 | AM4: Resorts to Throwaway/Expects To Get Hit | AN4: 2 | AO4: Gets Yard In Open Space | AP4: 3.5
A5: Zane Flores | B5: Oklahoma State | C5: Y | D5: =ifs(P5 = 0, "",P5<3.25, "G5 Backup QB", P5<3.75, "G5 Spot Starting QB",P5 < 4.25, "G5 Starter QB",P5 < 4.5, "P4 Spot Starting QB", P5 >= 4.5, "P4 Starter QB" ) -> P4 Spot Starting QB | E5: =If(T5>4.2, "Vertical Passing, ","Short/Intermediate, ")&if(U5>4.2, "Full-Field Progression Offense", "Half-Field Progression") -> Short/Intermediate, Half-Field Progression | G5: =IFS(AND(Q5<-1, T5<4), "Chain Mover w/Arm or Leg", AND(T5>5, Z5>5), "Elite Athlete at QB", AND(T5>5, X5<2.5), "Statue In Pocket Passer", AND(T5>5, X5<4), "Pocket Passer", AND(P5<4, Q5>1), "Chain Mover w/Arm", AND(T5>3, Z5>3), "Functional Athlete at QB") -> Functional Athlete at QB | I5: Ball Dips, Any Platform | J5: Correctly Deciphers Half Field Reads | K5: Can Hit, Struggles In Tight Windows | L5: Frequently Hits Hole Shots | M5: Likely to Bail From Clean Pocket | N5: Moves But Easily Chased By Defenders | O5: Gets Yard In Open Space | P5: =iferror((sum(T5:W5)*1.1+sum(X5:Z5)*0.9)/7,0) -> 4.3721429 | Q5: =(sum(T5:W5)-sum(X5:Z5)*1.3) -> 3.04 | T5: =iferror(XLOOKUP(I5, $AC$2:$AC$6,$AD$2:$AD$6), 0) -> 4.2 | U5: =iferror(XLOOKUP(J5, $AE$2:$AE$6,$AF$2:$AF$6), 0) -> 4.2 | V5: =iferror(XLOOKUP(K5, $AG$2:$AG$6,$AH$2:$AH$6), 0) -> 4.6 | W5: =iferror(XLOOKUP(L5, $AI$2:$AI$6,$AJ$2:$AJ$6), 0) -> 5.25 | X5: =iferror(XLOOKUP(M5, $AK$2:$AK$6,$AL$2:$AL$6), 0) -> 4.2 | Y5: =iferror(XLOOKUP(N5, $AM$2:$AM$6,$AN$2:$AN$6), 0) -> 4 | Z5: =iferror(XLOOKUP(O5, $AO$2:$AO$6,$AP$2:$AP$6), 0) -> 3.5 | AC5: Ball Dips, Firm Base | AD5: 2.8 | AE5: Telegraphs Reads Post Snap | AF5: 2.8 | AI5: Ball Dips To Open Receiver | AJ5: 1.75 | AK5: Throws Thru Pressure | AL5: 2.8 | AO5: Looks Reluctant To Run | AP5: 1.75
A6: Davin Wydner | B6: West Georgia | C6: Y | D6: =ifs(P6 = 0, "",P6<3.25, "G5 Backup QB", P6<3.75, "G5 Spot Starting QB",P6 < 4.25, "G5 Starter QB",P6 < 4.5, "P4 Spot Starting QB", P6 >= 4.5, "P4 Starter QB" ) -> G5 Starter QB | E6: =If(T6>4.2, "Vertical Passing, ","Short/Intermediate, ")&if(U6>4.2, "Full-Field Progression Offense", "Half-Field Progression") -> Short/Intermediate, Half-Field Progression | G6: =IFS(AND(Q6<-1, T6<4), "Chain Mover w/Arm or Leg", AND(T6>5, Z6>5), "Elite Athlete at QB", AND(T6>5, X6<2.5), "Statue In Pocket Passer", AND(T6>5, X6<4), "Pocket Passer", AND(P6<4, Q6>1), "Chain Mover w/Arm", AND(T6>3, Z6>3), "Functional Athlete at QB") -> Functional Athlete at QB | I6: Ball Dips, Any Platform | J6: Telegraphs Reads Post Snap | K6: Timing Is Off | L6: Frequently Hits Hole Shots | M6: Likely to Bail From Clean Pocket | N6: Moves But Easily Chased By Defenders | O6: Gets Yard In Open Space | P6: =iferror((sum(T6:W6)*1.1+sum(X6:Z6)*0.9)/7,0) -> 3.7959471 | Q6: =(sum(T6:W6)-sum(X6:Z6)*1.3) -> -0.6267 | T6: =iferror(XLOOKUP(I6, $AC$2:$AC$6,$AD$2:$AD$6), 0) -> 4.2 | U6: =iferror(XLOOKUP(J6, $AE$2:$AE$6,$AF$2:$AF$6), 0) -> 2.8 | V6: =iferror(XLOOKUP(K6, $AG$2:$AG$6,$AH$2:$AH$6), 0) -> 2.3333 | W6: =iferror(XLOOKUP(L6, $AI$2:$AI$6,$AJ$2:$AJ$6), 0) -> 5.25 | X6: =iferror(XLOOKUP(M6, $AK$2:$AK$6,$AL$2:$AL$6), 0) -> 4.2 | Y6: =iferror(XLOOKUP(N6, $AM$2:$AM$6,$AN$2:$AN$6), 0) -> 4 | Z6: =iferror(XLOOKUP(O6, $AO$2:$AO$6,$AP$2:$AP$6), 0) -> 3.5 | AC6: Arm Strength Increases On The Run | AD6: 1 | AE6: Won't Process Reads | AF6: 1 | AK6: Statue In Pocket | AL6: 1
A7: Devon Dampier | B7: Utah | C7: N | D7: =ifs(P7 = 0, "",P7<3.25, "G5 Backup QB", P7<3.75, "G5 Spot Starting QB",P7 < 4.25, "G5 Starter QB",P7 < 4.5, "P4 Spot Starting QB", P7 >= 4.5, "P4 Starter QB" ) -> P4 Starter QB | E7: =If(T7>4.2, "Vertical Passing, ","Short/Intermediate, ")&if(U7>4.2, "Full-Field Progression Offense", "Half-Field Progression") -> Short/Intermediate, Full-Field Progression Offense | G7: =IFS(AND(Q7<-1, T7<4), "Chain Mover w/Arm or Leg", AND(T7>5, Z7>5), "Elite Athlete at QB", AND(T7>5, X7<2.5), "Statue In Pocket Passer", AND(T7>5, X7<4), "Pocket Passer", AND(P7<4, Q7>1), "Chain Mover w/Arm", AND(T7>3, Z7>3), "Functional Athlete at QB") -> Functional Athlete at QB | I7: Ball Dips, Any Platform | J7: Will Occasionally Get To 3rd Read | K7: Can Hit, Struggles In Tight Windows | L7: Anticipates Throw, Ball Is In Defender's Reach | M7: Likely to Bail From Clean Pocket | N7: Makes Defenders Miss/Anticipatory Vision | O7: Gets Yard In Open Space | P7: =iferror((sum(T7:W7)*1.1+sum(X7:Z7)*0.9)/7,0) -> 4.5742857 | Q7: =(sum(T7:W7)-sum(X7:Z7)*1.3) -> 0.09 | T7: =iferror(XLOOKUP(I7, $AC$2:$AC$6,$AD$2:$AD$6), 0) -> 4.2 | U7: =iferror(XLOOKUP(J7, $AE$2:$AE$6,$AF$2:$AF$6), 0) -> 5.6 | V7: =iferror(XLOOKUP(K7, $AG$2:$AG$6,$AH$2:$AH$6), 0) -> 4.6 | W7: =iferror(XLOOKUP(L7, $AI$2:$AI$6,$AJ$2:$AJ$6), 0) -> 3.5 | X7: =iferror(XLOOKUP(M7, $AK$2:$AK$6,$AL$2:$AL$6), 0) -> 4.2 | Y7: =iferror(XLOOKUP(N7, $AM$2:$AM$6,$AN$2:$AN$6), 0) -> 6 | Z7: =iferror(XLOOKUP(O7, $AO$2:$AO$6,$AP$2:$AP$6), 0) -> 3.5
A8: Wyatt Bower | B8: Ferris State | C8: N | D8: =ifs(P8 = 0, "",P8<3.25, "G5 Backup QB", P8<3.75, "G5 Spot Starting QB",P8 < 4.25, "G5 Starter QB",P8 < 4.5, "P4 Spot Starting QB", P8 >= 4.5, "P4 Starter QB" ) -> P4 Spot Starting QB | E8: =If(T8>4.2, "Vertical Passing, ","Short/Intermediate, ")&if(U8>4.2, "Full-Field Progression Offense", "Half-Field Progression") -> Short/Intermediate, Half-Field Progression | G8: =IFS(AND(Q8<-1, T8<4), "Chain Mover w/Arm or Leg", AND(T8>5, Z8>5), "Elite Athlete at QB", AND(T8>5, X8<2.5), "Statue In Pocket Passer", AND(T8>5, X8<4), "Pocket Passer", AND(P8<4, Q8>1), "Chain Mover w/Arm", AND(T8>3, Z8>3), "Functional Athlete at QB") -> Functional Athlete at QB | I8: Ball Dips, Any Platform | J8: Telegraphs Reads Post Snap | K8: Can Hit, Struggles In Tight Windows | L8: Anticipates Throw, Ball Is In Defender's Reach | M8: Likely to Bail From Clean Pocket | N8: Makes Defenders Miss/Anticipatory Vision | O8: Good Space Eater | P8: =iferror((sum(T8:W8)*1.1+sum(X8:Z8)*0.9)/7,0) -> 4.3592857 | Q8: =(sum(T8:W8)-sum(X8:Z8)*1.3) -> -4.985 | T8: =iferror(XLOOKUP(I8, $AC$2:$AC$6,$AD$2:$AD$6), 0) -> 4.2 | U8: =iferror(XLOOKUP(J8, $AE$2:$AE$6,$AF$2:$AF$6), 0) -> 2.8 | V8: =iferror(XLOOKUP(K8, $AG$2:$AG$6,$AH$2:$AH$6), 0) -> 4.6 | W8: =iferror(XLOOKUP(L8, $AI$2:$AI$6,$AJ$2:$AJ$6), 0) -> 3.5 | X8: =iferror(XLOOKUP(M8, $AK$2:$AK$6,$AL$2:$AL$6), 0) -> 4.2 | Y8: =iferror(XLOOKUP(N8, $AM$2:$AM$6,$AN$2:$AN$6), 0) -> 6 | Z8: =iferror(XLOOKUP(O8, $AO$2:$AO$6,$AP$2:$AP$6), 0) -> 5.25
A9: Byrd Ficklin | B9: Utah | C9: N | D9: =ifs(P9 = 0, "",P9<3.25, "G5 Backup QB", P9<3.75, "G5 Spot Starting QB",P9 < 4.25, "G5 Starter QB",P9 < 4.5, "P4 Spot Starting QB", P9 >= 4.5, "P4 Starter QB" ) -> P4 Starter QB | E9: =If(T9>4.2, "Vertical Passing, ","Short/Intermediate, ")&if(U9>4.2, "Full-Field Progression Offense", "Half-Field Progression") -> Short/Intermediate, Half-Field Progression | G9: =IFS(AND(Q9<-1, T9<4), "Chain Mover w/Arm or Leg", AND(T9>5, Z9>5), "Elite Athlete at QB", AND(T9>5, X9<2.5), "Statue In Pocket Passer", AND(T9>5, X9<4), "Pocket Passer", AND(P9<4, Q9>1), "Chain Mover w/Arm", AND(T9>3, Z9>3), "Functional Athlete at QB") -> Functional Athlete at QB | I9: Ball Dips, Any Platform | J9: Telegraphs Reads Post Snap | K9: Can Hit, Struggles In Tight Windows | L9: Anticipates Throw, Ball Is In Defender's Reach | M9: Can Move Around But Doesn't Always Anticipate Pressure | N9: Makes Defenders Miss/Anticipatory Vision | O9: Good Space Eater | P9: =iferror((sum(T9:W9)*1.1+sum(X9:Z9)*0.9)/7,0) -> 4.5392857 | Q9: =(sum(T9:W9)-sum(X9:Z9)*1.3) -> -6.805 | T9: =iferror(XLOOKUP(I9, $AC$2:$AC$6,$AD$2:$AD$6), 0) -> 4.2 | U9: =iferror(XLOOKUP(J9, $AE$2:$AE$6,$AF$2:$AF$6), 0) -> 2.8 | V9: =iferror(XLOOKUP(K9, $AG$2:$AG$6,$AH$2:$AH$6), 0) -> 4.6 | W9: =iferror(XLOOKUP(L9, $AI$2:$AI$6,$AJ$2:$AJ$6), 0) -> 3.5 | X9: =iferror(XLOOKUP(M9, $AK$2:$AK$6,$AL$2:$AL$6), 0) -> 5.6 | Y9: =iferror(XLOOKUP(N9, $AM$2:$AM$6,$AN$2:$AN$6), 0) -> 6 | Z9: =iferror(XLOOKUP(O9, $AO$2:$AO$6,$AP$2:$AP$6), 0) -> 5.25
A10: Amari Odom | B10: Kennesaw State | C10: N | D10: =ifs(P10 = 0, "",P10<3.25, "G5 Backup QB", P10<3.75, "G5 Spot Starting QB",P10 < 4.25, "G5 Starter QB",P10 < 4.5, "P4 Spot Starting QB", P10 >= 4.5, "P4 Starter QB" ) -> G5 Starter QB | E10: =If(T10>4.2, "Vertical Passing, ","Short/Intermediate, ")&if(U10>4.2, "Full-Field Progression Offense", "Half-Field Progression") -> Vertical Passing, Half-Field Progression | G10: =IFS(AND(Q10<-1, T10<4), "Chain Mover w/Arm or Leg", AND(T10>5, Z10>5), "Elite Athlete at QB", AND(T10>5, X10<2.5), "Statue In Pocket Passer", AND(T10>5, X10<4), "Pocket Passer", AND(P10<4, Q10>1), "Chain Mover w/Arm", AND(T10>3, Z10>3), "Functional Athlete at QB") -> Elite Athlete at QB | I10: Any Throw, Firm Base | J10: Won't Process Reads | K10: Timing Is Off | L10: Anticipates Throw, Ball Is In Defender's Reach | M10: Quick Twitch, Anticipates, Escapes Tight Pocket | N10: Moves But Easily Chased By Defenders | O10: Good Space Eater | P10: =iferror((sum(T10:W10)*1.1+sum(X10:Z10)*0.9)/7,0) -> 4.04309 | Q10: =(sum(T10:W10)-sum(X10:Z10)*1.3) -> -8.6917 | T10: =iferror(XLOOKUP(I10, $AC$2:$AC$6,$AD$2:$AD$6), 0) -> 5.6 | U10: =iferror(XLOOKUP(J10, $AE$2:$AE$6,$AF$2:$AF$6), 0) -> 1 | V10: =iferror(XLOOKUP(K10, $AG$2:$AG$6,$AH$2:$AH$6), 0) -> 2.3333 | W10: =iferror(XLOOKUP(L10, $AI$2:$AI$6,$AJ$2:$AJ$6), 0) -> 3.5 | X10: =iferror(XLOOKUP(M10, $AK$2:$AK$6,$AL$2:$AL$6), 0) -> 7 | Y10: =iferror(XLOOKUP(N10, $AM$2:$AM$6,$AN$2:$AN$6), 0) -> 4 | Z10: =iferror(XLOOKUP(O10, $AO$2:$AO$6,$AP$2:$AP$6), 0) -> 5.25
A11: Carson Camp | B11: Southeastern Louisiana | C11: Y | D11: =ifs(P11 = 0, "",P11<3.25, "G5 Backup QB", P11<3.75, "G5 Spot Starting QB",P11 < 4.25, "G5 Starter QB",P11 < 4.5, "P4 Spot Starting QB", P11 >= 4.5, "P4 Starter QB" ) -> G5 Spot Starting QB | E11: =If(T11>4.2, "Vertical Passing, ","Short/Intermediate, ")&if(U11>4.2, "Full-Field Progression Offense", "Half-Field Progression") -> Short/Intermediate, Half-Field Progression | G11: =IFS(AND(Q11<-1, T11<4), "Chain Mover w/Arm or Leg", AND(T11>5, Z11>5), "Elite Athlete at QB", AND(T11>5, X11<2.5), "Statue In Pocket Passer", AND(T11>5, X11<4), "Pocket Passer", AND(P11<4, Q11>1), "Chain Mover w/Arm", AND(T11>3, Z11>3), "Functional Athlete at QB") -> Chain Mover w/Arm or Leg | I11: Ball Dips, Firm Base | J11: Won't Process Reads | K11: Can Hit, Struggles In Tight Windows | L11: Anticipates Throw, Ball Is In Defender's Reach | M11: Likely to Bail From Clean Pocket | N11: Makes Defenders Miss/Anticipatory Vision | O11: Gets Yard In Open Space | P11: =iferror((sum(T11:W11)*1.1+sum(X11:Z11)*0.9)/7,0) -> 3.6314286 | Q11: =(sum(T11:W11)-sum(X11:Z11)*1.3) -> -5.91 | T11: =iferror(XLOOKUP(I11, $AC$2:$AC$6,$AD$2:$AD$6), 0) -> 2.8 | U11: =iferror(XLOOKUP(J11, $AE$2:$AE$6,$AF$2:$AF$6), 0) -> 1 | V11: =iferror(XLOOKUP(K11, $AG$2:$AG$6,$AH$2:$AH$6), 0) -> 4.6 | W11: =iferror(XLOOKUP(L11, $AI$2:$AI$6,$AJ$2:$AJ$6), 0) -> 3.5 | X11: =iferror(XLOOKUP(M11, $AK$2:$AK$6,$AL$2:$AL$6), 0) -> 4.2 | Y11: =iferror(XLOOKUP(N11, $AM$2:$AM$6,$AN$2:$AN$6), 0) -> 6 | Z11: =iferror(XLOOKUP(O11, $AO$2:$AO$6,$AP$2:$AP$6), 0) -> 3.5
A12: Eli Holstein | B12: Pittsburgh | C12: N | D12: =ifs(P12 = 0, "",P12<3.25, "G5 Backup QB", P12<3.75, "G5 Spot Starting QB",P12 < 4.25, "G5 Starter QB",P12 < 4.5, "P4 Spot Starting QB", P12 >= 4.5, "P4 Starter QB" ) -> P4 Spot Starting QB | E12: =If(T12>4.2, "Vertical Passing, ","Short/Intermediate, ")&if(U12>4.2, "Full-Field Progression Offense", "Half-Field Progression") -> Short/Intermediate, Half-Field Progression | G12: =IFS(AND(Q12<-1, T12<4), "Chain Mover w/Arm or Leg", AND(T12>5, Z12>5), "Elite Athlete at QB", AND(T12>5, X12<2.5), "Statue In Pocket Passer", AND(T12>5, X12<4), "Pocket Passer", AND(P12<4, Q12>1), "Chain Mover w/Arm", AND(T12>3, Z12>3), "Functional Athlete at QB") -> Functional Athlete at QB | I12: Ball Dips, Any Platform | J12: Correctly Deciphers Half Field Reads | K12: Can Hit, Struggles In Tight Windows | L12: Anticipates Throw, Ball Is In Defender's Reach | M12: Can Move Around But Doesn't Always Anticipate Pressure | N12: Moves But Easily Chased By Defenders | O12: Gets Yard In Open Space | P12: =iferror((sum(T12:W12)*1.1+sum(X12:Z12)*0.9)/7,0) -> 4.2771429 | Q12: =(sum(T12:W12)-sum(X12:Z12)*1.3) -> -0.53 | T12: =iferror(XLOOKUP(I12, $AC$2:$AC$6,$AD$2:$AD$6), 0) -> 4.2 | U12: =iferror(XLOOKUP(J12, $AE$2:$AE$6,$AF$2:$AF$6), 0) -> 4.2 | V12: =iferror(XLOOKUP(K12, $AG$2:$AG$6,$AH$2:$AH$6), 0) -> 4.6 | W12: =iferror(XLOOKUP(L12, $AI$2:$AI$6,$AJ$2:$AJ$6), 0) -> 3.5 | X12: =iferror(XLOOKUP(M12, $AK$2:$AK$6,$AL$2:$AL$6), 0) -> 5.6 | Y12: =iferror(XLOOKUP(N12, $AM$2:$AM$6,$AN$2:$AN$6), 0) -> 4 | Z12: =iferror(XLOOKUP(O12, $AO$2:$AO$6,$AP$2:$AP$6), 0) -> 3.5
A13: Braxton Thomas | B13: North Carolina A&T | C13: N | D13: =ifs(P13 = 0, "",P13<3.25, "G5 Backup QB", P13<3.75, "G5 Spot Starting QB",P13 < 4.25, "G5 Starter QB",P13 < 4.5, "P4 Spot Starting QB", P13 >= 4.5, "P4 Starter QB" ) -> P4 Spot Starting QB | E13: =If(T13>4.2, "Vertical Passing, ","Short/Intermediate, ")&if(U13>4.2, "Full-Field Progression Offense", "Half-Field Progression") -> Vertical Passing, Half-Field Progression | G13: =IFS(AND(Q13<-1, T13<4), "Chain Mover w/Arm or Leg", AND(T13>5, Z13>5), "Elite Athlete at QB", AND(T13>5, X13<2.5), "Statue In Pocket Passer", AND(T13>5, X13<4), "Pocket Passer", AND(P13<4, Q13>1), "Chain Mover w/Arm", AND(T13>3, Z13>3), "Functional Athlete at QB") -> Functional Athlete at QB | I13: Any Throw, Firm Base | J13: Telegraphs Reads Post Snap | K13: Can Hit, Struggles In Tight Windows | L13: Frequently Hits Hole Shots | M13: Likely to Bail From Clean Pocket | N13: Moves But Easily Chased By Defenders | O13: Gets Yard In Open Space | P13: =iferror((sum(T13:W13)*1.1+sum(X13:Z13)*0.9)/7,0) -> 4.3721429 | Q13: =(sum(T13:W13)-sum(X13:Z13)*1.3) -> 3.04 | T13: =iferror(XLOOKUP(I13, $AC$2:$AC$6,$AD$2:$AD$6), 0) -> 5.6 | U13: =iferror(XLOOKUP(J13, $AE$2:$AE$6,$AF$2:$AF$6), 0) -> 2.8 | V13: =iferror(XLOOKUP(K13, $AG$2:$AG$6,$AH$2:$AH$6), 0) -> 4.6 | W13: =iferror(XLOOKUP(L13, $AI$2:$AI$6,$AJ$2:$AJ$6), 0) -> 5.25 | X13: =iferror(XLOOKUP(M13, $AK$2:$AK$6,$AL$2:$AL$6), 0) -> 4.2 | Y13: =iferror(XLOOKUP(N13, $AM$2:$AM$6,$AN$2:$AN$6), 0) -> 4 | Z13: =iferror(XLOOKUP(O13, $AO$2:$AO$6,$AP$2:$AP$6), 0) -> 3.5
A14: Jared Lockhart | B14: Jackson State | C14: N | D14: =ifs(P14 = 0, "",P14<3.25, "G5 Backup QB", P14<3.75, "G5 Spot Starting QB",P14 < 4.25, "G5 Starter QB",P14 < 4.5, "P4 Spot Starting QB", P14 >= 4.5, "P4 Starter QB" ) -> G5 Spot Starting QB | E14: =If(T14>4.2, "Vertical Passing, ","Short/Intermediate, ")&if(U14>4.2, "Full-Field Progression Offense", "Half-Field Progression") -> Vertical Passing, Half-Field Progression | G14: =IFS(AND(Q14<-1, T14<4), "Chain Mover w/Arm or Leg", AND(T14>5, Z14>5), "Elite Athlete at QB", AND(T14>5, X14<2.5), "Statue In Pocket Passer", AND(T14>5, X14<4), "Pocket Passer", AND(P14<4, Q14>1), "Chain Mover w/Arm", AND(T14>3, Z14>3), "Functional Athlete at QB") -> Elite Athlete at QB | I14: Any Throw, Firm Base | J14: Won't Process Reads | K14: Timing Is Off | L14: Anticipates Throw, Ball Is In Defender's Reach | M14: Likely to Bail From Clean Pocket | N14: Moves But Easily Chased By Defenders | O14: Good Space Eater | P14: =iferror((sum(T14:W14)*1.1+sum(X14:Z14)*0.9)/7,0) -> 3.68309 | Q14: =(sum(T14:W14)-sum(X14:Z14)*1.3) -> -5.0517 | T14: =iferror(XLOOKUP(I14, $AC$2:$AC$6,$AD$2:$AD$6), 0) -> 5.6 | U14: =iferror(XLOOKUP(J14, $AE$2:$AE$6,$AF$2:$AF$6), 0) -> 1 | V14: =iferror(XLOOKUP(K14, $AG$2:$AG$6,$AH$2:$AH$6), 0) -> 2.3333 | W14: =iferror(XLOOKUP(L14, $AI$2:$AI$6,$AJ$2:$AJ$6), 0) -> 3.5 | X14: =iferror(XLOOKUP(M14, $AK$2:$AK$6,$AL$2:$AL$6), 0) -> 4.2 | Y14: =iferror(XLOOKUP(N14, $AM$2:$AM$6,$AN$2:$AN$6), 0) -> 4 | Z14: =iferror(XLOOKUP(O14, $AO$2:$AO$6,$AP$2:$AP$6), 0) -> 5.25
A15: Johnny Weber | B15: SEMO | C15: N | D15: =ifs(P15 = 0, "",P15<3.25, "G5 Backup QB", P15<3.75, "G5 Spot Starting QB",P15 < 4.25, "G5 Starter QB",P15 < 4.5, "P4 Spot Starting QB", P15 >= 4.5, "P4 Starter QB" ) -> G5 Spot Starting QB | E15: =If(T15>4.2, "Vertical Passing, ","Short/Intermediate, ")&if(U15>4.2, "Full-Field Progression Offense", "Half-Field Progression") -> Short/Intermediate, Half-Field Progression | G15: =IFS(AND(Q15<-1, T15<4), "Chain Mover w/Arm or Leg", AND(T15>5, Z15>5), "Elite Athlete at QB", AND(T15>5, X15<2.5), "Statue In Pocket Passer", AND(T15>5, X15<4), "Pocket Passer", AND(P15<4, Q15>1), "Chain Mover w/Arm", AND(T15>3, Z15>3), "Functional Athlete at QB") -> Chain Mover w/Arm | I15: Ball Dips, Any Platform | J15: Correctly Deciphers Half Field Reads | K15: Can Hit, Struggles In Tight Windows | L15: Anticipates Throw, Ball Is In Defender's Reach | M15: Statue In Pocket | N15: Resorts to Throwaway/Expects To Get Hit | O15: Gets Yard In Open Space | P15: =iferror((sum(T15:W15)*1.1+sum(X15:Z15)*0.9)/7,0) -> 3.4285714 | Q15: =(sum(T15:W15)-sum(X15:Z15)*1.3) -> 8.05 | T15: =iferror(XLOOKUP(I15, $AC$2:$AC$6,$AD$2:$AD$6), 0) -> 4.2 | U15: =iferror(XLOOKUP(J15, $AE$2:$AE$6,$AF$2:$AF$6), 0) -> 4.2 | V15: =iferror(XLOOKUP(K15, $AG$2:$AG$6,$AH$2:$AH$6), 0) -> 4.6 | W15: =iferror(XLOOKUP(L15, $AI$2:$AI$6,$AJ$2:$AJ$6), 0) -> 3.5 | X15: =iferror(XLOOKUP(M15, $AK$2:$AK$6,$AL$2:$AL$6), 0) -> 1 | Y15: =iferror(XLOOKUP(N15, $AM$2:$AM$6,$AN$2:$AN$6), 0) -> 2 | Z15: =iferror(XLOOKUP(O15, $AO$2:$AO$6,$AP$2:$AP$6), 0) -> 3.5
A16: Jax Leatherwood | B16: SEMO | C16: Y | D16: =ifs(P16 = 0, "",P16<3.25, "G5 Backup QB", P16<3.75, "G5 Spot Starting QB",P16 < 4.25, "G5 Starter QB",P16 < 4.5, "P4 Spot Starting QB", P16 >= 4.5, "P4 Starter QB" ) -> P4 Starter QB | E16: =If(T16>4.2, "Vertical Passing, ","Short/Intermediate, ")&if(U16>4.2, "Full-Field Progression Offense", "Half-Field Progression") -> Vertical Passing, Full-Field Progression Offense | G16: =IFS(AND(Q16<-1, T16<4), "Chain Mover w/Arm or Leg", AND(T16>5, Z16>5), "Elite Athlete at QB", AND(T16>5, X16<2.5), "Statue In Pocket Passer", AND(T16>5, X16<4), "Pocket Passer", AND(P16<4, Q16>1), "Chain Mover w/Arm", AND(T16>3, Z16>3), "Functional Athlete at QB") -> Statue In Pocket Passer | I16: Any Throw, Firm Base | J16: Will Occasionally Get To 3rd Read | K16: Consistent Seam Beater | L16: No Velocity Dip On Field Side Throws | M16: Statue In Pocket | N16: Resorts to Throwaway/Expects To Get Hit | O16: Gets Yard In Open Space | P16: =iferror((sum(T16:W16)*1.1+sum(X16:Z16)*0.9)/7,0) -> 4.7957143 | Q16: =(sum(T16:W16)-sum(X16:Z16)*1.3) -> 16.75 | T16: =iferror(XLOOKUP(I16, $AC$2:$AC$6,$AD$2:$AD$6), 0) -> 5.6 | U16: =iferror(XLOOKUP(J16, $AE$2:$AE$6,$AF$2:$AF$6), 0) -> 5.6 | V16: =iferror(XLOOKUP(K16, $AG$2:$AG$6,$AH$2:$AH$6), 0) -> 7 | W16: =iferror(XLOOKUP(L16, $AI$2:$AI$6,$AJ$2:$AJ$6), 0) -> 7 | X16: =iferror(XLOOKUP(M16, $AK$2:$AK$6,$AL$2:$AL$6), 0) -> 1 | Y16: =iferror(XLOOKUP(N16, $AM$2:$AM$6,$AN$2:$AN$6), 0) -> 2 | Z16: =iferror(XLOOKUP(O16, $AO$2:$AO$6,$AP$2:$AP$6), 0) -> 3.5
A17: Nick Josifek | B17: Idaho | C17: Y | D17: =ifs(P17 = 0, "",P17<3.25, "G5 Backup QB", P17<3.75, "G5 Spot Starting QB",P17 < 4.25, "G5 Starter QB",P17 < 4.5, "P4 Spot Starting QB", P17 >= 4.5, "P4 Starter QB" ) -> G5 Starter QB | E17: =If(T17>4.2, "Vertical Passing, ","Short/Intermediate, ")&if(U17>4.2, "Full-Field Progression Offense", "Half-Field Progression") -> Short/Intermediate, Half-Field Progression | G17: =IFS(AND(Q17<-1, T17<4), "Chain Mover w/Arm or Leg", AND(T17>5, Z17>5), "Elite Athlete at QB", AND(T17>5, X17<2.5), "Statue In Pocket Passer", AND(T17>5, X17<4), "Pocket Passer", AND(P17<4, Q17>1), "Chain Mover w/Arm", AND(T17>3, Z17>3), "Functional Athlete at QB") -> Functional Athlete at QB | I17: Ball Dips, Any Platform | J17: Telegraphs Reads Post Snap | K17: Can Hit, Struggles In Tight Windows | L17: Anticipates Throw, Ball Is In Defender's Reach | M17: Likely to Bail From Clean Pocket | N17: Moves But Easily Chased By Defenders | O17: Gets Yard In Open Space | P17: =iferror((sum(T17:W17)*1.1+sum(X17:Z17)*0.9)/7,0) -> 3.8771429 | Q17: =(sum(T17:W17)-sum(X17:Z17)*1.3) -> -0.11 | T17: =iferror(XLOOKUP(I17, $AC$2:$AC$6,$AD$2:$AD$6), 0) -> 4.2 | U17: =iferror(XLOOKUP(J17, $AE$2:$AE$6,$AF$2:$AF$6), 0) -> 2.8 | V17: =iferror(XLOOKUP(K17, $AG$2:$AG$6,$AH$2:$AH$6), 0) -> 4.6 | W17: =iferror(XLOOKUP(L17, $AI$2:$AI$6,$AJ$2:$AJ$6), 0) -> 3.5 | X17: =iferror(XLOOKUP(M17, $AK$2:$AK$6,$AL$2:$AL$6), 0) -> 4.2 | Y17: =iferror(XLOOKUP(N17, $AM$2:$AM$6,$AN$2:$AN$6), 0) -> 4 | Z17: =iferror(XLOOKUP(O17, $AO$2:$AO$6,$AP$2:$AP$6), 0) -> 3.5
A18: Ean Rodrigue | B18: Nicholls St | C18: N | D18: =ifs(P18 = 0, "",P18<3.25, "G5 Backup QB", P18<3.75, "G5 Spot Starting QB",P18 < 4.25, "G5 Starter QB",P18 < 4.5, "P4 Spot Starting QB", P18 >= 4.5, "P4 Starter QB" ) -> P4 Spot Starting QB | E18: =If(T18>4.2, "Vertical Passing, ","Short/Intermediate, ")&if(U18>4.2, "Full-Field Progression Offense", "Half-Field Progression") -> Short/Intermediate, Half-Field Progression | G18: =IFS(AND(Q18<-1, T18<4), "Chain Mover w/Arm or Leg", AND(T18>5, Z18>5), "Elite Athlete at QB", AND(T18>5, X18<2.5), "Statue In Pocket Passer", AND(T18>5, X18<4), "Pocket Passer", AND(P18<4, Q18>1), "Chain Mover w/Arm", AND(T18>3, Z18>3), "Functional Athlete at QB") -> Functional Athlete at QB | I18: Ball Dips, Any Platform | J18: Correctly Deciphers Half Field Reads | K18: Can Hit, Struggles In Tight Windows | L18: Anticipates Throw, Ball Is In Defender's Reach | M18: Can Move Around But Doesn't Always Anticipate Pressure | N18: Moves But Easily Chased By Defenders | O18: Gets Yard In Open Space | P18: =iferror((sum(T18:W18)*1.1+sum(X18:Z18)*0.9)/7,0) -> 4.2771429 | Q18: =(sum(T18:W18)-sum(X18:Z18)*1.3) -> -0.53 | T18: =iferror(XLOOKUP(I18, $AC$2:$AC$6,$AD$2:$AD$6), 0) -> 4.2 | U18: =iferror(XLOOKUP(J18, $AE$2:$AE$6,$AF$2:$AF$6), 0) -> 4.2 | V18: =iferror(XLOOKUP(K18, $AG$2:$AG$6,$AH$2:$AH$6), 0) -> 4.6 | W18: =iferror(XLOOKUP(L18, $AI$2:$AI$6,$AJ$2:$AJ$6), 0) -> 3.5 | X18: =iferror(XLOOKUP(M18, $AK$2:$AK$6,$AL$2:$AL$6), 0) -> 5.6 | Y18: =iferror(XLOOKUP(N18, $AM$2:$AM$6,$AN$2:$AN$6), 0) -> 4 | Z18: =iferror(XLOOKUP(O18, $AO$2:$AO$6,$AP$2:$AP$6), 0) -> 3.5
A19: Kirk Francis | B19: Tulsa | C19: Y | D19: =ifs(P19 = 0, "",P19<3.25, "G5 Backup QB", P19<3.75, "G5 Spot Starting QB",P19 < 4.25, "G5 Starter QB",P19 < 4.5, "P4 Spot Starting QB", P19 >= 4.5, "P4 Starter QB" ) | P19: =iferror((sum(T19:W19)*1.1+sum(X19:Z19)*0.9)/7,0) -> 0 | Q19: =(sum(T19:W19)-sum(X19:Z19)*1.3) -> 0 | T19: =iferror(XLOOKUP(I19, $AC$2:$AC$6,$AD$2:$AD$6), 0) -> 0 | U19: =iferror(XLOOKUP(J19, $AE$2:$AE$6,$AF$2:$AF$6), 0) -> 0 | V19: =iferror(XLOOKUP(K19, $AG$2:$AG$6,$AH$2:$AH$6), 0) -> 0 | W19: =iferror(XLOOKUP(L19, $AI$2:$AI$6,$AJ$2:$AJ$6), 0) -> 0 | X19: =iferror(XLOOKUP(M19, $AK$2:$AK$6,$AL$2:$AL$6), 0) -> 0 | Y19: =iferror(XLOOKUP(N19, $AM$2:$AM$6,$AN$2:$AN$6), 0) -> 0 | Z19: =iferror(XLOOKUP(O19, $AO$2:$AO$6,$AP$2:$AP$6), 0) -> 0
A20: Liam O'Brien | B20: Penn | C20: Y | D20: =ifs(P20 = 0, "",P20<3.25, "G5 Backup QB", P20<3.75, "G5 Spot Starting QB",P20 < 4.25, "G5 Starter QB",P20 < 4.5, "P4 Spot Starting QB", P20 >= 4.5, "P4 Starter QB" ) -> G5 Spot Starting QB | E20: =If(T20>4.2, "Vertical Passing, ","Short/Intermediate, ")&if(U20>4.2, "Full-Field Progression Offense", "Half-Field Progression") -> Vertical Passing, Half-Field Progression | G20: =IFS(AND(Q20<-1, T20<4), "Chain Mover w/Arm or Leg", AND(T20>5, Z20>5), "Elite Athlete at QB", AND(T20>5, X20<2.5), "Statue In Pocket Passer", AND(T20>5, X20<4), "Pocket Passer", AND(P20<4, Q20>1), "Chain Mover w/Arm", AND(T20>3, Z20>3), "Functional Athlete at QB") -> Statue In Pocket Passer | I20: Any Throw, Firm Base | J20: Telegraphs Reads Post Snap | K20: Can Hit, Struggles In Tight Windows | L20: Anticipates Throw, Ball Is In Defender's Reach | M20: Statue In Pocket | N20: Moves But Easily Chased By Defenders | O20: Gets Yard In Open Space | P20: =iferror((sum(T20:W20)*1.1+sum(X20:Z20)*0.9)/7,0) -> 3.6857143 | Q20: =(sum(T20:W20)-sum(X20:Z20)*1.3) -> 5.45 | T20: =iferror(XLOOKUP(I20, $AC$2:$AC$6,$AD$2:$AD$6), 0) -> 5.6 | U20: =iferror(XLOOKUP(J20, $AE$2:$AE$6,$AF$2:$AF$6), 0) -> 2.8 | V20: =iferror(XLOOKUP(K20, $AG$2:$AG$6,$AH$2:$AH$6), 0) -> 4.6 | W20: =iferror(XLOOKUP(L20, $AI$2:$AI$6,$AJ$2:$AJ$6), 0) -> 3.5 | X20: =iferror(XLOOKUP(M20, $AK$2:$AK$6,$AL$2:$AL$6), 0) -> 1 | Y20: =iferror(XLOOKUP(N20, $AM$2:$AM$6,$AN$2:$AN$6), 0) -> 4 | Z20: =iferror(XLOOKUP(O20, $AO$2:$AO$6,$AP$2:$AP$6), 0) -> 3.5
A21: Coulter Cleland | B21: Davidson | C21: Y | D21: =ifs(P21 = 0, "",P21<3.25, "G5 Backup QB", P21<3.75, "G5 Spot Starting QB",P21 < 4.25, "G5 Starter QB",P21 < 4.5, "P4 Spot Starting QB", P21 >= 4.5, "P4 Starter QB" ) -> G5 Starter QB | E21: =If(T21>4.2, "Vertical Passing, ","Short/Intermediate, ")&if(U21>4.2, "Full-Field Progression Offense", "Half-Field Progression") -> Short/Intermediate, Half-Field Progression | G21: =IFS(AND(Q21<-1, T21<4), "Chain Mover w/Arm or Leg", AND(T21>5, Z21>5), "Elite Athlete at QB", AND(T21>5, X21<2.5), "Statue In Pocket Passer", AND(T21>5, X21<4), "Pocket Passer", AND(P21<4, Q21>1), "Chain Mover w/Arm", AND(T21>3, Z21>3), "Functional Athlete at QB") -> Chain Mover w/Arm or Leg | I21: Ball Dips, Firm Base | J21: Telegraphs Reads Post Snap | K21: Can Hit, Struggles In Tight Windows | L21: Anticipates Throw, Ball Is In Defender's Reach | M21: Quick Twitch, Anticipates, Escapes Tight Pocket | N21: Moves But Easily Chased By Defenders | O21: Gets Yard In Open Space | P21: =iferror((sum(T21:W21)*1.1+sum(X21:Z21)*0.9)/7,0) -> 4.0171429 | Q21: =(sum(T21:W21)-sum(X21:Z21)*1.3) -> -5.15 | T21: =iferror(XLOOKUP(I21, $AC$2:$AC$6,$AD$2:$AD$6), 0) -> 2.8 | U21: =iferror(XLOOKUP(J21, $AE$2:$AE$6,$AF$2:$AF$6), 0) -> 2.8 | V21: =iferror(XLOOKUP(K21, $AG$2:$AG$6,$AH$2:$AH$6), 0) -> 4.6 | W21: =iferror(XLOOKUP(L21, $AI$2:$AI$6,$AJ$2:$AJ$6), 0) -> 3.5 | X21: =iferror(XLOOKUP(M21, $AK$2:$AK$6,$AL$2:$AL$6), 0) -> 7 | Y21: =iferror(XLOOKUP(N21, $AM$2:$AM$6,$AN$2:$AN$6), 0) -> 4 | Z21: =iferror(XLOOKUP(O21, $AO$2:$AO$6,$AP$2:$AP$6), 0) -> 3.5
A22: Dez Thomas | B22: Georgetown | C22: Y | D22: =ifs(P22 = 0, "",P22<3.25, "G5 Backup QB", P22<3.75, "G5 Spot Starting QB",P22 < 4.25, "G5 Starter QB",P22 < 4.5, "P4 Spot Starting QB", P22 >= 4.5, "P4 Starter QB" ) -> G5 Backup QB | E22: =If(T22>4.2, "Vertical Passing, ","Short/Intermediate, ")&if(U22>4.2, "Full-Field Progression Offense", "Half-Field Progression") -> Short/Intermediate, Half-Field Progression | G22: =IFS(AND(Q22<-1, T22<4), "Chain Mover w/Arm or Leg", AND(T22>5, Z22>5), "Elite Athlete at QB", AND(T22>5, X22<2.5), "Statue In Pocket Passer", AND(T22>5, X22<4), "Pocket Passer", AND(P22<4, Q22>1), "Chain Mover w/Arm", AND(T22>3, Z22>3), "Functional Athlete at QB") -> Chain Mover w/Arm or Leg | I22: Ball Dips, Firm Base | J22: Telegraphs Reads Post Snap | K22: Timing Is Off | L22: Ball Dips To Open Receiver | M22: Likely to Bail From Clean Pocket | N22: Moves But Easily Chased By Defenders | O22: Gets Yard In Open Space | P22: =iferror((sum(T22:W22)*1.1+sum(X22:Z22)*0.9)/7,0) -> 3.0259471 | Q22: =(sum(T22:W22)-sum(X22:Z22)*1.3) -> -5.5267 | T22: =iferror(XLOOKUP(I22, $AC$2:$AC$6,$AD$2:$AD$6), 0) -> 2.8 | U22: =iferror(XLOOKUP(J22, $AE$2:$AE$6,$AF$2:$AF$6), 0) -> 2.8 | V22: =iferror(XLOOKUP(K22, $AG$2:$AG$6,$AH$2:$AH$6), 0) -> 2.3333 | W22: =iferror(XLOOKUP(L22, $AI$2:$AI$6,$AJ$2:$AJ$6), 0) -> 1.75 | X22: =iferror(XLOOKUP(M22, $AK$2:$AK$6,$AL$2:$AL$6), 0) -> 4.2 | Y22: =iferror(XLOOKUP(N22, $AM$2:$AM$6,$AN$2:$AN$6), 0) -> 4 | Z22: =iferror(XLOOKUP(O22, $AO$2:$AO$6,$AP$2:$AP$6), 0) -> 3.5
A23: Sonny Mannino | B23: Marist | C23: Y | D23: =ifs(P23 = 0, "",P23<3.25, "G5 Backup QB", P23<3.75, "G5 Spot Starting QB",P23 < 4.25, "G5 Starter QB",P23 < 4.5, "P4 Spot Starting QB", P23 >= 4.5, "P4 Starter QB" ) -> G5 Starter QB | E23: =If(T23>4.2, "Vertical Passing, ","Short/Intermediate, ")&if(U23>4.2, "Full-Field Progression Offense", "Half-Field Progression") -> Vertical Passing, Half-Field Progression | G23: =IFS(AND(Q23<-1, T23<4), "Chain Mover w/Arm or Leg", AND(T23>5, Z23>5), "Elite Athlete at QB", AND(T23>5, X23<2.5), "Statue In Pocket Passer", AND(T23>5, X23<4), "Pocket Passer", AND(P23<4, Q23>1), "Chain Mover w/Arm", AND(T23>3, Z23>3), "Functional Athlete at QB") -> Pocket Passer | I23: Any Throw, Any Platform | J23: Telegraphs Reads Post Snap | K23: Timing Is Off | L23: Frequently Hits Hole Shots | M23: Throws Thru Pressure | N23: Moves But Easily Chased By Defenders | O23: Gets Yard In Open Space | P23: =iferror((sum(T23:W23)*1.1+sum(X23:Z23)*0.9)/7,0) -> 4.0559471 | Q23: =(sum(T23:W23)-sum(X23:Z23)*1.3) -> 3.9933 | T23: =iferror(XLOOKUP(I23, $AC$2:$AC$6,$AD$2:$AD$6), 0) -> 7 | U23: =iferror(XLOOKUP(J23, $AE$2:$AE$6,$AF$2:$AF$6), 0) -> 2.8 | V23: =iferror(XLOOKUP(K23, $AG$2:$AG$6,$AH$2:$AH$6), 0) -> 2.3333 | W23: =iferror(XLOOKUP(L23, $AI$2:$AI$6,$AJ$2:$AJ$6), 0) -> 5.25 | X23: =iferror(XLOOKUP(M23, $AK$2:$AK$6,$AL$2:$AL$6), 0) -> 2.8 | Y23: =iferror(XLOOKUP(N23, $AM$2:$AM$6,$AN$2:$AN$6), 0) -> 4 | Z23: =iferror(XLOOKUP(O23, $AO$2:$AO$6,$AP$2:$AP$6), 0) -> 3.5
A24: Colton Joseph | B24: Old Dominion | C24: Y | D24: =ifs(P24 = 0, "",P24<3.25, "G5 Backup QB", P24<3.75, "G5 Spot Starting QB",P24 < 4.25, "G5 Starter QB",P24 < 4.5, "P4 Spot Starting QB", P24 >= 4.5, "P4 Starter QB" ) -> P4 Starter QB | E24: =If(T24>4.2, "Vertical Passing, ","Short/Intermediate, ")&if(U24>4.2, "Full-Field Progression Offense", "Half-Field Progression") -> Short/Intermediate, Half-Field Progression | G24: =IFS(AND(Q24<-1, T24<4), "Chain Mover w/Arm or Leg", AND(T24>5, Z24>5), "Elite Athlete at QB", AND(T24>5, X24<2.5), "Statue In Pocket Passer", AND(T24>5, X24<4), "Pocket Passer", AND(P24<4, Q24>1), "Chain Mover w/Arm", AND(T24>3, Z24>3), "Functional Athlete at QB") -> Functional Athlete at QB | I24: Ball Dips, Any Platform | J24: Correctly Deciphers Half Field Reads | K24: Can Hit, Struggles In Tight Windows | L24: Frequently Hits Hole Shots | M24: Can Move Around But Doesn't Always Anticipate Pressure | N24: Moves But Easily Chased By Defenders | O24: Good Space Eater | P24: =iferror((sum(T24:W24)*1.1+sum(X24:Z24)*0.9)/7,0) -> 4.7771429 | Q24: =(sum(T24:W24)-sum(X24:Z24)*1.3) -> -1.055 | T24: =iferror(XLOOKUP(I24, $AC$2:$AC$6,$AD$2:$AD$6), 0) -> 4.2 | U24: =iferror(XLOOKUP(J24, $AE$2:$AE$6,$AF$2:$AF$6), 0) -> 4.2 | V24: =iferror(XLOOKUP(K24, $AG$2:$AG$6,$AH$2:$AH$6), 0) -> 4.6 | W24: =iferror(XLOOKUP(L24, $AI$2:$AI$6,$AJ$2:$AJ$6), 0) -> 5.25 | X24: =iferror(XLOOKUP(M24, $AK$2:$AK$6,$AL$2:$AL$6), 0) -> 5.6 | Y24: =iferror(XLOOKUP(N24, $AM$2:$AM$6,$AN$2:$AN$6), 0) -> 4 | Z24: =iferror(XLOOKUP(O24, $AO$2:$AO$6,$AP$2:$AP$6), 0) -> 5.25
A25: Raymond Moore III | B25: Morgan State | C25: Y | D25: =ifs(P25 = 0, "",P25<3.25, "G5 Backup QB", P25<3.75, "G5 Spot Starting QB",P25 < 4.25, "G5 Starter QB",P25 < 4.5, "P4 Spot Starting QB", P25 >= 4.5, "P4 Starter QB" ) -> P4 Spot Starting QB | E25: =If(T25>4.2, "Vertical Passing, ","Short/Intermediate, ")&if(U25>4.2, "Full-Field Progression Offense", "Half-Field Progression") -> Vertical Passing, Half-Field Progression | G25: =IFS(AND(Q25<-1, T25<4), "Chain Mover w/Arm or Leg", AND(T25>5, Z25>5), "Elite Athlete at QB", AND(T25>5, X25<2.5), "Statue In Pocket Passer", AND(T25>5, X25<4), "Pocket Passer", AND(P25<4, Q25>1), "Chain Mover w/Arm", AND(T25>3, Z25>3), "Functional Athlete at QB") -> Elite Athlete at QB | I25: Any Throw, Firm Base | J25: Correctly Deciphers Half Field Reads | K25: Timing Is Off | L25: Anticipates Throw, Ball Is In Defender's Reach | M25: Can Move Around But Doesn't Always Anticipate Pressure | N25: Moves But Easily Chased By Defenders | O25: Good Space Eater | P25: =iferror((sum(T25:W25)*1.1+sum(X25:Z25)*0.9)/7,0) -> 4.3659471 | Q25: =(sum(T25:W25)-sum(X25:Z25)*1.3) -> -3.6717 | T25: =iferror(XLOOKUP(I25, $AC$2:$AC$6,$AD$2:$AD$6), 0) -> 5.6 | U25: =iferror(XLOOKUP(J25, $AE$2:$AE$6,$AF$2:$AF$6), 0) -> 4.2 | V25: =iferror(XLOOKUP(K25, $AG$2:$AG$6,$AH$2:$AH$6), 0) -> 2.3333 | W25: =iferror(XLOOKUP(L25, $AI$2:$AI$6,$AJ$2:$AJ$6), 0) -> 3.5 | X25: =iferror(XLOOKUP(M25, $AK$2:$AK$6,$AL$2:$AL$6), 0) -> 5.6 | Y25: =iferror(XLOOKUP(N25, $AM$2:$AM$6,$AN$2:$AN$6), 0) -> 4 | Z25: =iferror(XLOOKUP(O25, $AO$2:$AO$6,$AP$2:$AP$6), 0) -> 5.25
A26: Jackson Proctor | B26: NIU | C26: Y | D26: =ifs(P26 = 0, "",P26<3.25, "G5 Backup QB", P26<3.75, "G5 Spot Starting QB",P26 < 4.25, "G5 Starter QB",P26 < 4.5, "P4 Spot Starting QB", P26 >= 4.5, "P4 Starter QB" ) -> G5 Starter QB | E26: =If(T26>4.2, "Vertical Passing, ","Short/Intermediate, ")&if(U26>4.2, "Full-Field Progression Offense", "Half-Field Progression") -> Short/Intermediate, Half-Field Progression | G26: =IFS(AND(Q26<-1, T26<4), "Chain Mover w/Arm or Leg", AND(T26>5, Z26>5), "Elite Athlete at QB", AND(T26>5, X26<2.5), "Statue In Pocket Passer", AND(T26>5, X26<4), "Pocket Passer", AND(P26<4, Q26>1), "Chain Mover w/Arm", AND(T26>3, Z26>3), "Functional Athlete at QB") -> Functional Athlete at QB | I26: Ball Dips, Any Platform | J26: Correctly Deciphers Half Field Reads | K26: Can Hit, Struggles In Tight Windows | L26: Anticipates Throw, Ball Is In Defender's Reach | M26: Likely to Bail From Clean Pocket | N26: Moves But Easily Chased By Defenders | O26: Gets Yard In Open Space | P26: =iferror((sum(T26:W26)*1.1+sum(X26:Z26)*0.9)/7,0) -> 4.0971429 | Q26: =(sum(T26:W26)-sum(X26:Z26)*1.3) -> 1.29 | T26: =iferror(XLOOKUP(I26, $AC$2:$AC$6,$AD$2:$AD$6), 0) -> 4.2 | U26: =iferror(XLOOKUP(J26, $AE$2:$AE$6,$AF$2:$AF$6), 0) -> 4.2 | V26: =iferror(XLOOKUP(K26, $AG$2:$AG$6,$AH$2:$AH$6), 0) -> 4.6 | W26: =iferror(XLOOKUP(L26, $AI$2:$AI$6,$AJ$2:$AJ$6), 0) -> 3.5 | X26: =iferror(XLOOKUP(M26, $AK$2:$AK$6,$AL$2:$AL$6), 0) -> 4.2 | Y26: =iferror(XLOOKUP(N26, $AM$2:$AM$6,$AN$2:$AN$6), 0) -> 4 | Z26: =iferror(XLOOKUP(O26, $AO$2:$AO$6,$AP$2:$AP$6), 0) -> 3.5
A27: AJ Hairston | B27: UMass | C27: Y | D27: =ifs(P27 = 0, "",P27<3.25, "G5 Backup QB", P27<3.75, "G5 Spot Starting QB",P27 < 4.25, "G5 Starter QB",P27 < 4.5, "P4 Spot Starting QB", P27 >= 4.5, "P4 Starter QB" ) -> G5 Starter QB | E27: =If(T27>4.2, "Vertical Passing, ","Short/Intermediate, ")&if(U27>4.2, "Full-Field Progression Offense", "Half-Field Progression") -> Vertical Passing, Half-Field Progression | G27: =IFS(AND(Q27<-1, T27<4), "Chain Mover w/Arm or Leg", AND(T27>5, Z27>5), "Elite Athlete at QB", AND(T27>5, X27<2.5), "Statue In Pocket Passer", AND(T27>5, X27<4), "Pocket Passer", AND(P27<4, Q27>1), "Chain Mover w/Arm", AND(T27>3, Z27>3), "Functional Athlete at QB") -> Statue In Pocket Passer | I27: Any Throw, Firm Base | J27: Telegraphs Reads Post Snap | K27: Can Hit, Struggles In Tight Windows | L27: No Velocity Dip On Field Side Throws | M27: Statue In Pocket | N27: Moves But Easily Chased By Defenders | O27: Gets Yard In Open Space | P27: =iferror((sum(T27:W27)*1.1+sum(X27:Z27)*0.9)/7,0) -> 4.2357143 | Q27: =(sum(T27:W27)-sum(X27:Z27)*1.3) -> 8.95 | T27: =iferror(XLOOKUP(I27, $AC$2:$AC$6,$AD$2:$AD$6), 0) -> 5.6 | U27: =iferror(XLOOKUP(J27, $AE$2:$AE$6,$AF$2:$AF$6), 0) -> 2.8 | V27: =iferror(XLOOKUP(K27, $AG$2:$AG$6,$AH$2:$AH$6), 0) -> 4.6 | W27: =iferror(XLOOKUP(L27, $AI$2:$AI$6,$AJ$2:$AJ$6), 0) -> 7 | X27: =iferror(XLOOKUP(M27, $AK$2:$AK$6,$AL$2:$AL$6), 0) -> 1 | Y27: =iferror(XLOOKUP(N27, $AM$2:$AM$6,$AN$2:$AN$6), 0) -> 4 | Z27: =iferror(XLOOKUP(O27, $AO$2:$AO$6,$AP$2:$AP$6), 0) -> 3.5
A28: Jackson Brousseau | B28: Colorado State | C28: Y | D28: =ifs(P28 = 0, "",P28<3.25, "G5 Backup QB", P28<3.75, "G5 Spot Starting QB",P28 < 4.25, "G5 Starter QB",P28 < 4.5, "P4 Spot Starting QB", P28 >= 4.5, "P4 Starter QB" ) -> P4 Spot Starting QB | E28: =If(T28>4.2, "Vertical Passing, ","Short/Intermediate, ")&if(U28>4.2, "Full-Field Progression Offense", "Half-Field Progression") -> Vertical Passing, Half-Field Progression | G28: =IFS(AND(Q28<-1, T28<4), "Chain Mover w/Arm or Leg", AND(T28>5, Z28>5), "Elite Athlete at QB", AND(T28>5, X28<2.5), "Statue In Pocket Passer", AND(T28>5, X28<4), "Pocket Passer", AND(P28<4, Q28>1), "Chain Mover w/Arm", AND(T28>3, Z28>3), "Functional Athlete at QB") -> Functional Athlete at QB | I28: Any Throw, Firm Base | J28: Telegraphs Reads Post Snap | K28: Can Hit, Struggles In Tight Windows | L28: Frequently Hits Hole Shots | M28: Can Move Around But Doesn't Always Anticipate Pressure | N28: Resorts to Throwaway/Expects To Get Hit | O28: Gets Yard In Open Space | P28: =iferror((sum(T28:W28)*1.1+sum(X28:Z28)*0.9)/7,0) -> 4.295 | Q28: =(sum(T28:W28)-sum(X28:Z28)*1.3) -> 3.82 | T28: =iferror(XLOOKUP(I28, $AC$2:$AC$6,$AD$2:$AD$6), 0) -> 5.6 | U28: =iferror(XLOOKUP(J28, $AE$2:$AE$6,$AF$2:$AF$6), 0) -> 2.8 | V28: =iferror(XLOOKUP(K28, $AG$2:$AG$6,$AH$2:$AH$6), 0) -> 4.6 | W28: =iferror(XLOOKUP(L28, $AI$2:$AI$6,$AJ$2:$AJ$6), 0) -> 5.25 | X28: =iferror(XLOOKUP(M28, $AK$2:$AK$6,$AL$2:$AL$6), 0) -> 5.6 | Y28: =iferror(XLOOKUP(N28, $AM$2:$AM$6,$AN$2:$AN$6), 0) -> 2 | Z28: =iferror(XLOOKUP(O28, $AO$2:$AO$6,$AP$2:$AP$6), 0) -> 3.5
A29: Grant Jordan | B29: UMass | C29: Y | D29: =ifs(P29 = 0, "",P29<3.25, "G5 Backup QB", P29<3.75, "G5 Spot Starting QB",P29 < 4.25, "G5 Starter QB",P29 < 4.5, "P4 Spot Starting QB", P29 >= 4.5, "P4 Starter QB" ) -> P4 Starter QB | E29: =If(T29>4.2, "Vertical Passing, ","Short/Intermediate, ")&if(U29>4.2, "Full-Field Progression Offense", "Half-Field Progression") -> Short/Intermediate, Half-Field Progression | G29: =IFS(AND(Q29<-1, T29<4), "Chain Mover w/Arm or Leg", AND(T29>5, Z29>5), "Elite Athlete at QB", AND(T29>5, X29<2.5), "Statue In Pocket Passer", AND(T29>5, X29<4), "Pocket Passer", AND(P29<4, Q29>1), "Chain Mover w/Arm", AND(T29>3, Z29>3), "Functional Athlete at QB") -> Functional Athlete at QB | I29: Ball Dips, Any Platform | J29: Correctly Deciphers Half Field Reads | K29: Can Hit, Struggles In Tight Windows | L29: Anticipates Throw, Ball Is In Defender's Reach | M29: Can Move Around But Doesn't Always Anticipate Pressure | N29: Moves But Easily Chased By Defenders | O29: Good Space Eater | P29: =iferror((sum(T29:W29)*1.1+sum(X29:Z29)*0.9)/7,0) -> 4.5021429 | Q29: =(sum(T29:W29)-sum(X29:Z29)*1.3) -> -2.805 | T29: =iferror(XLOOKUP(I29, $AC$2:$AC$6,$AD$2:$AD$6), 0) -> 4.2 | U29: =iferror(XLOOKUP(J29, $AE$2:$AE$6,$AF$2:$AF$6), 0) -> 4.2 | V29: =iferror(XLOOKUP(K29, $AG$2:$AG$6,$AH$2:$AH$6), 0) -> 4.6 | W29: =iferror(XLOOKUP(L29, $AI$2:$AI$6,$AJ$2:$AJ$6), 0) -> 3.5 | X29: =iferror(XLOOKUP(M29, $AK$2:$AK$6,$AL$2:$AL$6), 0) -> 5.6 | Y29: =iferror(XLOOKUP(N29, $AM$2:$AM$6,$AN$2:$AN$6), 0) -> 4 | Z29: =iferror(XLOOKUP(O29, $AO$2:$AO$6,$AP$2:$AP$6), 0) -> 5.25
A30: Harrison Burch | B30: Kentucky Wesleyan | C30: Y | D30: =ifs(P30 = 0, "",P30<3.25, "G5 Backup QB", P30<3.75, "G5 Spot Starting QB",P30 < 4.25, "G5 Starter QB",P30 < 4.5, "P4 Spot Starting QB", P30 >= 4.5, "P4 Starter QB" ) -> G5 Starter QB | E30: =If(T30>4.2, "Vertical Passing, ","Short/Intermediate, ")&if(U30>4.2, "Full-Field Progression Offense", "Half-Field Progression") -> Short/Intermediate, Half-Field Progression | G30: =IFS(AND(Q30<-1, T30<4), "Chain Mover w/Arm or Leg", AND(T30>5, Z30>5), "Elite Athlete at QB", AND(T30>5, X30<2.5), "Statue In Pocket Passer", AND(T30>5, X30<4), "Pocket Passer", AND(P30<4, Q30>1), "Chain Mover w/Arm", AND(T30>3, Z30>3), "Functional Athlete at QB") -> Functional Athlete at QB | I30: Ball Dips, Any Platform | J30: Telegraphs Reads Post Snap | K30: Can Hit, Struggles In Tight Windows | L30: Anticipates Throw, Ball Is In Defender's Reach | M30: Likely to Bail From Clean Pocket | N30: Moves But Easily Chased By Defenders | O30: Gets Yard In Open Space | P30: =iferror((sum(T30:W30)*1.1+sum(X30:Z30)*0.9)/7,0) -> 3.8771429 | Q30: =(sum(T30:W30)-sum(X30:Z30)*1.3) -> -0.11 | T30: =iferror(XLOOKUP(I30, $AC$2:$AC$6,$AD$2:$AD$6), 0) -> 4.2 | U30: =iferror(XLOOKUP(J30, $AE$2:$AE$6,$AF$2:$AF$6), 0) -> 2.8 | V30: =iferror(XLOOKUP(K30, $AG$2:$AG$6,$AH$2:$AH$6), 0) -> 4.6 | W30: =iferror(XLOOKUP(L30, $AI$2:$AI$6,$AJ$2:$AJ$6), 0) -> 3.5 | X30: =iferror(XLOOKUP(M30, $AK$2:$AK$6,$AL$2:$AL$6), 0) -> 4.2 | Y30: =iferror(XLOOKUP(N30, $AM$2:$AM$6,$AN$2:$AN$6), 0) -> 4 | Z30: =iferror(XLOOKUP(O30, $AO$2:$AO$6,$AP$2:$AP$6), 0) -> 3.5
A31: Collin Hurst | B31: Presbyterian | C31: Y | D31: =ifs(P31 = 0, "",P31<3.25, "G5 Backup QB", P31<3.75, "G5 Spot Starting QB",P31 < 4.25, "G5 Starter QB",P31 < 4.5, "P4 Spot Starting QB", P31 >= 4.5, "P4 Starter QB" ) -> G5 Starter QB | E31: =If(T31>4.2, "Vertical Passing, ","Short/Intermediate, ")&if(U31>4.2, "Full-Field Progression Offense", "Half-Field Progression") -> Short/Intermediate, Full-Field Progression Offense | G31: =IFS(AND(Q31<-1, T31<4), "Chain Mover w/Arm or Leg", AND(T31>5, Z31>5), "Elite Athlete at QB", AND(T31>5, X31<2.5), "Statue In Pocket Passer", AND(T31>5, X31<4), "Pocket Passer", AND(P31<4, Q31>1), "Chain Mover w/Arm", AND(T31>3, Z31>3), "Functional Athlete at QB") -> Functional Athlete at QB | I31: Ball Dips, Any Platform | J31: Will Occasionally Get To 3rd Read | K31: Can Hit, Struggles In Tight Windows | L31: Anticipates Throw, Ball Is In Defender's Reach | M31: Can Move Around But Doesn't Always Anticipate Pressure | N31: Resorts to Throwaway/Expects To Get Hit | O31: Gets Yard In Open Space | P31: =iferror((sum(T31:W31)*1.1+sum(X31:Z31)*0.9)/7,0) -> 4.24 | Q31: =(sum(T31:W31)-sum(X31:Z31)*1.3) -> 3.47 | T31: =iferror(XLOOKUP(I31, $AC$2:$AC$6,$AD$2:$AD$6), 0) -> 4.2 | U31: =iferror(XLOOKUP(J31, $AE$2:$AE$6,$AF$2:$AF$6), 0) -> 5.6 | V31: =iferror(XLOOKUP(K31, $AG$2:$AG$6,$AH$2:$AH$6), 0) -> 4.6 | W31: =iferror(XLOOKUP(L31, $AI$2:$AI$6,$AJ$2:$AJ$6), 0) -> 3.5 | X31: =iferror(XLOOKUP(M31, $AK$2:$AK$6,$AL$2:$AL$6), 0) -> 5.6 | Y31: =iferror(XLOOKUP(N31, $AM$2:$AM$6,$AN$2:$AN$6), 0) -> 2 | Z31: =iferror(XLOOKUP(O31, $AO$2:$AO$6,$AP$2:$AP$6), 0) -> 3.5
... A35: Austin Myers | B35: Central Arkansas | C35: Y | D35: =ifs(P35 = 0, "",P35<3.25, "G5 Backup QB", P35<3.75, "G5 Spot Starting QB",P35 < 4.25, "G5 Starter QB",P35 < 4.5, "P4 Spot Starting QB", P35 >= 4.5, "P4 Starter QB" ) -> G5 Backup QB | E35: =If(T35>4.2, "Vertical Passing, ","Short/Intermediate, ")&if(U35>4.2, "Full-Field Progression Offense", "Half-Field Progression") -> Short/Intermediate, Half-Field Progression | G35: =IFS(AND(Q35<-1, T35<4), "Chain Mover w/Arm or Leg", AND(T35>5, Z35>5), "Elite Athlete at QB", AND(T35>5, X35<2.5), "Statue In Pocket Passer", AND(T35>5, X35<4), "Pocket Passer", AND(P35<4, Q35>1), "Chain Mover w/Arm", AND(T35>3, Z35>3), "Functional Athlete at QB") -> Chain Mover w/Arm | I35: Ball Dips, Firm Base | J35: Telegraphs Reads Post Snap | K35: Timing Is Off | L35: Ball Dips To Open Receiver | M35: Throws Thru Pressure | N35: Resorts to Throwaway/Expects To Get Hit | O35: Looks Reluctant To Run | P35: =iferror((sum(T35:W35)*1.1+sum(X35:Z35)*0.9)/7,0) -> 2.3638043 | Q35: =(sum(T35:W35)-sum(X35:Z35)*1.3) -> 1.1683 | T35: =iferror(XLOOKUP(I35, $AC$2:$AC$6,$AD$2:$AD$6), 0) -> 2.8 | U35: =iferror(XLOOKUP(J35, $AE$2:$AE$6,$AF$2:$AF$6), 0) -> 2.8 | V35: =iferror(XLOOKUP(K35, $AG$2:$AG$6,$AH$2:$AH$6), 0) -> 2.3333 | W35: =iferror(XLOOKUP(L35, $AI$2:$AI$6,$AJ$2:$AJ$6), 0) -> 1.75 | X35: =iferror(XLOOKUP(M35, $AK$2:$AK$6,$AL$2:$AL$6), 0) -> 2.8 | Y35: =iferror(XLOOKUP(N35, $AM$2:$AM$6,$AN$2:$AN$6), 0) -> 2 | Z35: =iferror(XLOOKUP(O35, $AO$2:$AO$6,$AP$2:$AP$6), 0) -> 1.75
A36: Dexter Williams | B36: Kennesaw State | C36: Y | D36: =ifs(P36 = 0, "",P36<3.25, "G5 Backup QB", P36<3.75, "G5 Spot Starting QB",P36 < 4.25, "G5 Starter QB",P36 < 4.5, "P4 Spot Starting QB", P36 >= 4.5, "P4 Starter QB" ) | P36: =iferror((sum(T36:W36)*1.1+sum(X36:Z36)*0.9)/7,0) -> 0 | Q36: =(sum(T36:W36)-sum(X36:Z36)*1.3) -> 0 | T36: =iferror(XLOOKUP(I36, $AC$2:$AC$6,$AD$2:$AD$6), 0) -> 0 | U36: =iferror(XLOOKUP(J36, $AE$2:$AE$6,$AF$2:$AF$6), 0) -> 0 | V36: =iferror(XLOOKUP(K36, $AG$2:$AG$6,$AH$2:$AH$6), 0) -> 0 | W36: =iferror(XLOOKUP(L36, $AI$2:$AI$6,$AJ$2:$AJ$6), 0) -> 0 | X36: =iferror(XLOOKUP(M36, $AK$2:$AK$6,$AL$2:$AL$6), 0) -> 0 | Y36: =iferror(XLOOKUP(N36, $AM$2:$AM$6,$AN$2:$AN$6), 0) -> 0 | Z36: =iferror(XLOOKUP(O36, $AO$2:$AO$6,$AP$2:$AP$6), 0) -> 0
A37: Trey Hedden | B37: Furman | C37: Y | D37: =ifs(P37 = 0, "",P37<3.25, "G5 Backup QB", P37<3.75, "G5 Spot Starting QB",P37 < 4.25, "G5 Starter QB",P37 < 4.5, "P4 Spot Starting QB", P37 >= 4.5, "P4 Starter QB" ) -> P4 Spot Starting QB | E37: =If(T37>4.2, "Vertical Passing, ","Short/Intermediate, ")&if(U37>4.2, "Full-Field Progression Offense", "Half-Field Progression") -> Vertical Passing, Full-Field Progression Offense | G37: =IFS(AND(Q37<-1, T37<4), "Chain Mover w/Arm or Leg", AND(T37>5, Z37>5), "Elite Athlete at QB", AND(T37>5, X37<2.5), "Statue In Pocket Passer", AND(T37>5, X37<4), "Pocket Passer", AND(P37<4, Q37>1), "Chain Mover w/Arm", AND(T37>3, Z37>3), "Functional Athlete at QB") -> Pocket Passer | I37: Any Throw, Firm Base | J37: Will Occasionally Get To 3rd Read | K37: Consistent Seam Beater | L37: Anticipates Throw, Ball Is In Defender's Reach | M37: Throws Thru Pressure | N37: Resorts to Throwaway/Expects To Get Hit | O37: Looks Reluctant To Run | P37: =iferror((sum(T37:W37)*1.1+sum(X37:Z37)*0.9)/7,0) -> 4.2521429 | Q37: =(sum(T37:W37)-sum(X37:Z37)*1.3) -> 13.185 | T37: =iferror(XLOOKUP(I37, $AC$2:$AC$6,$AD$2:$AD$6), 0) -> 5.6 | U37: =iferror(XLOOKUP(J37, $AE$2:$AE$6,$AF$2:$AF$6), 0) -> 5.6 | V37: =iferror(XLOOKUP(K37, $AG$2:$AG$6,$AH$2:$AH$6), 0) -> 7 | W37: =iferror(XLOOKUP(L37, $AI$2:$AI$6,$AJ$2:$AJ$6), 0) -> 3.5 | X37: =iferror(XLOOKUP(M37, $AK$2:$AK$6,$AL$2:$AL$6), 0) -> 2.8 | Y37: =iferror(XLOOKUP(N37, $AM$2:$AM$6,$AN$2:$AN$6), 0) -> 2 | Z37: =iferror(XLOOKUP(O37, $AO$2:$AO$6,$AP$2:$AP$6), 0) -> 1.75
A38: Katin Houser | B38: East Carolina | C38: Y | D38: =ifs(P38 = 0, "",P38<3.25, "G5 Backup QB", P38<3.75, "G5 Spot Starting QB",P38 < 4.25, "G5 Starter QB",P38 < 4.5, "P4 Spot Starting QB", P38 >= 4.5, "P4 Starter QB" ) | P38: =iferror((sum(T38:W38)*1.1+sum(X38:Z38)*0.9)/7,0) -> 0 | Q38: =(sum(T38:W38)-sum(X38:Z38)*1.3) -> 0 | T38: =iferror(XLOOKUP(I38, $AC$2:$AC$6,$AD$2:$AD$6), 0) -> 0 | U38: =iferror(XLOOKUP(J38, $AE$2:$AE$6,$AF$2:$AF$6), 0) -> 0 | V38: =iferror(XLOOKUP(K38, $AG$2:$AG$6,$AH$2:$AH$6), 0) -> 0 | W38: =iferror(XLOOKUP(L38, $AI$2:$AI$6,$AJ$2:$AJ$6), 0) -> 0 | X38: =iferror(XLOOKUP(M38, $AK$2:$AK$6,$AL$2:$AL$6), 0) -> 0 | Y38: =iferror(XLOOKUP(N38, $AM$2:$AM$6,$AN$2:$AN$6), 0) -> 0 | Z38: =iferror(XLOOKUP(O38, $AO$2:$AO$6,$AP$2:$AP$6), 0) -> 0
A39: Dylan Raiola | B39: Nebraska | C39: Y | D39: =ifs(P39 = 0, "",P39<3.25, "G5 Backup QB", P39<3.75, "G5 Spot Starting QB",P39 < 4.25, "G5 Starter QB",P39 < 4.5, "P4 Spot Starting QB", P39 >= 4.5, "P4 Starter QB" ) -> P4 Starter QB | E39: =If(T39>4.2, "Vertical Passing, ","Short/Intermediate, ")&if(U39>4.2, "Full-Field Progression Offense", "Half-Field Progression") -> Vertical Passing, Full-Field Progression Offense | G39: =IFS(AND(Q39<-1, T39<4), "Chain Mover w/Arm or Leg", AND(T39>5, Z39>5), "Elite Athlete at QB", AND(T39>5, X39<2.5), "Statue In Pocket Passer", AND(T39>5, X39<4), "Pocket Passer", AND(P39<4, Q39>1), "Chain Mover w/Arm", AND(T39>3, Z39>3), "Functional Athlete at QB") -> Functional Athlete at QB | I39: Any Throw, Any Platform | J39: Consistently Works Thru Full-Field Reads | K39: Can Hit, Struggles In Tight Windows | L39: Frequently Hits Hole Shots | M39: Quick Twitch, Anticipates, Escapes Tight Pocket | N39: Resorts to Throwaway/Expects To Get Hit | O39: Gets Yard In Open Space | P39: =iferror((sum(T39:W39)*1.1+sum(X39:Z39)*0.9)/7,0) -> 5.355 | Q39: =(sum(T39:W39)-sum(X39:Z39)*1.3) -> 7.6 | T39: =iferror(XLOOKUP(I39, $AC$2:$AC$6,$AD$2:$AD$6), 0) -> 7 | U39: =iferror(XLOOKUP(J39, $AE$2:$AE$6,$AF$2:$AF$6), 0) -> 7 | V39: =iferror(XLOOKUP(K39, $AG$2:$AG$6,$AH$2:$AH$6), 0) -> 4.6 | W39: =iferror(XLOOKUP(L39, $AI$2:$AI$6,$AJ$2:$AJ$6), 0) -> 5.25 | X39: =iferror(XLOOKUP(M39, $AK$2:$AK$6,$AL$2:$AL$6), 0) -> 7 | Y39: =iferror(XLOOKUP(N39, $AM$2:$AM$6,$AN$2:$AN$6), 0) -> 2 | Z39: =iferror(XLOOKUP(O39, $AO$2:$AO$6,$AP$2:$AP$6), 0) -> 3.5
A40: Brendan Sorsby | B40: Cincinnati | C40: Y | D40: =ifs(P40 = 0, "",P40<3.25, "G5 Backup QB", P40<3.75, "G5 Spot Starting QB",P40 < 4.25, "G5 Starter QB",P40 < 4.5, "P4 Spot Starting QB", P40 >= 4.5, "P4 Starter QB" ) -> P4 Starter QB | E40: =If(T40>4.2, "Vertical Passing, ","Short/Intermediate, ")&if(U40>4.2, "Full-Field Progression Offense", "Half-Field Progression") -> Vertical Passing, Half-Field Progression | G40: =IFS(AND(Q40<-1, T40<4), "Chain Mover w/Arm or Leg", AND(T40>5, Z40>5), "Elite Athlete at QB", AND(T40>5, X40<2.5), "Statue In Pocket Passer", AND(T40>5, X40<4), "Pocket Passer", AND(P40<4, Q40>1), "Chain Mover w/Arm", AND(T40>3, Z40>3), "Functional Athlete at QB") -> Elite Athlete at QB | I40: Any Throw, Any Platform | J40: Correctly Deciphers Half Field Reads | K40: Can Hit, Struggles In Tight Windows | L40: No Velocity Dip On Field Side Throws | M40: Can Move Around But Doesn't Always Anticipate Pressure | N40: Moves But Easily Chased By Defenders | O40: Good Space Eater | P40: =iferror((sum(T40:W40)*1.1+sum(X40:Z40)*0.9)/7,0) -> 5.4921429 | Q40: =(sum(T40:W40)-sum(X40:Z40)*1.3) -> 3.495 | T40: =iferror(XLOOKUP(I40, $AC$2:$AC$6,$AD$2:$AD$6), 0) -> 7 | U40: =iferror(XLOOKUP(J40, $AE$2:$AE$6,$AF$2:$AF$6), 0) -> 4.2 | V40: =iferror(XLOOKUP(K40, $AG$2:$AG$6,$AH$2:$AH$6), 0) -> 4.6 | W40: =iferror(XLOOKUP(L40, $AI$2:$AI$6,$AJ$2:$AJ$6), 0) -> 7 | X40: =iferror(XLOOKUP(M40, $AK$2:$AK$6,$AL$2:$AL$6), 0) -> 5.6 | Y40: =iferror(XLOOKUP(N40, $AM$2:$AM$6,$AN$2:$AN$6), 0) -> 4 | Z40: =iferror(XLOOKUP(O40, $AO$2:$AO$6,$AP$2:$AP$6), 0) -> 5.25
A41: Skyler Locklear | B41: UTEP | C41: Y | D41: =ifs(P41 = 0, "",P41<3.25, "G5 Backup QB", P41<3.75, "G5 Spot Starting QB",P41 < 4.25, "G5 Starter QB",P41 < 4.5, "P4 Spot Starting QB", P41 >= 4.5, "P4 Starter QB" ) -> P4 Spot Starting QB | E41: =If(T41>4.2, "Vertical Passing, ","Short/Intermediate, ")&if(U41>4.2, "Full-Field Progression Offense", "Half-Field Progression") -> Short/Intermediate, Half-Field Progression | G41: =IFS(AND(Q41<-1, T41<4), "Chain Mover w/Arm or Leg", AND(T41>5, Z41>5), "Elite Athlete at QB", AND(T41>5, X41<2.5), "Statue In Pocket Passer", AND(T41>5, X41<4), "Pocket Passer", AND(P41<4, Q41>1), "Chain Mover w/Arm", AND(T41>3, Z41>3), "Functional Athlete at QB") -> Functional Athlete at QB | I41: Ball Dips, Any Platform | J41: Correctly Deciphers Half Field Reads | K41: Can Hit, Struggles In Tight Windows | L41: Anticipates Throw, Ball Is In Defender's Reach | M41: Likely to Bail From Clean Pocket | N41: Moves But Easily Chased By Defenders | O41: Good Space Eater | P41: =iferror((sum(T41:W41)*1.1+sum(X41:Z41)*0.9)/7,0) -> 4.3221429 | Q41: =(sum(T41:W41)-sum(X41:Z41)*1.3) -> -0.985 | T41: =iferror(XLOOKUP(I41, $AC$2:$AC$6,$AD$2:$AD$6), 0) -> 4.2 | U41: =iferror(XLOOKUP(J41, $AE$2:$AE$6,$AF$2:$AF$6), 0) -> 4.2 | V41: =iferror(XLOOKUP(K41, $AG$2:$AG$6,$AH$2:$AH$6), 0) -> 4.6 | W41: =iferror(XLOOKUP(L41, $AI$2:$AI$6,$AJ$2:$AJ$6), 0) -> 3.5 | X41: =iferror(XLOOKUP(M41, $AK$2:$AK$6,$AL$2:$AL$6), 0) -> 4.2 | Y41: =iferror(XLOOKUP(N41, $AM$2:$AM$6,$AN$2:$AN$6), 0) -> 4 | Z41: =iferror(XLOOKUP(O41, $AO$2:$AO$6,$AP$2:$AP$6), 0) -> 5.25
A42: Drew Mestemaker | B42: North Texas | C42: Y | D42: =ifs(P42 = 0, "",P42<3.25, "G5 Backup QB", P42<3.75, "G5 Spot Starting QB",P42 < 4.25, "G5 Starter QB",P42 < 4.5, "P4 Spot Starting QB", P42 >= 4.5, "P4 Starter QB" ) -> P4 Starter QB | E42: =If(T42>4.2, "Vertical Passing, ","Short/Intermediate, ")&if(U42>4.2, "Full-Field Progression Offense", "Half-Field Progression") -> Vertical Passing, Full-Field Progression Offense | G42: =IFS(AND(Q42<-1, T42<4), "Chain Mover w/Arm or Leg", AND(T42>5, Z42>5), "Elite Athlete at QB", AND(T42>5, X42<2.5), "Statue In Pocket Passer", AND(T42>5, X42<4), "Pocket Passer", AND(P42<4, Q42>1), "Chain Mover w/Arm", AND(T42>3, Z42>3), "Functional Athlete at QB") -> Statue In Pocket Passer | I42: Any Throw, Any Platform | J42: Consistently Works Thru Full-Field Reads | K42: Consistent Seam Beater | L42: No Velocity Dip On Field Side Throws | M42: Statue In Pocket | N42: Resorts to Throwaway/Expects To Get Hit | O42: Gets Yard In Open Space | P42: =iferror((sum(T42:W42)*1.1+sum(X42:Z42)*0.9)/7,0) -> 5.2357143 | Q42: =(sum(T42:W42)-sum(X42:Z42)*1.3) -> 19.55 | T42: =iferror(XLOOKUP(I42, $AC$2:$AC$6,$AD$2:$AD$6), 0) -> 7 | U42: =iferror(XLOOKUP(J42, $AE$2:$AE$6,$AF$2:$AF$6), 0) -> 7 | V42: =iferror(XLOOKUP(K42, $AG$2:$AG$6,$AH$2:$AH$6), 0) -> 7 | W42: =iferror(XLOOKUP(L42, $AI$2:$AI$6,$AJ$2:$AJ$6), 0) -> 7 | X42: =iferror(XLOOKUP(M42, $AK$2:$AK$6,$AL$2:$AL$6), 0) -> 1 | Y42: =iferror(XLOOKUP(N42, $AM$2:$AM$6,$AN$2:$AN$6), 0) -> 2 | Z42: =iferror(XLOOKUP(O42, $AO$2:$AO$6,$AP$2:$AP$6), 0) -> 3.5
A43: Sam Leavitt | B43: Arizona State | C43: Y | D43: =ifs(P43 = 0, "",P43<3.25, "G5 Backup QB", P43<3.75, "G5 Spot Starting QB",P43 < 4.25, "G5 Starter QB",P43 < 4.5, "P4 Spot Starting QB", P43 >= 4.5, "P4 Starter QB" ) -> P4 Spot Starting QB | E43: =If(T43>4.2, "Vertical Passing, ","Short/Intermediate, ")&if(U43>4.2, "Full-Field Progression Offense", "Half-Field Progression") -> Vertical Passing, Half-Field Progression | G43: =IFS(AND(Q43<-1, T43<4), "Chain Mover w/Arm or Leg", AND(T43>5, Z43>5), "Elite Athlete at QB", AND(T43>5, X43<2.5), "Statue In Pocket Passer", AND(T43>5, X43<4), "Pocket Passer", AND(P43<4, Q43>1), "Chain Mover w/Arm", AND(T43>3, Z43>3), "Functional Athlete at QB") -> Elite Athlete at QB | I43: Any Throw, Firm Base | J43: Telegraphs Reads Post Snap | K43: Timing Is Off | L43: Frequently Hits Hole Shots | M43: Likely to Bail From Clean Pocket | N43: Makes Defenders Miss/Anticipatory Vision | O43: Good Space Eater | P43: =iferror((sum(T43:W43)*1.1+sum(X43:Z43)*0.9)/7,0) -> 4.49809 | Q43: =(sum(T43:W43)-sum(X43:Z43)*1.3) -> -4.1017 | T43: =iferror(XLOOKUP(I43, $AC$2:$AC$6,$AD$2:$AD$6), 0) -> 5.6 | U43: =iferror(XLOOKUP(J43, $AE$2:$AE$6,$AF$2:$AF$6), 0) -> 2.8 | V43: =iferror(XLOOKUP(K43, $AG$2:$AG$6,$AH$2:$AH$6), 0) -> 2.3333 | W43: =iferror(XLOOKUP(L43, $AI$2:$AI$6,$AJ$2:$AJ$6), 0) -> 5.25 | X43: =iferror(XLOOKUP(M43, $AK$2:$AK$6,$AL$2:$AL$6), 0) -> 4.2 | Y43: =iferror(XLOOKUP(N43, $AM$2:$AM$6,$AN$2:$AN$6), 0) -> 6 | Z43: =iferror(XLOOKUP(O43, $AO$2:$AO$6,$AP$2:$AP$6), 0) -> 5.25
A44: JJ Kohl | B44: App State | C44: Y | D44: =ifs(P44 = 0, "",P44<3.25, "G5 Backup QB", P44<3.75, "G5 Spot Starting QB",P44 < 4.25, "G5 Starter QB",P44 < 4.5, "P4 Spot Starting QB", P44 >= 4.5, "P4 Starter QB" ) -> G5 Starter QB | E44: =If(T44>4.2, "Vertical Passing, ","Short/Intermediate, ")&if(U44>4.2, "Full-Field Progression Offense", "Half-Field Progression") -> Vertical Passing, Half-Field Progression | G44: =IFS(AND(Q44<-1, T44<4), "Chain Mover w/Arm or Leg", AND(T44>5, Z44>5), "Elite Athlete at QB", AND(T44>5, X44<2.5), "Statue In Pocket Passer", AND(T44>5, X44<4), "Pocket Passer", AND(P44<4, Q44>1), "Chain Mover w/Arm", AND(T44>3, Z44>3), "Functional Athlete at QB") -> Pocket Passer | I44: Any Throw, Firm Base | J44: Correctly Deciphers Half Field Reads | K44: Can Hit, Struggles In Tight Windows | L44: Frequently Hits Hole Shots | M44: Throws Thru Pressure | N44: Resorts to Throwaway/Expects To Get Hit | O44: Gets Yard In Open Space | P44: =iferror((sum(T44:W44)*1.1+sum(X44:Z44)*0.9)/7,0) -> 4.155 | Q44: =(sum(T44:W44)-sum(X44:Z44)*1.3) -> 8.86 | T44: =iferror(XLOOKUP(I44, $AC$2:$AC$6,$AD$2:$AD$6), 0) -> 5.6 | U44: =iferror(XLOOKUP(J44, $AE$2:$AE$6,$AF$2:$AF$6), 0) -> 4.2 | V44: =iferror(XLOOKUP(K44, $AG$2:$AG$6,$AH$2:$AH$6), 0) -> 4.6 | W44: =iferror(XLOOKUP(L44, $AI$2:$AI$6,$AJ$2:$AJ$6), 0) -> 5.25 | X44: =iferror(XLOOKUP(M44, $AK$2:$AK$6,$AL$2:$AL$6), 0) -> 2.8 | Y44: =iferror(XLOOKUP(N44, $AM$2:$AM$6,$AN$2:$AN$6), 0) -> 2 | Z44: =iferror(XLOOKUP(O44, $AO$2:$AO$6,$AP$2:$AP$6), 0) -> 3.5
A45: Tayven Jackson | B45: UCF | C45: Y | D45: =ifs(P45 = 0, "",P45<3.25, "G5 Backup QB", P45<3.75, "G5 Spot Starting QB",P45 < 4.25, "G5 Starter QB",P45 < 4.5, "P4 Spot Starting QB", P45 >= 4.5, "P4 Starter QB" ) | P45: =iferror((sum(T45:W45)*1.1+sum(X45:Z45)*0.9)/7,0) -> 0 | Q45: =(sum(T45:W45)-sum(X45:Z45)*1.3) -> 0 | T45: =iferror(XLOOKUP(I45, $AC$2:$AC$6,$AD$2:$AD$6), 0) -> 0 | U45: =iferror(XLOOKUP(J45, $AE$2:$AE$6,$AF$2:$AF$6), 0) -> 0 | V45: =iferror(XLOOKUP(K45, $AG$2:$AG$6,$AH$2:$AH$6), 0) -> 0 | W45: =iferror(XLOOKUP(L45, $AI$2:$AI$6,$AJ$2:$AJ$6), 0) -> 0 | X45: =iferror(XLOOKUP(M45, $AK$2:$AK$6,$AL$2:$AL$6), 0) -> 0 | Y45: =iferror(XLOOKUP(N45, $AM$2:$AM$6,$AN$2:$AN$6), 0) -> 0 | Z45: =iferror(XLOOKUP(O45, $AO$2:$AO$6,$AP$2:$AP$6), 0) -> 0
A46: Nicco Marchiol | B46: West Virginia | C46: Y | D46: =ifs(P46 = 0, "",P46<3.25, "G5 Backup QB", P46<3.75, "G5 Spot Starting QB",P46 < 4.25, "G5 Starter QB",P46 < 4.5, "P4 Spot Starting QB", P46 >= 4.5, "P4 Starter QB" ) -> G5 Starter QB | E46: =If(T46>4.2, "Vertical Passing, ","Short/Intermediate, ")&if(U46>4.2, "Full-Field Progression Offense", "Half-Field Progression") -> Short/Intermediate, Half-Field Progression | G46: =IFS(AND(Q46<-1, T46<4), "Chain Mover w/Arm or Leg", AND(T46>5, Z46>5), "Elite Athlete at QB", AND(T46>5, X46<2.5), "Statue In Pocket Passer", AND(T46>5, X46<4), "Pocket Passer", AND(P46<4, Q46>1), "Chain Mover w/Arm", AND(T46>3, Z46>3), "Functional Athlete at QB") -> Functional Athlete at QB | I46: Ball Dips, Any Platform | J46: Telegraphs Reads Post Snap | K46: Can Hit, Struggles In Tight Windows | L46: Anticipates Throw, Ball Is In Defender's Reach | M46: Likely to Bail From Clean Pocket | N46: Moves But Easily Chased By Defenders | O46: Gets Yard In Open Space | P46: =iferror((sum(T46:W46)*1.1+sum(X46:Z46)*0.9)/7,0) -> 3.8771429 | Q46: =(sum(T46:W46)-sum(X46:Z46)*1.3) -> -0.11 | T46: =iferror(XLOOKUP(I46, $AC$2:$AC$6,$AD$2:$AD$6), 0) -> 4.2 | U46: =iferror(XLOOKUP(J46, $AE$2:$AE$6,$AF$2:$AF$6), 0) -> 2.8 | V46: =iferror(XLOOKUP(K46, $AG$2:$AG$6,$AH$2:$AH$6), 0) -> 4.6 | W46: =iferror(XLOOKUP(L46, $AI$2:$AI$6,$AJ$2:$AJ$6), 0) -> 3.5 | X46: =iferror(XLOOKUP(M46, $AK$2:$AK$6,$AL$2:$AL$6), 0) -> 4.2 | Y46: =iferror(XLOOKUP(N46, $AM$2:$AM$6,$AN$2:$AN$6), 0) -> 4 | Z46: =iferror(XLOOKUP(O46, $AO$2:$AO$6,$AP$2:$AP$6), 0) -> 3.5
A47: Josh Hoover | B47: TCU | C47: Y | D47: =ifs(P47 = 0, "",P47<3.25, "G5 Backup QB", P47<3.75, "G5 Spot Starting QB",P47 < 4.25, "G5 Starter QB",P47 < 4.5, "P4 Spot Starting QB", P47 >= 4.5, "P4 Starter QB" ) -> P4 Starter QB | E47: =If(T47>4.2, "Vertical Passing, ","Short/Intermediate, ")&if(U47>4.2, "Full-Field Progression Offense", "Half-Field Progression") -> Vertical Passing, Half-Field Progression | G47: =IFS(AND(Q47<-1, T47<4), "Chain Mover w/Arm or Leg", AND(T47>5, Z47>5), "Elite Athlete at QB", AND(T47>5, X47<2.5), "Statue In Pocket Passer", AND(T47>5, X47<4), "Pocket Passer", AND(P47<4, Q47>1), "Chain Mover w/Arm", AND(T47>3, Z47>3), "Functional Athlete at QB") -> Functional Athlete at QB | I47: Any Throw, Any Platform | J47: Correctly Deciphers Half Field Reads | K47: Can Hit, Struggles In Tight Windows | L47: Frequently Hits Hole Shots | M47: Can Move Around But Doesn't Always Anticipate Pressure | N47: Moves But Easily Chased By Defenders | O47: Gets Yard In Open Space | P47: =iferror((sum(T47:W47)*1.1+sum(X47:Z47)*0.9)/7,0) -> 4.9921429 | Q47: =(sum(T47:W47)-sum(X47:Z47)*1.3) -> 4.02 | T47: =iferror(XLOOKUP(I47, $AC$2:$AC$6,$AD$2:$AD$6), 0) -> 7 | U47: =iferror(XLOOKUP(J47, $AE$2:$AE$6,$AF$2:$AF$6), 0) -> 4.2 | V47: =iferror(XLOOKUP(K47, $AG$2:$AG$6,$AH$2:$AH$6), 0) -> 4.6 | W47: =iferror(XLOOKUP(L47, $AI$2:$AI$6,$AJ$2:$AJ$6), 0) -> 5.25 | X47: =iferror(XLOOKUP(M47, $AK$2:$AK$6,$AL$2:$AL$6), 0) -> 5.6 | Y47: =iferror(XLOOKUP(N47, $AM$2:$AM$6,$AN$2:$AN$6), 0) -> 4 | Z47: =iferror(XLOOKUP(O47, $AO$2:$AO$6,$AP$2:$AP$6), 0) -> 3.5
A48: DJ Lagway | B48: Florida | C48: Y | D48: =ifs(P48 = 0, "",P48<3.25, "G5 Backup QB", P48<3.75, "G5 Spot Starting QB",P48 < 4.25, "G5 Starter QB",P48 < 4.5, "P4 Spot Starting QB", P48 >= 4.5, "P4 Starter QB" ) -> P4 Starter QB | E48: =If(T48>4.2, "Vertical Passing, ","Short/Intermediate, ")&if(U48>4.2, "Full-Field Progression Offense", "Half-Field Progression") -> Vertical Passing, Half-Field Progression | G48: =IFS(AND(Q48<-1, T48<4), "Chain Mover w/Arm or Leg", AND(T48>5, Z48>5), "Elite Athlete at QB", AND(T48>5, X48<2.5), "Statue In Pocket Passer", AND(T48>5, X48<4), "Pocket Passer", AND(P48<4, Q48>1), "Chain Mover w/Arm", AND(T48>3, Z48>3), "Functional Athlete at QB") -> Functional Athlete at QB | I48: Any Throw, Any Platform | J48: Correctly Deciphers Half Field Reads | K48: Can Hit, Struggles In Tight Windows | L48: No Velocity Dip On Field Side Throws | M48: Can Move Around But Doesn't Always Anticipate Pressure | N48: Moves But Easily Chased By Defenders | O48: Gets Yard In Open Space | P48: =iferror((sum(T48:W48)*1.1+sum(X48:Z48)*0.9)/7,0) -> 5.2671429 | Q48: =(sum(T48:W48)-sum(X48:Z48)*1.3) -> 5.77 | T48: =iferror(XLOOKUP(I48, $AC$2:$AC$6,$AD$2:$AD$6), 0) -> 7 | U48: =iferror(XLOOKUP(J48, $AE$2:$AE$6,$AF$2:$AF$6), 0) -> 4.2 | V48: =iferror(XLOOKUP(K48, $AG$2:$AG$6,$AH$2:$AH$6), 0) -> 4.6 | W48: =iferror(XLOOKUP(L48, $AI$2:$AI$6,$AJ$2:$AJ$6), 0) -> 7 | X48: =iferror(XLOOKUP(M48, $AK$2:$AK$6,$AL$2:$AL$6), 0) -> 5.6 | Y48: =iferror(XLOOKUP(N48, $AM$2:$AM$6,$AN$2:$AN$6), 0) -> 4 | Z48: =iferror(XLOOKUP(O48, $AO$2:$AO$6,$AP$2:$AP$6), 0) -> 3.5
D49: =ifs(P49 = 0, "",P49<3.25, "G5 Backup QB", P49<3.75, "G5 Spot Starting QB",P49 < 4.25, "G5 Starter QB",P49 < 4.5, "P4 Spot Starting QB", P49 >= 4.5, "P4 Starter QB" ) | P49: =iferror((sum(T49:W49)*1.1+sum(X49:Z49)*0.9)/7,0) -> 0 | Q49: =(sum(T49:W49)-sum(X49:Z49)*1.3) -> 0 | T49: =iferror(XLOOKUP(I49, $AC$2:$AC$6,$AD$2:$AD$6), 0) -> 0 | U49: =iferror(XLOOKUP(J49, $AE$2:$AE$6,$AF$2:$AF$6), 0) -> 0 | V49: =iferror(XLOOKUP(K49, $AG$2:$AG$6,$AH$2:$AH$6), 0) -> 0 | W49: =iferror(XLOOKUP(L49, $AI$2:$AI$6,$AJ$2:$AJ$6), 0) -> 0 | X49: =iferror(XLOOKUP(M49, $AK$2:$AK$6,$AL$2:$AL$6), 0) -> 0 | Y49: =iferror(XLOOKUP(N49, $AM$2:$AM$6,$AN$2:$AN$6), 0) -> 0 | Z49: =iferror(XLOOKUP(O49, $AO$2:$AO$6,$AP$2:$AP$6), 0) -> 0
D50: =ifs(P50 = 0, "",P50<3.25, "G5 Backup QB", P50<3.75, "G5 Spot Starting QB",P50 < 4.25, "G5 Starter QB",P50 < 4.5, "P4 Spot Starting QB", P50 >= 4.5, "P4 Starter QB" ) | P50: =iferror((sum(T50:W50)*1.1+sum(X50:Z50)*0.9)/7,0) -> 0 | Q50: =(sum(T50:W50)-sum(X50:Z50)*1.3) -> 0 | T50: =iferror(XLOOKUP(I50, $AC$2:$AC$6,$AD$2:$AD$6), 0) -> 0 | U50: =iferror(XLOOKUP(J50, $AE$2:$AE$6,$AF$2:$AF$6), 0) -> 0 | V50: =iferror(XLOOKUP(K50, $AG$2:$AG$6,$AH$2:$AH$6), 0) -> 0 | W50: =iferror(XLOOKUP(L50, $AI$2:$AI$6,$AJ$2:$AJ$6), 0) -> 0 | X50: =iferror(XLOOKUP(M50, $AK$2:$AK$6,$AL$2:$AL$6), 0) -> 0 | Y50: =iferror(XLOOKUP(N50, $AM$2:$AM$6,$AN$2:$AN$6), 0) -> 0 | Z50: =iferror(XLOOKUP(O50, $AO$2:$AO$6,$AP$2:$AP$6), 0) -> 0
D51: =ifs(P51 = 0, "",P51<3.25, "G5 Backup QB", P51<3.75, "G5 Spot Starting QB",P51 < 4.25, "G5 Starter QB",P51 < 4.5, "P4 Spot Starting QB", P51 >= 4.5, "P4 Starter QB" ) | P51: =iferror((sum(T51:W51)*1.1+sum(X51:Z51)*0.9)/7,0) -> 0 | Q51: =(sum(T51:W51)-sum(X51:Z51)*1.3) -> 0 | T51: =iferror(XLOOKUP(I51, $AC$2:$AC$6,$AD$2:$AD$6), 0) -> 0 | U51: =iferror(XLOOKUP(J51, $AE$2:$AE$6,$AF$2:$AF$6), 0) -> 0 | V51: =iferror(XLOOKUP(K51, $AG$2:$AG$6,$AH$2:$AH$6), 0) -> 0 | W51: =iferror(XLOOKUP(L51, $AI$2:$AI$6,$AJ$2:$AJ$6), 0) -> 0 | X51: =iferror(XLOOKUP(M51, $AK$2:$AK$6,$AL$2:$AL$6), 0) -> 0 | Y51: =iferror(XLOOKUP(N51, $AM$2:$AM$6,$AN$2:$AN$6), 0) -> 0 | Z51: =iferror(XLOOKUP(O51, $AO$2:$AO$6,$AP$2:$AP$6), 0) -> 0
D52: =ifs(P52 = 0, "",P52<3.25, "G5 Backup QB", P52<3.75, "G5 Spot Starting QB",P52 < 4.25, "G5 Starter QB",P52 < 4.5, "P4 Spot Starting QB", P52 >= 4.5, "P4 Starter QB" ) | P52: =iferror((sum(T52:W52)*1.1+sum(X52:Z52)*0.9)/7,0) -> 0 | Q52: =(sum(T52:W52)-sum(X52:Z52)*1.3) -> 0 | T52: =iferror(XLOOKUP(I52, $AC$2:$AC$6,$AD$2:$AD$6), 0) -> 0 | U52: =iferror(XLOOKUP(J52, $AE$2:$AE$6,$AF$2:$AF$6), 0) -> 0 | V52: =iferror(XLOOKUP(K52, $AG$2:$AG$6,$AH$2:$AH$6), 0) -> 0 | W52: =iferror(XLOOKUP(L52, $AI$2:$AI$6,$AJ$2:$AJ$6), 0) -> 0 | X52: =iferror(XLOOKUP(M52, $AK$2:$AK$6,$AL$2:$AL$6), 0) -> 0 | Y52: =iferror(XLOOKUP(N52, $AM$2:$AM$6,$AN$2:$AN$6), 0) -> 0 | Z52: =iferror(XLOOKUP(O52, $AO$2:$AO$6,$AP$2:$AP$6), 0) -> 0
D53: =ifs(P53 = 0, "",P53<3.25, "G5 Backup QB", P53<3.75, "G5 Spot Starting QB",P53 < 4.25, "G5 Starter QB",P53 < 4.5, "P4 Spot Starting QB", P53 >= 4.5, "P4 Starter QB" ) | P53: =iferror((sum(T53:W53)*1.1+sum(X53:Z53)*0.9)/7,0) -> 0 | Q53: =(sum(T53:W53)-sum(X53:Z53)*1.3) -> 0 | T53: =iferror(XLOOKUP(I53, $AC$2:$AC$6,$AD$2:$AD$6), 0) -> 0 | U53: =iferror(XLOOKUP(J53, $AE$2:$AE$6,$AF$2:$AF$6), 0) -> 0 | V53: =iferror(XLOOKUP(K53, $AG$2:$AG$6,$AH$2:$AH$6), 0) -> 0 | W53: =iferror(XLOOKUP(L53, $AI$2:$AI$6,$AJ$2:$AJ$6), 0) -> 0 | X53: =iferror(XLOOKUP(M53, $AK$2:$AK$6,$AL$2:$AL$6), 0) -> 0 | Y53: =iferror(XLOOKUP(N53, $AM$2:$AM$6,$AN$2:$AN$6), 0) -> 0 | Z53: =iferror(XLOOKUP(O53, $AO$2:$AO$6,$AP$2:$AP$6), 0) -> 0
D54: =ifs(P54 = 0, "",P54<3.25, "G5 Backup QB", P54<3.75, "G5 Spot Starting QB",P54 < 4.25, "G5 Starter QB",P54 < 4.5, "P4 Spot Starting QB", P54 >= 4.5, "P4 Starter QB" ) | P54: =iferror((sum(T54:W54)*1.1+sum(X54:Z54)*0.9)/7,0) -> 0 | Q54: =(sum(T54:W54)-sum(X54:Z54)*1.3) -> 0 | T54: =iferror(XLOOKUP(I54, $AC$2:$AC$6,$AD$2:$AD$6), 0) -> 0 | U54: =iferror(XLOOKUP(J54, $AE$2:$AE$6,$AF$2:$AF$6), 0) -> 0 | V54: =iferror(XLOOKUP(K54, $AG$2:$AG$6,$AH$2:$AH$6), 0) -> 0 | W54: =iferror(XLOOKUP(L54, $AI$2:$AI$6,$AJ$2:$AJ$6), 0) -> 0 | X54: =iferror(XLOOKUP(M54, $AK$2:$AK$6,$AL$2:$AL$6), 0) -> 0 | Y54: =iferror(XLOOKUP(N54, $AM$2:$AM$6,$AN$2:$AN$6), 0) -> 0 | Z54: =iferror(XLOOKUP(O54, $AO$2:$AO$6,$AP$2:$AP$6), 0) -> 0
D55: =ifs(P55 = 0, "",P55<3.25, "G5 Backup QB", P55<3.75, "G5 Spot Starting QB",P55 < 4.25, "G5 Starter QB",P55 < 4.5, "P4 Spot Starting QB", P55 >= 4.5, "P4 Starter QB" ) | P55: =iferror((sum(T55:W55)*1.1+sum(X55:Z55)*0.9)/7,0) -> 0 | Q55: =(sum(T55:W55)-sum(X55:Z55)*1.3) -> 0 | T55: =iferror(XLOOKUP(I55, $AC$2:$AC$6,$AD$2:$AD$6), 0) -> 0 | U55: =iferror(XLOOKUP(J55, $AE$2:$AE$6,$AF$2:$AF$6), 0) -> 0 | V55: =iferror(XLOOKUP(K55, $AG$2:$AG$6,$AH$2:$AH$6), 0) -> 0 | W55: =iferror(XLOOKUP(L55, $AI$2:$AI$6,$AJ$2:$AJ$6), 0) -> 0 | X55: =iferror(XLOOKUP(M55, $AK$2:$AK$6,$AL$2:$AL$6), 0) -> 0 | Y55: =iferror(XLOOKUP(N55, $AM$2:$AM$6,$AN$2:$AN$6), 0) -> 0 | Z55: =iferror(XLOOKUP(O55, $AO$2:$AO$6,$AP$2:$AP$6), 0) -> 0
D56: =ifs(P56 = 0, "",P56<3.25, "G5 Backup QB", P56<3.75, "G5 Spot Starting QB",P56 < 4.25, "G5 Starter QB",P56 < 4.5, "P4 Spot Starting QB", P56 >= 4.5, "P4 Starter QB" ) | P56: =iferror((sum(T56:W56)*1.1+sum(X56:Z56)*0.9)/7,0) -> 0 | Q56: =(sum(T56:W56)-sum(X56:Z56)*1.3) -> 0 | T56: =iferror(XLOOKUP(I56, $AC$2:$AC$6,$AD$2:$AD$6), 0) -> 0 | U56: =iferror(XLOOKUP(J56, $AE$2:$AE$6,$AF$2:$AF$6), 0) -> 0 | V56: =iferror(XLOOKUP(K56, $AG$2:$AG$6,$AH$2:$AH$6), 0) -> 0 | W56: =iferror(XLOOKUP(L56, $AI$2:$AI$6,$AJ$2:$AJ$6), 0) -> 0 | X56: =iferror(XLOOKUP(M56, $AK$2:$AK$6,$AL$2:$AL$6), 0) -> 0 | Y56: =iferror(XLOOKUP(N56, $AM$2:$AM$6,$AN$2:$AN$6), 0) -> 0 | Z56: =iferror(XLOOKUP(O56, $AO$2:$AO$6,$AP$2:$AP$6), 0) -> 0
D57: =ifs(P57 = 0, "",P57<3.25, "G5 Backup QB", P57<3.75, "G5 Spot Starting QB",P57 < 4.25, "G5 Starter QB",P57 < 4.5, "P4 Spot Starting QB", P57 >= 4.5, "P4 Starter QB" ) | P57: =iferror((sum(T57:W57)*1.1+sum(X57:Z57)*0.9)/7,0) -> 0 | Q57: =(sum(T57:W57)-sum(X57:Z57)*1.3) -> 0 | T57: =iferror(XLOOKUP(I57, $AC$2:$AC$6,$AD$2:$AD$6), 0) -> 0 | U57: =iferror(XLOOKUP(J57, $AE$2:$AE$6,$AF$2:$AF$6), 0) -> 0 | V57: =iferror(XLOOKUP(K57, $AG$2:$AG$6,$AH$2:$AH$6), 0) -> 0 | W57: =iferror(XLOOKUP(L57, $AI$2:$AI$6,$AJ$2:$AJ$6), 0) -> 0 | X57: =iferror(XLOOKUP(M57, $AK$2:$AK$6,$AL$2:$AL$6), 0) -> 0 | Y57: =iferror(XLOOKUP(N57, $AM$2:$AM$6,$AN$2:$AN$6), 0) -> 0 | Z57: =iferror(XLOOKUP(O57, $AO$2:$AO$6,$AP$2:$AP$6), 0) -> 0
D58: =ifs(P58 = 0, "",P58<3.25, "G5 Backup QB", P58<3.75, "G5 Spot Starting QB",P58 < 4.25, "G5 Starter QB",P58 < 4.5, "P4 Spot Starting QB", P58 >= 4.5, "P4 Starter QB" ) | P58: =iferror((sum(T58:W58)*1.1+sum(X58:Z58)*0.9)/7,0) -> 0 | Q58: =(sum(T58:W58)-sum(X58:Z58)*1.3) -> 0 | T58: =iferror(XLOOKUP(I58, $AC$2:$AC$6,$AD$2:$AD$6), 0) -> 0 | U58: =iferror(XLOOKUP(J58, $AE$2:$AE$6,$AF$2:$AF$6), 0) -> 0 | V58: =iferror(XLOOKUP(K58, $AG$2:$AG$6,$AH$2:$AH$6), 0) -> 0 | W58: =iferror(XLOOKUP(L58, $AI$2:$AI$6,$AJ$2:$AJ$6), 0) -> 0 | X58: =iferror(XLOOKUP(M58, $AK$2:$AK$6,$AL$2:$AL$6), 0) -> 0 | Y58: =iferror(XLOOKUP(N58, $AM$2:$AM$6,$AN$2:$AN$6), 0) -> 0 | Z58: =iferror(XLOOKUP(O58, $AO$2:$AO$6,$AP$2:$AP$6), 0) -> 0
D59: =ifs(P59 = 0, "",P59<3.25, "G5 Backup QB", P59<3.75, "G5 Spot Starting QB",P59 < 4.25, "G5 Starter QB",P59 < 4.5, "P4 Spot Starting QB", P59 >= 4.5, "P4 Starter QB" ) | P59: =iferror((sum(T59:W59)*1.1+sum(X59:Z59)*0.9)/7,0) -> 0 | Q59: =(sum(T59:W59)-sum(X59:Z59)*1.3) -> 0 | T59: =iferror(XLOOKUP(I59, $AC$2:$AC$6,$AD$2:$AD$6), 0) -> 0 | U59: =iferror(XLOOKUP(J59, $AE$2:$AE$6,$AF$2:$AF$6), 0) -> 0 | V59: =iferror(XLOOKUP(K59, $AG$2:$AG$6,$AH$2:$AH$6), 0) -> 0 | W59: =iferror(XLOOKUP(L59, $AI$2:$AI$6,$AJ$2:$AJ$6), 0) -> 0 | X59: =iferror(XLOOKUP(M59, $AK$2:$AK$6,$AL$2:$AL$6), 0) -> 0 | Y59: =iferror(XLOOKUP(N59, $AM$2:$AM$6,$AN$2:$AN$6), 0) -> 0 | Z59: =iferror(XLOOKUP(O59, $AO$2:$AO$6,$AP$2:$AP$6), 0) -> 0
D60: =ifs(P60 = 0, "",P60<3.25, "G5 Backup QB", P60<3.75, "G5 Spot Starting QB",P60 < 4.25, "G5 Starter QB",P60 < 4.5, "P4 Spot Starting QB", P60 >= 4.5, "P4 Starter QB" ) | P60: =iferror((sum(T60:W60)*1.1+sum(X60:Z60)*0.9)/7,0) -> 0 | Q60: =(sum(T60:W60)-sum(X60:Z60)*1.3) -> 0 | T60: =iferror(XLOOKUP(I60, $AC$2:$AC$6,$AD$2:$AD$6), 0) -> 0 | U60: =iferror(XLOOKUP(J60, $AE$2:$AE$6,$AF$2:$AF$6), 0) -> 0 | V60: =iferror(XLOOKUP(K60, $AG$2:$AG$6,$AH$2:$AH$6), 0) -> 0 | W60: =iferror(XLOOKUP(L60, $AI$2:$AI$6,$AJ$2:$AJ$6), 0) -> 0 | X60: =iferror(XLOOKUP(M60, $AK$2:$AK$6,$AL$2:$AL$6), 0) -> 0 | Y60: =iferror(XLOOKUP(N60, $AM$2:$AM$6,$AN$2:$AN$6), 0) -> 0 | Z60: =iferror(XLOOKUP(O60, $AO$2:$AO$6,$AP$2:$AP$6), 0) -> 0
... D346: =ifs(P346 = 0, "",P346<3.25, "G5 Backup QB", P346<3.75, "G5 Spot Starting QB",P346 < 4.25, "G5 Starter QB",P346 < 4.5, "P4 Spot Starting QB", P346 >= 4.5, "P4 Starter QB" ) | P346: =iferror((sum(T346:W346)*1.1+sum(X346:Z346)*0.9)/7,0) -> 0 | Q346: =(sum(T346:W346)-sum(X346:Z346)*1.3) -> 0 | T346: =iferror(XLOOKUP(I346, $AC$2:$AC$6,$AD$2:$AD$6), 0) -> 0 | U346: =iferror(XLOOKUP(J346, $AE$2:$AE$6,$AF$2:$AF$6), 0) -> 0 | V346: =iferror(XLOOKUP(K346, $AG$2:$AG$6,$AH$2:$AH$6), 0) -> 0 | W346: =iferror(XLOOKUP(L346, $AI$2:$AI$6,$AJ$2:$AJ$6), 0) -> 0 | X346: =iferror(XLOOKUP(M346, $AK$2:$AK$6,$AL$2:$AL$6), 0) -> 0 | Y346: =iferror(XLOOKUP(N346, $AM$2:$AM$6,$AN$2:$AN$6), 0) -> 0 | Z346: =iferror(XLOOKUP(O346, $AO$2:$AO$6,$AP$2:$AP$6), 0) -> 0
D347: =ifs(P347 = 0, "",P347<3.25, "G5 Backup QB", P347<3.75, "G5 Spot Starting QB",P347 < 4.25, "G5 Starter QB",P347 < 4.5, "P4 Spot Starting QB", P347 >= 4.5, "P4 Starter QB" ) | T347: =iferror(XLOOKUP(I347, $AC$2:$AC$6,$AD$2:$AD$6), 0) -> 0 | U347: =iferror(XLOOKUP(J347, $AE$2:$AE$6,$AF$2:$AF$6), 0) -> 0 | V347: =iferror(XLOOKUP(K347, $AG$2:$AG$6,$AH$2:$AH$6), 0) -> 0 | W347: =iferror(XLOOKUP(L347, $AI$2:$AI$6,$AJ$2:$AJ$6), 0) -> 0 | X347: =iferror(XLOOKUP(M347, $AK$2:$AK$6,$AL$2:$AL$6), 0) -> 0 | Y347: =iferror(XLOOKUP(N347, $AM$2:$AM$6,$AN$2:$AN$6), 0) -> 0 | Z347: =iferror(XLOOKUP(O347, $AO$2:$AO$6,$AP$2:$AP$6), 0) -> 0
D348: =ifs(P348 = 0, "",P348<3.25, "G5 Backup QB", P348<3.75, "G5 Spot Starting QB",P348 < 4.25, "G5 Starter QB",P348 < 4.5, "P4 Spot Starting QB", P348 >= 4.5, "P4 Starter QB" ) | T348: =iferror(XLOOKUP(I348, $AC$2:$AC$6,$AD$2:$AD$6), 0) -> 0 | U348: =iferror(XLOOKUP(J348, $AE$2:$AE$6,$AF$2:$AF$6), 0) -> 0 | V348: =iferror(XLOOKUP(K348, $AG$2:$AG$6,$AH$2:$AH$6), 0) -> 0 | W348: =iferror(XLOOKUP(L348, $AI$2:$AI$6,$AJ$2:$AJ$6), 0) -> 0 | X348: =iferror(XLOOKUP(M348, $AK$2:$AK$6,$AL$2:$AL$6), 0) -> 0 | Y348: =iferror(XLOOKUP(N348, $AM$2:$AM$6,$AN$2:$AN$6), 0) -> 0 | Z348: =iferror(XLOOKUP(O348, $AO$2:$AO$6,$AP$2:$AP$6), 0) -> 0
D349: =ifs(P349 = 0, "",P349<3.25, "G5 Backup QB", P349<3.75, "G5 Spot Starting QB",P349 < 4.25, "G5 Starter QB",P349 < 4.5, "P4 Spot Starting QB", P349 >= 4.5, "P4 Starter QB" ) | T349: =iferror(XLOOKUP(I349, $AC$2:$AC$6,$AD$2:$AD$6), 0) -> 0 | U349: =iferror(XLOOKUP(J349, $AE$2:$AE$6,$AF$2:$AF$6), 0) -> 0 | V349: =iferror(XLOOKUP(K349, $AG$2:$AG$6,$AH$2:$AH$6), 0) -> 0 | W349: =iferror(XLOOKUP(L349, $AI$2:$AI$6,$AJ$2:$AJ$6), 0) -> 0 | X349: =iferror(XLOOKUP(M349, $AK$2:$AK$6,$AL$2:$AL$6), 0) -> 0 | Y349: =iferror(XLOOKUP(N349, $AM$2:$AM$6,$AN$2:$AN$6), 0) -> 0 | Z349: =iferror(XLOOKUP(O349, $AO$2:$AO$6,$AP$2:$AP$6), 0) -> 0
D350: =ifs(P350 = 0, "",P350<3.25, "G5 Backup QB", P350<3.75, "G5 Spot Starting QB",P350 < 4.25, "G5 Starter QB",P350 < 4.5, "P4 Spot Starting QB", P350 >= 4.5, "P4 Starter QB" ) | T350: =iferror(XLOOKUP(I350, $AC$2:$AC$6,$AD$2:$AD$6), 0) -> 0 | U350: =iferror(XLOOKUP(J350, $AE$2:$AE$6,$AF$2:$AF$6), 0) -> 0 | V350: =iferror(XLOOKUP(K350, $AG$2:$AG$6,$AH$2:$AH$6), 0) -> 0 | W350: =iferror(XLOOKUP(L350, $AI$2:$AI$6,$AJ$2:$AJ$6), 0) -> 0 | X350: =iferror(XLOOKUP(M350, $AK$2:$AK$6,$AL$2:$AL$6), 0) -> 0 | Y350: =iferror(XLOOKUP(N350, $AM$2:$AM$6,$AN$2:$AN$6), 0) -> 0 | Z350: =iferror(XLOOKUP(O350, $AO$2:$AO$6,$AP$2:$AP$6), 0) -> 0
D351: =ifs(P351 = 0, "",P351<3.25, "G5 Backup QB", P351<3.75, "G5 Spot Starting QB",P351 < 4.25, "G5 Starter QB",P351 < 4.5, "P4 Spot Starting QB", P351 >= 4.5, "P4 Starter QB" ) | T351: =iferror(XLOOKUP(I351, $AC$2:$AC$6,$AD$2:$AD$6), 0) -> 0 | U351: =iferror(XLOOKUP(J351, $AE$2:$AE$6,$AF$2:$AF$6), 0) -> 0 | V351: =iferror(XLOOKUP(K351, $AG$2:$AG$6,$AH$2:$AH$6), 0) -> 0 | W351: =iferror(XLOOKUP(L351, $AI$2:$AI$6,$AJ$2:$AJ$6), 0) -> 0 | X351: =iferror(XLOOKUP(M351, $AK$2:$AK$6,$AL$2:$AL$6), 0) -> 0 | Y351: =iferror(XLOOKUP(N351, $AM$2:$AM$6,$AN$2:$AN$6), 0) -> 0 | Z351: =iferror(XLOOKUP(O351, $AO$2:$AO$6,$AP$2:$AP$6), 0) -> 0
D352: =ifs(P352 = 0, "",P352<3.25, "G5 Backup QB", P352<3.75, "G5 Spot Starting QB",P352 < 4.25, "G5 Starter QB",P352 < 4.5, "P4 Spot Starting QB", P352 >= 4.5, "P4 Starter QB" ) | T352: =iferror(XLOOKUP(I352, $AC$2:$AC$6,$AD$2:$AD$6), 0) -> 0 | U352: =iferror(XLOOKUP(J352, $AE$2:$AE$6,$AF$2:$AF$6), 0) -> 0 | V352: =iferror(XLOOKUP(K352, $AG$2:$AG$6,$AH$2:$AH$6), 0) -> 0 | W352: =iferror(XLOOKUP(L352, $AI$2:$AI$6,$AJ$2:$AJ$6), 0) -> 0 | X352: =iferror(XLOOKUP(M352, $AK$2:$AK$6,$AL$2:$AL$6), 0) -> 0 | Y352: =iferror(XLOOKUP(N352, $AM$2:$AM$6,$AN$2:$AN$6), 0) -> 0 | Z352: =iferror(XLOOKUP(O352, $AO$2:$AO$6,$AP$2:$AP$6), 0) -> 0
D353: =ifs(P353 = 0, "",P353<3.25, "G5 Backup QB", P353<3.75, "G5 Spot Starting QB",P353 < 4.25, "G5 Starter QB",P353 < 4.5, "P4 Spot Starting QB", P353 >= 4.5, "P4 Starter QB" ) | T353: =iferror(XLOOKUP(I353, $AC$2:$AC$6,$AD$2:$AD$6), 0) -> 0 | U353: =iferror(XLOOKUP(J353, $AE$2:$AE$6,$AF$2:$AF$6), 0) -> 0 | V353: =iferror(XLOOKUP(K353, $AG$2:$AG$6,$AH$2:$AH$6), 0) -> 0 | W353: =iferror(XLOOKUP(L353, $AI$2:$AI$6,$AJ$2:$AJ$6), 0) -> 0 | X353: =iferror(XLOOKUP(M353, $AK$2:$AK$6,$AL$2:$AL$6), 0) -> 0 | Y353: =iferror(XLOOKUP(N353, $AM$2:$AM$6,$AN$2:$AN$6), 0) -> 0 | Z353: =iferror(XLOOKUP(O353, $AO$2:$AO$6,$AP$2:$AP$6), 0) -> 0
D354: =ifs(P354 = 0, "",P354<3.25, "G5 Backup QB", P354<3.75, "G5 Spot Starting QB",P354 < 4.25, "G5 Starter QB",P354 < 4.5, "P4 Spot Starting QB", P354 >= 4.5, "P4 Starter QB" ) | T354: =iferror(XLOOKUP(I354, $AC$2:$AC$6,$AD$2:$AD$6), 0) -> 0 | U354: =iferror(XLOOKUP(J354, $AE$2:$AE$6,$AF$2:$AF$6), 0) -> 0 | V354: =iferror(XLOOKUP(K354, $AG$2:$AG$6,$AH$2:$AH$6), 0) -> 0 | W354: =iferror(XLOOKUP(L354, $AI$2:$AI$6,$AJ$2:$AJ$6), 0) -> 0 | X354: =iferror(XLOOKUP(M354, $AK$2:$AK$6,$AL$2:$AL$6), 0) -> 0 | Y354: =iferror(XLOOKUP(N354, $AM$2:$AM$6,$AN$2:$AN$6), 0) -> 0 | Z354: =iferror(XLOOKUP(O354, $AO$2:$AO$6,$AP$2:$AP$6), 0) -> 0
D355: =ifs(P355 = 0, "",P355<3.25, "G5 Backup QB", P355<3.75, "G5 Spot Starting QB",P355 < 4.25, "G5 Starter QB",P355 < 4.5, "P4 Spot Starting QB", P355 >= 4.5, "P4 Starter QB" ) | T355: =iferror(XLOOKUP(I355, $AC$2:$AC$6,$AD$2:$AD$6), 0) -> 0 | U355: =iferror(XLOOKUP(J355, $AE$2:$AE$6,$AF$2:$AF$6), 0) -> 0 | V355: =iferror(XLOOKUP(K355, $AG$2:$AG$6,$AH$2:$AH$6), 0) -> 0 | W355: =iferror(XLOOKUP(L355, $AI$2:$AI$6,$AJ$2:$AJ$6), 0) -> 0 | X355: =iferror(XLOOKUP(M355, $AK$2:$AK$6,$AL$2:$AL$6), 0) -> 0 | Y355: =iferror(XLOOKUP(N355, $AM$2:$AM$6,$AN$2:$AN$6), 0) -> 0 | Z355: =iferror(XLOOKUP(O355, $AO$2:$AO$6,$AP$2:$AP$6), 0) -> 0
D356: =ifs(P356 = 0, "",P356<3.25, "G5 Backup QB", P356<3.75, "G5 Spot Starting QB",P356 < 4.25, "G5 Starter QB",P356 < 4.5, "P4 Spot Starting QB", P356 >= 4.5, "P4 Starter QB" ) | T356: =iferror(XLOOKUP(I356, $AC$2:$AC$6,$AD$2:$AD$6), 0) -> 0 | U356: =iferror(XLOOKUP(J356, $AE$2:$AE$6,$AF$2:$AF$6), 0) -> 0 | V356: =iferror(XLOOKUP(K356, $AG$2:$AG$6,$AH$2:$AH$6), 0) -> 0 | W356: =iferror(XLOOKUP(L356, $AI$2:$AI$6,$AJ$2:$AJ$6), 0) -> 0 | X356: =iferror(XLOOKUP(M356, $AK$2:$AK$6,$AL$2:$AL$6), 0) -> 0 | Y356: =iferror(XLOOKUP(N356, $AM$2:$AM$6,$AN$2:$AN$6), 0) -> 0 | Z356: =iferror(XLOOKUP(O356, $AO$2:$AO$6,$AP$2:$AP$6), 0) -> 0
D357: =ifs(P357 = 0, "",P357<3.25, "G5 Backup QB", P357<3.75, "G5 Spot Starting QB",P357 < 4.25, "G5 Starter QB",P357 < 4.5, "P4 Spot Starting QB", P357 >= 4.5, "P4 Starter QB" ) | T357: =iferror(XLOOKUP(I357, $AC$2:$AC$6,$AD$2:$AD$6), 0) -> 0 | U357: =iferror(XLOOKUP(J357, $AE$2:$AE$6,$AF$2:$AF$6), 0) -> 0 | V357: =iferror(XLOOKUP(K357, $AG$2:$AG$6,$AH$2:$AH$6), 0) -> 0 | W357: =iferror(XLOOKUP(L357, $AI$2:$AI$6,$AJ$2:$AJ$6), 0) -> 0 | X357: =iferror(XLOOKUP(M357, $AK$2:$AK$6,$AL$2:$AL$6), 0) -> 0 | Y357: =iferror(XLOOKUP(N357, $AM$2:$AM$6,$AN$2:$AN$6), 0) -> 0 | Z357: =iferror(XLOOKUP(O357, $AO$2:$AO$6,$AP$2:$AP$6), 0) -> 0
D358: =ifs(P358 = 0, "",P358<3.25, "G5 Backup QB", P358<3.75, "G5 Spot Starting QB",P358 < 4.25, "G5 Starter QB",P358 < 4.5, "P4 Spot Starting QB", P358 >= 4.5, "P4 Starter QB" ) | T358: =iferror(XLOOKUP(I358, $AC$2:$AC$6,$AD$2:$AD$6), 0) -> 0 | U358: =iferror(XLOOKUP(J358, $AE$2:$AE$6,$AF$2:$AF$6), 0) -> 0 | V358: =iferror(XLOOKUP(K358, $AG$2:$AG$6,$AH$2:$AH$6), 0) -> 0 | W358: =iferror(XLOOKUP(L358, $AI$2:$AI$6,$AJ$2:$AJ$6), 0) -> 0 | X358: =iferror(XLOOKUP(M358, $AK$2:$AK$6,$AL$2:$AL$6), 0) -> 0 | Y358: =iferror(XLOOKUP(N358, $AM$2:$AM$6,$AN$2:$AN$6), 0) -> 0 | Z358: =iferror(XLOOKUP(O358, $AO$2:$AO$6,$AP$2:$AP$6), 0) -> 0
... D999: =ifs(P999 = 0, "",P999<3.25, "G5 Backup QB", P999<3.75, "G5 Spot Starting QB",P999 < 4.25, "G5 Starter QB",P999 < 4.5, "P4 Spot Starting QB", P999 >= 4.5, "P4 Starter QB" ) | T999: =iferror(XLOOKUP(I999, $AC$2:$AC$6,$AD$2:$AD$6), 0) -> 0 | U999: =iferror(XLOOKUP(J999, $AE$2:$AE$6,$AF$2:$AF$6), 0) -> 0 | V999: =iferror(XLOOKUP(K999, $AG$2:$AG$6,$AH$2:$AH$6), 0) -> 0 | W999: =iferror(XLOOKUP(L999, $AI$2:$AI$6,$AJ$2:$AJ$6), 0) -> 0 | X999: =iferror(XLOOKUP(M999, $AK$2:$AK$6,$AL$2:$AL$6), 0) -> 0 | Y999: =iferror(XLOOKUP(N999, $AM$2:$AM$6,$AN$2:$AN$6), 0) -> 0 | Z999: =iferror(XLOOKUP(O999, $AO$2:$AO$6,$AP$2:$AP$6), 0) -> 0

Sheet RB
A1: Name | B1: COLLEGE | C1: TRANSFER PORTAL | D1: TIER | E1: SCHEME FIT | G1: ARCHETYPE | I1: Man Coverage Matchup Advantage | J1: Field Stretch | K1: Ball Skills | L1: Yards After Catch | M1: Pass Protection | N1: Gap Run Vision | O1: Zone Run Vision | P1: Create At/Behind the LOS | Q1: Create At the 2nd Level | R1: Homerun Ability | S1: GRADE | T1: DIFFERENTIAL | U1: AA Grade | X1: Grade | Y1: Grade | Z1: Grade | AA1: Grade | AB1: Grade | AC1: Grade | AD1: Grade | AE1: Grade | AF1: Grade | AG1: Grade | AJ1: Grade | AL1: Grade | AN1: Grade | AP1: Grade | AR1: Grade | AT1: Grade | AV1: Grade | AX1: Grade | AZ1: Grade
A2: Brady Hensley | B2: Eastern Kentucky | C2: N | D2: =ifs(S2 = 0, "",S2<3, "G5 Backup RB", S2<3.75, "G5 Spot Starting RB",S2 < 4.25, "G5 Starter RB",S2 < 4.5, "P4 Spot Starting RB",S2 >= 4.5, "P4 Starter RB" ) -> P4 Spot Starting RB | E2: =if(S2=0, "",ifs(AC2>AD2, "Gap Scheme ", AC2<AD2, "Zone Scheme ", AC2=AD2, "Combo Scheme ")&if(T2>-0.05, "RB", "3DRB")) -> Zone Scheme RB | G2: =IFS(S2 = 0, "", T2<-1.5, "Impact Receiver", T2<0, "More Dynamic As Receiver", T2<1.5, "More Dynamic As Runner", T2>1.5, "Impact Runner") -> Impact Runner | I2: Understands Defender Leverage, Movement Isn't Synchronized | J2: LBs Match Him Vertically | K2: Body Catcher, Thru Traffic | L2: Solid Vision, Below Average Elusiveness | M2: Good Technique; Bad Play Strength | N2: Inconsistent at Seeing Hole and Blocker Leverage | O2: Sees Hole; Immediately Read/Reacts To Blocker Leverage | P2: Run Through Defender In Backfield | Q2: Can Drive For Yards After Initial Contact | R2: Consistently Breaks Loose From 2nd Level | S2: =iferror((AB2+sum(AC2:AG2))/6,"") -> 4.375 | T2: =sum(AC2:AG2)-sum(X2:AB2) -> 4.4167 | X2: =XLOOKUP(I2, $AI$2:$AI$8, $AJ$2:$AJ$8) -> 4.6 | Y2: =XLOOKUP(J2, $AK$2:$AK$8, $AL$2:$AL$8) -> 2.3333 | Z2: =XLOOKUP(K2, $AM$2:$AM$8, $AN$2:$AN$8) -> 3.7 | AA2: =XLOOKUP(L2, $AO$2:$AO$8, $AP$2:$AP$8) -> 4.2 | AB2: =XLOOKUP(M2, $AQ$2:$AQ$8, $AR$2:$AR$8) -> 3.5 | AC2: =XLOOKUP(N2, $AS$2:$AS$8, $AT$2:$AT$8) -> 3.5 | AD2: =XLOOKUP(O2, $AS$2:$AS$8, $AT$2:$AT$8) -> 7 | AE2: =XLOOKUP(P2, $AU$2:$AU$8, $AV$2:$AV$8) -> 3.5 | AF2: =XLOOKUP(Q2, $AW$2:$AW$8, $AX$2:$AX$8) -> 3.5 | AG2: =XLOOKUP(R2, $AY$2:$AY$8, $AZ$2:$AZ$8) -> 5.25 | AI2: Consistently Separates vs LB | AJ2: 7 | AK2: Consistently Separates Deep | AL2: 7 | AM2: Hands Catcher; Thru Traffic | AN2: 7 | AO2: Good Vision Immediately; Shows Elusiveness | AP2: 7 | AQ2: Sturdy; Good Technique | AR2: 7 | AS2: Sees Hole; Immediately Read/Reacts To Blocker Leverage | AT2: 7 | AU2: Often Makes Defenders Miss In Backfield | AV2: 7 | AW2: Forces Bad Pursuit Angles In The Box | AX2: 7 | AY2: Takes Every Run To The House | AZ2: 7
A3: Daelen Alexander | B3: Rice | C3: N | D3: =ifs(S3 = 0, "",S3<3, "G5 Backup RB", S3<3.75, "G5 Spot Starting RB",S3 < 4.25, "G5 Starter RB",S3 < 4.5, "P4 Spot Starting RB",S3 >= 4.5, "P4 Starter RB" ) -> P4 Starter RB | E3: =if(S3=0, "",ifs(AC3>AD3, "Gap Scheme ", AC3<AD3, "Zone Scheme ", AC3=AD3, "Combo Scheme ")&if(T3>-0.05, "RB", "3DRB")) -> Gap Scheme RB | G3: =IFS(S3 = 0, "", T3<-1.5, "Impact Receiver", T3<0, "More Dynamic As Receiver", T3<1.5, "More Dynamic As Runner", T3>1.5, "Impact Runner") -> Impact Runner | I3: Gets Swallowed Up By LB | J3: Can't Separate vs Off Coverage | K3: Body Catcher | L3: Turns Up Field Late | M3: Sturdy; Developing Technique | N3: Sees Hole; Inconsistent At Reading Blocker Leverage | O3: Inconsistent at Seeing Hole and Blocker Leverage | P3: Run Through Defender In Backfield | Q3: Forces Bad Pursuit Angles In The Alley | R3: Consistently Breaks Loose From 2nd Level | S3: =iferror((AB3+sum(AC3:AG3))/6,"") -> 4.6666667 | T3: =sum(AC3:AG3)-sum(X3:AB3) -> 5.1667 | X3: =XLOOKUP(I3, $AI$2:$AI$8, $AJ$2:$AJ$8) -> 2.3333 | Y3: =XLOOKUP(J3, $AK$2:$AK$8, $AL$2:$AL$8) -> 4.6 | Z3: =XLOOKUP(K3, $AM$2:$AM$8, $AN$2:$AN$8) -> 2.6 | AA3: =XLOOKUP(L3, $AO$2:$AO$8, $AP$2:$AP$8) -> 2.8 | AB3: =XLOOKUP(M3, $AQ$2:$AQ$8, $AR$2:$AR$8) -> 5.25 | AC3: =XLOOKUP(N3, $AS$2:$AS$8, $AT$2:$AT$8) -> 5.25 | AD3: =XLOOKUP(O3, $AS$2:$AS$8, $AT$2:$AT$8) -> 3.5 | AE3: =XLOOKUP(P3, $AU$2:$AU$8, $AV$2:$AV$8) -> 3.5 | AF3: =XLOOKUP(Q3, $AW$2:$AW$8, $AX$2:$AX$8) -> 5.25 | AG3: =XLOOKUP(R3, $AY$2:$AY$8, $AZ$2:$AZ$8) -> 5.25 | AI3: Understands Defender Leverage, Movement Isn't Synchronized | AJ3: 4.6 | AK3: Can't Separate vs Off Coverage | AL3: 4.6 | AM3: Hands Catcher, Away From His Body | AN3: 5.9 | AO3: Solid Vision, Can Still Break Thru Contact | AP3: 5.6 | AQ3: Sturdy; Developing Technique | AR3: 5.25 | AS3: Sees Hole; Inconsistent At Reading Blocker Leverage | AT3: 5.25 | AU3: Occasionally Makes Defenders Miss In Backfield | AV3: 5.25 | AW3: Forces Bad Pursuit Angles In The Alley | AX3: 5.25 | AY3: Consistently Breaks Loose From 2nd Level | AZ3: 5.25
A4: Trequan Jones | B4: Old Dominion | C4: Y | D4: =ifs(S4 = 0, "",S4<3, "G5 Backup RB", S4<3.75, "G5 Spot Starting RB",S4 < 4.25, "G5 Starter RB",S4 < 4.5, "P4 Spot Starting RB",S4 >= 4.5, "P4 Starter RB" ) -> G5 Spot Starting RB | E4: =if(S4=0, "",ifs(AC4>AD4, "Gap Scheme ", AC4<AD4, "Zone Scheme ", AC4=AD4, "Combo Scheme ")&if(T4>-0.05, "RB", "3DRB")) -> Zone Scheme RB | G4: =IFS(S4 = 0, "", T4<-1.5, "Impact Receiver", T4<0, "More Dynamic As Receiver", T4<1.5, "More Dynamic As Runner", T4>1.5, "Impact Runner") -> Impact Runner | I4: Gets Swallowed Up By LB | J4: LBs Match Him Vertically | K4: Hands Catcher | L4: Solid Vision, Below Average Elusiveness | M4: Bad Technique; Bad Play Strength | N4: Inconsistent at Seeing Hole and Blocker Leverage | O4: Sees Hole; Inconsistent At Reading Blocker Leverage | P4: Run Through Defender In Backfield | Q4: Gets Stopped Upon Initial Contact | R4: Vision Can Disrupt His Ability To Break Loose | S4: =iferror((AB4*0.9+sum(AC4:AG4)*1.1)/6,"") -> 3.4708333 | T4: =sum(AC4:AG4)-sum(X4:AB4) -> 2.0834 | X4: =XLOOKUP(I4, $AI$2:$AI$8, $AJ$2:$AJ$8) -> 2.3333 | Y4: =XLOOKUP(J4, $AK$2:$AK$8, $AL$2:$AL$8) -> 2.3333 | Z4: =XLOOKUP(K4, $AM$2:$AM$8, $AN$2:$AN$8) -> 4.8 | AA4: =XLOOKUP(L4, $AO$2:$AO$8, $AP$2:$AP$8) -> 4.2 | AB4: =XLOOKUP(M4, $AQ$2:$AQ$8, $AR$2:$AR$8) -> 1.75 | AC4: =XLOOKUP(N4, $AS$2:$AS$8, $AT$2:$AT$8) -> 3.5 | AD4: =XLOOKUP(O4, $AS$2:$AS$8, $AT$2:$AT$8) -> 5.25 | AE4: =XLOOKUP(P4, $AU$2:$AU$8, $AV$2:$AV$8) -> 3.5 | AF4: =XLOOKUP(Q4, $AW$2:$AW$8, $AX$2:$AX$8) -> 1.75 | AG4: =XLOOKUP(R4, $AY$2:$AY$8, $AZ$2:$AZ$8) -> 3.5 | AI4: Gets Swallowed Up By LB | AJ4: 2.3333 | AK4: LBs Match Him Vertically | AL4: 2.3333 | AM4: Hands Catcher | AN4: 4.8 | AO4: Solid Vision, Below Average Elusiveness | AP4: 4.2 | AQ4: Good Technique; Bad Play Strength | AR4: 3.5 | AS4: Inconsistent at Seeing Hole and Blocker Leverage | AT4: 3.5 | AU4: Run Through Defender In Backfield | AV4: 3.5 | AW4: Can Drive For Yards After Initial Contact | AX4: 3.5 | AY4: Vision Can Disrupt His Ability To Break Loose | AZ4: 3.5
A5: Landan Harris | B5: Sam Houston | C5: N | D5: =ifs(S5 = 0, "",S5<3, "G5 Backup RB", S5<3.75, "G5 Spot Starting RB",S5 < 4.25, "G5 Starter RB",S5 < 4.5, "P4 Spot Starting RB",S5 >= 4.5, "P4 Starter RB" ) -> P4 Spot Starting RB | E5: =if(S5=0, "",ifs(AC5>AD5, "Gap Scheme ", AC5<AD5, "Zone Scheme ", AC5=AD5, "Combo Scheme ")&if(T5>-0.05, "RB", "3DRB")) -> Combo Scheme RB | G5: =IFS(S5 = 0, "", T5<-1.5, "Impact Receiver", T5<0, "More Dynamic As Receiver", T5<1.5, "More Dynamic As Runner", T5>1.5, "Impact Runner") -> More Dynamic As Runner | I5: Gets Swallowed Up By LB | J5: LBs Match Him Vertically | K5: Body Catcher, Thru Traffic | L5: Solid Vision, Below Average Elusiveness | M5: Sturdy; Developing Technique | N5: Inconsistent at Seeing Hole and Blocker Leverage | O5: Inconsistent at Seeing Hole and Blocker Leverage | P5: Occasionally Makes Defenders Miss In Backfield | Q5: Can Drive For Yards After Initial Contact | R5: Vision Can Disrupt His Ability To Break Loose | S5: =iferror((AB5*0.9+sum(AC5:AG5)*1.1)/6,"") -> 4.3166667 | T5: =sum(AC5:AG5)-sum(X5:AB5) -> 1.4334 | X5: =XLOOKUP(I5, $AI$2:$AI$8, $AJ$2:$AJ$8) -> 2.3333 | Y5: =XLOOKUP(J5, $AK$2:$AK$8, $AL$2:$AL$8) -> 2.3333 | Z5: =XLOOKUP(K5, $AM$2:$AM$8, $AN$2:$AN$8) -> 3.7 | AA5: =XLOOKUP(L5, $AO$2:$AO$8, $AP$2:$AP$8) -> 4.2 | AB5: =XLOOKUP(M5, $AQ$2:$AQ$8, $AR$2:$AR$8) -> 5.25 | AC5: =XLOOKUP(N5, $AS$2:$AS$8, $AT$2:$AT$8) -> 3.5 | AD5: =XLOOKUP(O5, $AS$2:$AS$8, $AT$2:$AT$8) -> 3.5 | AE5: =XLOOKUP(P5, $AU$2:$AU$8, $AV$2:$AV$8) -> 5.25 | AF5: =XLOOKUP(Q5, $AW$2:$AW$8, $AX$2:$AX$8) -> 3.5 | AG5: =XLOOKUP(R5, $AY$2:$AY$8, $AZ$2:$AZ$8) -> 3.5 | AM5: Body Catcher, Thru Traffic | AN5: 3.7 | AO5: Turns Up Field Late | AP5: 2.8 | AQ5: Bad Technique; Bad Play Strength | AR5: 1.75 | AS5: Bad at Seeing Hole and Blocker Leverage | AT5: 1.75 | AU5: Gets Stopped In Backfield Regularly | AV5: 1.75 | AW5: Gets Stopped Upon Initial Contact | AX5: 1.75 | AY5: Lacking Speed To Get To 3rd Level | AZ5: 1.75
A6: Clay Thevenin | B6: Louisiana Tech | C6: N | D6: =ifs(S6 = 0, "",S6<3, "G5 Backup RB", S6<3.75, "G5 Spot Starting RB",S6 < 4.25, "G5 Starter RB",S6 < 4.5, "P4 Spot Starting RB",S6 >= 4.5, "P4 Starter RB" ) -> P4 Spot Starting RB | E6: =if(S6=0, "",ifs(AC6>AD6, "Gap Scheme ", AC6<AD6, "Zone Scheme ", AC6=AD6, "Combo Scheme ")&if(T6>-0.05, "RB", "3DRB")) -> Gap Scheme RB | G6: =IFS(S6 = 0, "", T6<-1.5, "Impact Receiver", T6<0, "More Dynamic As Receiver", T6<1.5, "More Dynamic As Runner", T6>1.5, "Impact Runner") -> Impact Runner | I6: Gets Swallowed Up By LB | J6: LBs Match Him Vertically | K6: Body Catcher, Thru Traffic | L6: Solid Vision, Below Average Elusiveness | M6: Good Technique; Bad Play Strength | N6: Sees Hole; Inconsistent At Reading Blocker Leverage | O6: Inconsistent at Seeing Hole and Blocker Leverage | P6: Occasionally Makes Defenders Miss In Backfield | Q6: Can Drive For Yards After Initial Contact | R6: Vision Can Disrupt His Ability To Break Loose | S6: =iferror((AB6*0.9+sum(AC6:AG6)*1.1)/6,"") -> 4.375 | T6: =sum(AC6:AG6)-sum(X6:AB6) -> 4.9334 | X6: =XLOOKUP(I6, $AI$2:$AI$8, $AJ$2:$AJ$8) -> 2.3333 | Y6: =XLOOKUP(J6, $AK$2:$AK$8, $AL$2:$AL$8) -> 2.3333 | Z6: =XLOOKUP(K6, $AM$2:$AM$8, $AN$2:$AN$8) -> 3.7 | AA6: =XLOOKUP(L6, $AO$2:$AO$8, $AP$2:$AP$8) -> 4.2 | AB6: =XLOOKUP(M6, $AQ$2:$AQ$8, $AR$2:$AR$8) -> 3.5 | AC6: =XLOOKUP(N6, $AS$2:$AS$8, $AT$2:$AT$8) -> 5.25 | AD6: =XLOOKUP(O6, $AS$2:$AS$8, $AT$2:$AT$8) -> 3.5 | AE6: =XLOOKUP(P6, $AU$2:$AU$8, $AV$2:$AV$8) -> 5.25 | AF6: =XLOOKUP(Q6, $AW$2:$AW$8, $AX$2:$AX$8) -> 3.5 | AG6: =XLOOKUP(R6, $AY$2:$AY$8, $AZ$2:$AZ$8) -> 3.5 | AM6: Body Catcher | AN6: 2.6 | AO6: Goes Down Immediately | AP6: 1
A7: Anthony Carrie | B7: FIU | C7: N | D7: =ifs(S7 = 0, "",S7<3, "G5 Backup RB", S7<3.75, "G5 Spot Starting RB",S7 < 4.25, "G5 Starter RB",S7 < 4.5, "P4 Spot Starting RB",S7 >= 4.5, "P4 Starter RB" ) -> G5 Spot Starting RB | E7: =if(S7=0, "",ifs(AC7>AD7, "Gap Scheme ", AC7<AD7, "Zone Scheme ", AC7=AD7, "Combo Scheme ")&if(T7>-0.05, "RB", "3DRB")) -> Combo Scheme RB | G7: =IFS(S7 = 0, "", T7<-1.5, "Impact Receiver", T7<0, "More Dynamic As Receiver", T7<1.5, "More Dynamic As Runner", T7>1.5, "Impact Runner") -> More Dynamic As Runner | I7: Gets Swallowed Up By LB | J7: LBs Match Him Vertically | K7: Body Catcher, Thru Traffic | L7: Solid Vision, Below Average Elusiveness | M7: Good Technique; Bad Play Strength | N7: Inconsistent at Seeing Hole and Blocker Leverage | O7: Inconsistent at Seeing Hole and Blocker Leverage | P7: Gets Stopped In Backfield Regularly | Q7: Can Drive For Yards After Initial Contact | R7: Consistently Breaks Loose From 2nd Level | S7: =iferror((AB7*0.9+sum(AC7:AG7)*1.1)/6,"") -> 3.7333333 | T7: =sum(AC7:AG7)-sum(X7:AB7) -> 1.4334 | X7: =XLOOKUP(I7, $AI$2:$AI$8, $AJ$2:$AJ$8) -> 2.3333 | Y7: =XLOOKUP(J7, $AK$2:$AK$8, $AL$2:$AL$8) -> 2.3333 | Z7: =XLOOKUP(K7, $AM$2:$AM$8, $AN$2:$AN$8) -> 3.7 | AA7: =XLOOKUP(L7, $AO$2:$AO$8, $AP$2:$AP$8) -> 4.2 | AB7: =XLOOKUP(M7, $AQ$2:$AQ$8, $AR$2:$AR$8) -> 3.5 | AC7: =XLOOKUP(N7, $AS$2:$AS$8, $AT$2:$AT$8) -> 3.5 | AD7: =XLOOKUP(O7, $AS$2:$AS$8, $AT$2:$AT$8) -> 3.5 | AE7: =XLOOKUP(P7, $AU$2:$AU$8, $AV$2:$AV$8) -> 1.75 | AF7: =XLOOKUP(Q7, $AW$2:$AW$8, $AX$2:$AX$8) -> 3.5 | AG7: =XLOOKUP(R7, $AY$2:$AY$8, $AZ$2:$AZ$8) -> 5.25 | AM7: Inconsistent Body Catcher | AN7: 1.5
A8: Cam Scott | B8: Jacksonville State | C8: N | D8: =ifs(S8 = 0, "",S8<3, "G5 Backup RB", S8<3.75, "G5 Spot Starting RB",S8 < 4.25, "G5 Starter RB",S8 < 4.5, "P4 Spot Starting RB",S8 >= 4.5, "P4 Starter RB" ) -> P4 Starter RB | E8: =if(S8=0, "",ifs(AC8>AD8, "Gap Scheme ", AC8<AD8, "Zone Scheme ", AC8=AD8, "Combo Scheme ")&if(T8>-0.05, "RB", "3DRB")) -> Zone Scheme RB | G8: =IFS(S8 = 0, "", T8<-1.5, "Impact Receiver", T8<0, "More Dynamic As Receiver", T8<1.5, "More Dynamic As Runner", T8>1.5, "Impact Runner") -> Impact Runner | I8: Understands Defender Leverage, Movement Isn't Synchronized | J8: Can't Separate vs Off Coverage | K8: Body Catcher, Thru Traffic | L8: Solid Vision, Below Average Elusiveness | M8: Good Technique; Bad Play Strength | N8: Sees Hole; Inconsistent At Reading Blocker Leverage | O8: Sees Hole; Immediately Read/Reacts To Blocker Leverage | P8: Run Through Defender In Backfield | Q8: Forces Bad Pursuit Angles In The Alley | R8: Consistently Breaks Loose From 2nd Level | S8: =iferror((AB8*0.9+sum(AC8:AG8)*1.1)/6,"") -> 5.3375 | T8: =sum(AC8:AG8)-sum(X8:AB8) -> 5.65 | X8: =XLOOKUP(I8, $AI$2:$AI$8, $AJ$2:$AJ$8) -> 4.6 | Y8: =XLOOKUP(J8, $AK$2:$AK$8, $AL$2:$AL$8) -> 4.6 | Z8: =XLOOKUP(K8, $AM$2:$AM$8, $AN$2:$AN$8) -> 3.7 | AA8: =XLOOKUP(L8, $AO$2:$AO$8, $AP$2:$AP$8) -> 4.2 | AB8: =XLOOKUP(M8, $AQ$2:$AQ$8, $AR$2:$AR$8) -> 3.5 | AC8: =XLOOKUP(N8, $AS$2:$AS$8, $AT$2:$AT$8) -> 5.25 | AD8: =XLOOKUP(O8, $AS$2:$AS$8, $AT$2:$AT$8) -> 7 | AE8: =XLOOKUP(P8, $AU$2:$AU$8, $AV$2:$AV$8) -> 3.5 | AF8: =XLOOKUP(Q8, $AW$2:$AW$8, $AX$2:$AX$8) -> 5.25 | AG8: =XLOOKUP(R8, $AY$2:$AY$8, $AZ$2:$AZ$8) -> 5.25
A9: Ofa Mataele | B9: Western Michigan | C9: N | D9: =ifs(S9 = 0, "",S9<3, "G5 Backup RB", S9<3.75, "G5 Spot Starting RB",S9 < 4.25, "G5 Starter RB",S9 < 4.5, "P4 Spot Starting RB",S9 >= 4.5, "P4 Starter RB" ) -> P4 Starter RB | E9: =if(S9=0, "",ifs(AC9>AD9, "Gap Scheme ", AC9<AD9, "Zone Scheme ", AC9=AD9, "Combo Scheme ")&if(T9>-0.05, "RB", "3DRB")) -> Combo Scheme RB | G9: =IFS(S9 = 0, "", T9<-1.5, "Impact Receiver", T9<0, "More Dynamic As Receiver", T9<1.5, "More Dynamic As Runner", T9>1.5, "Impact Runner") -> Impact Runner | I9: Gets Swallowed Up By LB | J9: LBs Match Him Vertically | K9: Body Catcher | L9: Solid Vision, Below Average Elusiveness | M9: Sturdy; Developing Technique | N9: Sees Hole; Inconsistent At Reading Blocker Leverage | O9: Sees Hole; Inconsistent At Reading Blocker Leverage | P9: Run Through Defender In Backfield | Q9: Can Drive For Yards After Initial Contact | R9: Consistently Breaks Loose From 2nd Level | S9: =iferror((AB9*0.9+sum(AC9:AG9)*1.1)/6,"") -> 4.9583333 | T9: =sum(AC9:AG9)-sum(X9:AB9) -> 6.0334 | X9: =XLOOKUP(I9, $AI$2:$AI$8, $AJ$2:$AJ$8) -> 2.3333 | Y9: =XLOOKUP(J9, $AK$2:$AK$8, $AL$2:$AL$8) -> 2.3333 | Z9: =XLOOKUP(K9, $AM$2:$AM$8, $AN$2:$AN$8) -> 2.6 | AA9: =XLOOKUP(L9, $AO$2:$AO$8, $AP$2:$AP$8) -> 4.2 | AB9: =XLOOKUP(M9, $AQ$2:$AQ$8, $AR$2:$AR$8) -> 5.25 | AC9: =XLOOKUP(N9, $AS$2:$AS$8, $AT$2:$AT$8) -> 5.25 | AD9: =XLOOKUP(O9, $AS$2:$AS$8, $AT$2:$AT$8) -> 5.25 | AE9: =XLOOKUP(P9, $AU$2:$AU$8, $AV$2:$AV$8) -> 3.5 | AF9: =XLOOKUP(Q9, $AW$2:$AW$8, $AX$2:$AX$8) -> 3.5 | AG9: =XLOOKUP(R9, $AY$2:$AY$8, $AZ$2:$AZ$8) -> 5.25
A10: Terron Kellman | B10: Wyoming | C10: Y | D10: =ifs(S10 = 0, "",S10<3, "G5 Backup RB", S10<3.75, "G5 Spot Starting RB",S10 < 4.25, "G5 Starter RB",S10 < 4.5, "P4 Spot Starting RB",S10 >= 4.5, "P4 Starter RB" ) -> P4 Spot Starting RB | E10: =if(S10=0, "",ifs(AC10>AD10, "Gap Scheme ", AC10<AD10, "Zone Scheme ", AC10=AD10, "Combo Scheme ")&if(T10>-0.05, "RB", "3DRB")) -> Gap Scheme RB | G10: =IFS(S10 = 0, "", T10<-1.5, "Impact Receiver", T10<0, "More Dynamic As Receiver", T10<1.5, "More Dynamic As Runner", T10>1.5, "Impact Runner") -> Impact Runner | I10: Gets Swallowed Up By LB | J10: LBs Match Him Vertically | K10: Body Catcher | L10: Solid Vision, Below Average Elusiveness | M10: Good Technique; Bad Play Strength | N10: Sees Hole; Inconsistent At Reading Blocker Leverage | O10: Inconsistent at Seeing Hole and Blocker Leverage | P10: Gets Stopped In Backfield Regularly | Q10: Forces Bad Pursuit Angles In The Alley | R10: Consistently Breaks Loose From 2nd Level | S10: =iferror((AB10*0.9+sum(AC10:AG10)*1.1)/6,"") -> 4.375 | T10: =sum(AC10:AG10)-sum(X10:AB10) -> 6.0334 | X10: =XLOOKUP(I10, $AI$2:$AI$8, $AJ$2:$AJ$8) -> 2.3333 | Y10: =XLOOKUP(J10, $AK$2:$AK$8, $AL$2:$AL$8) -> 2.3333 | Z10: =XLOOKUP(K10, $AM$2:$AM$8, $AN$2:$AN$8) -> 2.6 | AA10: =XLOOKUP(L10, $AO$2:$AO$8, $AP$2:$AP$8) -> 4.2 | AB10: =XLOOKUP(M10, $AQ$2:$AQ$8, $AR$2:$AR$8) -> 3.5 | AC10: =XLOOKUP(N10, $AS$2:$AS$8, $AT$2:$AT$8) -> 5.25 | AD10: =XLOOKUP(O10, $AS$2:$AS$8, $AT$2:$AT$8) -> 3.5 | AE10: =XLOOKUP(P10, $AU$2:$AU$8, $AV$2:$AV$8) -> 1.75 | AF10: =XLOOKUP(Q10, $AW$2:$AW$8, $AX$2:$AX$8) -> 5.25 | AG10: =XLOOKUP(R10, $AY$2:$AY$8, $AZ$2:$AZ$8) -> 5.25
A11: TJ Thomas Jr. | B11: Elon | C11: N | D11: =ifs(S11 = 0, "",S11<3, "G5 Backup RB", S11<3.75, "G5 Spot Starting RB",S11 < 4.25, "G5 Starter RB",S11 < 4.5, "P4 Spot Starting RB",S11 >= 4.5, "P4 Starter RB" ) -> G5 Spot Starting RB | E11: =if(S11=0, "",ifs(AC11>AD11, "Gap Scheme ", AC11<AD11, "Zone Scheme ", AC11=AD11, "Combo Scheme ")&if(T11>-0.05, "RB", "3DRB")) -> Gap Scheme RB | G11: =IFS(S11 = 0, "", T11<-1.5, "Impact Receiver", T11<0, "More Dynamic As Receiver", T11<1.5, "More Dynamic As Runner", T11>1.5, "Impact Runner") -> Impact Runner | I11: Gets Swallowed Up By LB | J11: LBs Match Him Vertically | K11: Body Catcher | L11: Solid Vision, Below Average Elusiveness | M11: Good Technique; Bad Play Strength | N11: Sees Hole; Inconsistent At Reading Blocker Leverage | O11: Inconsistent at Seeing Hole and Blocker Leverage | P11: Gets Stopped In Backfield Regularly | Q11: Forces Bad Pursuit Angles In The Alley | R11: Lacking Speed To Get To 3rd Level | S11: =iferror((AB11+sum(AC11:AG11))/6,"") -> 3.5 | T11: =sum(AC11:AG11)-sum(X11:AB11) -> 2.5334 | X11: =XLOOKUP(I11, $AI$2:$AI$8, $AJ$2:$AJ$8) -> 2.3333 | Y11: =XLOOKUP(J11, $AK$2:$AK$8, $AL$2:$AL$8) -> 2.3333 | Z11: =XLOOKUP(K11, $AM$2:$AM$8, $AN$2:$AN$8) -> 2.6 | AA11: =XLOOKUP(L11, $AO$2:$AO$8, $AP$2:$AP$8) -> 4.2 | AB11: =XLOOKUP(M11, $AQ$2:$AQ$8, $AR$2:$AR$8) -> 3.5 | AC11: =XLOOKUP(N11, $AS$2:$AS$8, $AT$2:$AT$8) -> 5.25 | AD11: =XLOOKUP(O11, $AS$2:$AS$8, $AT$2:$AT$8) -> 3.5 | AE11: =XLOOKUP(P11, $AU$2:$AU$8, $AV$2:$AV$8) -> 1.75 | AF11: =XLOOKUP(Q11, $AW$2:$AW$8, $AX$2:$AX$8) -> 5.25 | AG11: =XLOOKUP(R11, $AY$2:$AY$8, $AZ$2:$AZ$8) -> 1.75
A12: Solomon Beebe | B12: UAB | C12: Y | D12: =ifs(S12 = 0, "",S12<3, "G5 Backup RB", S12<3.75, "G5 Spot Starting RB",S12 < 4.25, "G5 Starter RB",S12 < 4.5, "P4 Spot Starting RB",S12 >= 4.5, "P4 Starter RB" ) -> G5 Starter RB | E12: =if(S12=0, "",ifs(AC12>AD12, "Gap Scheme ", AC12<AD12, "Zone Scheme ", AC12=AD12, "Combo Scheme ")&if(T12>-0.05, "RB", "3DRB")) -> Combo Scheme 3DRB | G12: =IFS(S12 = 0, "", T12<-1.5, "Impact Receiver", T12<0, "More Dynamic As Receiver", T12<1.5, "More Dynamic As Runner", T12>1.5, "Impact Runner") -> More Dynamic As Receiver | I12: Gets Swallowed Up By LB | J12: Can't Separate vs Off Coverage | K12: Hands Catcher | L12: Solid Vision, Below Average Elusiveness | M12: Good Technique; Bad Play Strength | N12: Inconsistent at Seeing Hole and Blocker Leverage | O12: Inconsistent at Seeing Hole and Blocker Leverage | P12: Occasionally Makes Defenders Miss In Backfield | Q12: Can Drive For Yards After Initial Contact | R12: Vision Can Disrupt His Ability To Break Loose | S12: =iferror((AB12*0.9+sum(AC12:AG12)*1.1)/6,"") -> 4.0541667 | T12: =sum(AC12:AG12)-sum(X12:AB12) -> -0.1833 | X12: =XLOOKUP(I12, $AI$2:$AI$8, $AJ$2:$AJ$8) -> 2.3333 | Y12: =XLOOKUP(J12, $AK$2:$AK$8, $AL$2:$AL$8) -> 4.6 | Z12: =XLOOKUP(K12, $AM$2:$AM$8, $AN$2:$AN$8) -> 4.8 | AA12: =XLOOKUP(L12, $AO$2:$AO$8, $AP$2:$AP$8) -> 4.2 | AB12: =XLOOKUP(M12, $AQ$2:$AQ$8, $AR$2:$AR$8) -> 3.5 | AC12: =XLOOKUP(N12, $AS$2:$AS$8, $AT$2:$AT$8) -> 3.5 | AD12: =XLOOKUP(O12, $AS$2:$AS$8, $AT$2:$AT$8) -> 3.5 | AE12: =XLOOKUP(P12, $AU$2:$AU$8, $AV$2:$AV$8) -> 5.25 | AF12: =XLOOKUP(Q12, $AW$2:$AW$8, $AX$2:$AX$8) -> 3.5 | AG12: =XLOOKUP(R12, $AY$2:$AY$8, $AZ$2:$AZ$8) -> 3.5
A13: Brock Townsend | B13: Central Michigan | C13: N | D13: =ifs(S13 = 0, "",S13<3, "G5 Backup RB", S13<3.75, "G5 Spot Starting RB",S13 < 4.25, "G5 Starter RB",S13 < 4.5, "P4 Spot Starting RB",S13 >= 4.5, "P4 Starter RB" ) -> G5 Backup RB | E13: =if(S13=0, "",ifs(AC13>AD13, "Gap Scheme ", AC13<AD13, "Zone Scheme ", AC13=AD13, "Combo Scheme ")&if(T13>-0.05, "RB", "3DRB")) -> Combo Scheme 3DRB | G13: =IFS(S13 = 0, "", T13<-1.5, "Impact Receiver", T13<0, "More Dynamic As Receiver", T13<1.5, "More Dynamic As Runner", T13>1.5, "Impact Runner") -> Impact Receiver | I13: Gets Swallowed Up By LB | J13: Can't Separate vs Off Coverage | K13: Hands Catcher | L13: Solid Vision, Below Average Elusiveness | M13: Bad Technique; Bad Play Strength | N13: Inconsistent at Seeing Hole and Blocker Leverage | O13: Inconsistent at Seeing Hole and Blocker Leverage | P13: Gets Stopped In Backfield Regularly | Q13: Can Drive For Yards After Initial Contact | R13: Lacking Speed To Get To 3rd Level | S13: =iferror((AB13*0.9+sum(AC13:AG13)*1.1)/6,"") -> 2.8291667 | T13: =sum(AC13:AG13)-sum(X13:AB13) -> -3.6833 | X13: =XLOOKUP(I13, $AI$2:$AI$8, $AJ$2:$AJ$8) -> 2.3333 | Y13: =XLOOKUP(J13, $AK$2:$AK$8, $AL$2:$AL$8) -> 4.6 | Z13: =XLOOKUP(K13, $AM$2:$AM$8, $AN$2:$AN$8) -> 4.8 | AA13: =XLOOKUP(L13, $AO$2:$AO$8, $AP$2:$AP$8) -> 4.2 | AB13: =XLOOKUP(M13, $AQ$2:$AQ$8, $AR$2:$AR$8) -> 1.75 | AC13: =XLOOKUP(N13, $AS$2:$AS$8, $AT$2:$AT$8) -> 3.5 | AD13: =XLOOKUP(O13, $AS$2:$AS$8, $AT$2:$AT$8) -> 3.5 | AE13: =XLOOKUP(P13, $AU$2:$AU$8, $AV$2:$AV$8) -> 1.75 | AF13: =XLOOKUP(Q13, $AW$2:$AW$8, $AX$2:$AX$8) -> 3.5 | AG13: =XLOOKUP(R13, $AY$2:$AY$8, $AZ$2:$AZ$8) -> 1.75
A14: Jordan Gant | B14: Akron | C14: N | D14: =ifs(S14 = 0, "",S14<3, "G5 Backup RB", S14<3.75, "G5 Spot Starting RB",S14 < 4.25, "G5 Starter RB",S14 < 4.5, "P4 Spot Starting RB",S14 >= 4.5, "P4 Starter RB" ) -> G5 Starter RB | E14: =if(S14=0, "",ifs(AC14>AD14, "Gap Scheme ", AC14<AD14, "Zone Scheme ", AC14=AD14, "Combo Scheme ")&if(T14>-0.05, "RB", "3DRB")) -> Gap Scheme RB | G14: =IFS(S14 = 0, "", T14<-1.5, "Impact Receiver", T14<0, "More Dynamic As Receiver", T14<1.5, "More Dynamic As Runner", T14>1.5, "Impact Runner") -> Impact Runner | I14: Gets Swallowed Up By LB | J14: LBs Match Him Vertically | K14: Body Catcher, Thru Traffic | L14: Solid Vision, Below Average Elusiveness | M14: Bad Technique; Bad Play Strength | N14: Sees Hole; Inconsistent At Reading Blocker Leverage | O14: Inconsistent at Seeing Hole and Blocker Leverage | P14: Gets Stopped In Backfield Regularly | Q14: Can Drive For Yards After Initial Contact | R14: Consistently Breaks Loose From 2nd Level | S14: =iferror((AB14*0.9+sum(AC14:AG14)*1.1)/6,"") -> 3.7916667 | T14: =sum(AC14:AG14)-sum(X14:AB14) -> 4.9334 | X14: =XLOOKUP(I14, $AI$2:$AI$8, $AJ$2:$AJ$8) -> 2.3333 | Y14: =XLOOKUP(J14, $AK$2:$AK$8, $AL$2:$AL$8) -> 2.3333 | Z14: =XLOOKUP(K14, $AM$2:$AM$8, $AN$2:$AN$8) -> 3.7 | AA14: =XLOOKUP(L14, $AO$2:$AO$8, $AP$2:$AP$8) -> 4.2 | AB14: =XLOOKUP(M14, $AQ$2:$AQ$8, $AR$2:$AR$8) -> 1.75 | AC14: =XLOOKUP(N14, $AS$2:$AS$8, $AT$2:$AT$8) -> 5.25 | AD14: =XLOOKUP(O14, $AS$2:$AS$8, $AT$2:$AT$8) -> 3.5 | AE14: =XLOOKUP(P14, $AU$2:$AU$8, $AV$2:$AV$8) -> 1.75 | AF14: =XLOOKUP(Q14, $AW$2:$AW$8, $AX$2:$AX$8) -> 3.5 | AG14: =XLOOKUP(R14, $AY$2:$AY$8, $AZ$2:$AZ$8) -> 5.25
A15: Telly Johnson | B15: NIU | C15: N | D15: =ifs(S15 = 0, "",S15<3, "G5 Backup RB", S15<3.75, "G5 Spot Starting RB",S15 < 4.25, "G5 Starter RB",S15 < 4.5, "P4 Spot Starting RB",S15 >= 4.5, "P4 Starter RB" ) -> P4 Starter RB | E15: =if(S15=0, "",ifs(AC15>AD15, "Gap Scheme ", AC15<AD15, "Zone Scheme ", AC15=AD15, "Combo Scheme ")&if(T15>-0.05, "RB", "3DRB")) -> Gap Scheme RB | G15: =IFS(S15 = 0, "", T15<-1.5, "Impact Receiver", T15<0, "More Dynamic As Receiver", T15<1.5, "More Dynamic As Runner", T15>1.5, "Impact Runner") -> Impact Runner | I15: Gets Swallowed Up By LB | J15: Can't Separate vs Off Coverage | K15: Body Catcher, Thru Traffic | L15: Solid Vision, Can Still Break Thru Contact | M15: Bad Technique; Bad Play Strength | N15: Sees Hole; Inconsistent At Reading Blocker Leverage | O15: Inconsistent at Seeing Hole and Blocker Leverage | P15: Run Through Defender In Backfield | Q15: Forces Bad Pursuit Angles In The Alley | R15: Takes Every Run To The House | S15: =iferror((AB15*0.9+sum(AC15:AG15)*1.1)/6,"") -> 4.7541667 | T15: =sum(AC15:AG15)-sum(X15:AB15) -> 6.5167 | X15: =XLOOKUP(I15, $AI$2:$AI$8, $AJ$2:$AJ$8) -> 2.3333 | Y15: =XLOOKUP(J15, $AK$2:$AK$8, $AL$2:$AL$8) -> 4.6 | Z15: =XLOOKUP(K15, $AM$2:$AM$8, $AN$2:$AN$8) -> 3.7 | AA15: =XLOOKUP(L15, $AO$2:$AO$8, $AP$2:$AP$8) -> 5.6 | AB15: =XLOOKUP(M15, $AQ$2:$AQ$8, $AR$2:$AR$8) -> 1.75 | AC15: =XLOOKUP(N15, $AS$2:$AS$8, $AT$2:$AT$8) -> 5.25 | AD15: =XLOOKUP(O15, $AS$2:$AS$8, $AT$2:$AT$8) -> 3.5 | AE15: =XLOOKUP(P15, $AU$2:$AU$8, $AV$2:$AV$8) -> 3.5 | AF15: =XLOOKUP(Q15, $AW$2:$AW$8, $AX$2:$AX$8) -> 5.25 | AG15: =XLOOKUP(R15, $AY$2:$AY$8, $AZ$2:$AZ$8) -> 7
A16: Dominic Knicely | B16: Coastal Carolina | C16: N | D16: =ifs(S16 = 0, "",S16<3, "G5 Backup RB", S16<3.75, "G5 Spot Starting RB",S16 < 4.25, "G5 Starter RB",S16 < 4.5, "P4 Spot Starting RB",S16 >= 4.5, "P4 Starter RB" ) -> P4 Starter RB | E16: =if(S16=0, "",ifs(AC16>AD16, "Gap Scheme ", AC16<AD16, "Zone Scheme ", AC16=AD16, "Combo Scheme ")&if(T16>-0.05, "RB", "3DRB")) -> Combo Scheme RB | G16: =IFS(S16 = 0, "", T16<-1.5, "Impact Receiver", T16<0, "More Dynamic As Receiver", T16<1.5, "More Dynamic As Runner", T16>1.5, "Impact Runner") -> Impact Runner | I16: Gets Swallowed Up By LB | J16: LBs Match Him Vertically | K16: Body Catcher, Thru Traffic | L16: Solid Vision, Below Average Elusiveness | M16: Good Technique; Bad Play Strength | N16: Sees Hole; Inconsistent At Reading Blocker Leverage | O16: Sees Hole; Inconsistent At Reading Blocker Leverage | P16: Gets Stopped In Backfield Regularly | Q16: Forces Bad Pursuit Angles In The Alley | R16: Consistently Breaks Loose From 2nd Level | S16: =iferror((AB16*0.9+sum(AC16:AG16)*1.1)/6,"") -> 4.6958333 | T16: =sum(AC16:AG16)-sum(X16:AB16) -> 6.6834 | X16: =XLOOKUP(I16, $AI$2:$AI$8, $AJ$2:$AJ$8) -> 2.3333 | Y16: =XLOOKUP(J16, $AK$2:$AK$8, $AL$2:$AL$8) -> 2.3333 | Z16: =XLOOKUP(K16, $AM$2:$AM$8, $AN$2:$AN$8) -> 3.7 | AA16: =XLOOKUP(L16, $AO$2:$AO$8, $AP$2:$AP$8) -> 4.2 | AB16: =XLOOKUP(M16, $AQ$2:$AQ$8, $AR$2:$AR$8) -> 3.5 | AC16: =XLOOKUP(N16, $AS$2:$AS$8, $AT$2:$AT$8) -> 5.25 | AD16: =XLOOKUP(O16, $AS$2:$AS$8, $AT$2:$AT$8) -> 5.25 | AE16: =XLOOKUP(P16, $AU$2:$AU$8, $AV$2:$AV$8) -> 1.75 | AF16: =XLOOKUP(Q16, $AW$2:$AW$8, $AX$2:$AX$8) -> 5.25 | AG16: =XLOOKUP(R16, $AY$2:$AY$8, $AZ$2:$AZ$8) -> 5.25
A17: Scottre Humphrey | B17: New Mexico | C17: N | D17: =ifs(S17 = 0, "",S17<3, "G5 Backup RB", S17<3.75, "G5 Spot Starting RB",S17 < 4.25, "G5 Starter RB",S17 < 4.5, "P4 Spot Starting RB",S17 >= 4.5, "P4 Starter RB" ) -> G5 Starter RB | E17: =if(S17=0, "",ifs(AC17>AD17, "Gap Scheme ", AC17<AD17, "Zone Scheme ", AC17=AD17, "Combo Scheme ")&if(T17>-0.05, "RB", "3DRB")) -> Zone Scheme RB | G17: =IFS(S17 = 0, "", T17<-1.5, "Impact Receiver", T17<0, "More Dynamic As Receiver", T17<1.5, "More Dynamic As Runner", T17>1.5, "Impact Runner") -> Impact Runner | I17: Understands Defender Leverage, Movement Isn't Synchronized | J17: Can't Separate vs Off Coverage | K17: Body Catcher | L17: Turns Up Field Late | M17: Bad Technique; Bad Play Strength | N17: Sees Hole; Inconsistent At Reading Blocker Leverage | O17: Sees Hole; Immediately Read/Reacts To Blocker Leverage | P17: Run Through Defender In Backfield | Q17: Can Drive For Yards After Initial Contact | R17: Vision Can Disrupt His Ability To Break Loose | S17: =iferror((AB17+sum(AC17:AG17))/6,"") -> 4.0833333 | T17: =sum(AC17:AG17)-sum(X17:AB17) -> 6.4 | X17: =XLOOKUP(I17, $AI$2:$AI$8, $AJ$2:$AJ$8) -> 4.6 | Y17: =XLOOKUP(J17, $AK$2:$AK$8, $AL$2:$AL$8) -> 4.6 | Z17: =XLOOKUP(K17, $AM$2:$AM$8, $AN$2:$AN$8) -> 2.6 | AA17: =XLOOKUP(L17, $AO$2:$AO$8, $AP$2:$AP$8) -> 2.8 | AB17: =XLOOKUP(M17, $AQ$2:$AQ$8, $AR$2:$AR$8) -> 1.75 | AC17: =XLOOKUP(N17, $AS$2:$AS$8, $AT$2:$AT$8) -> 5.25 | AD17: =XLOOKUP(O17, $AS$2:$AS$8, $AT$2:$AT$8) -> 7 | AE17: =XLOOKUP(P17, $AU$2:$AU$8, $AV$2:$AV$8) -> 3.5 | AF17: =XLOOKUP(Q17, $AW$2:$AW$8, $AX$2:$AX$8) -> 3.5 | AG17: =XLOOKUP(R17, $AY$2:$AY$8, $AZ$2:$AZ$8) -> 3.5
A18: D.J. McKinney | B18: New Mexico | C18: N | D18: =ifs(S18 = 0, "",S18<3, "G5 Backup RB", S18<3.75, "G5 Spot Starting RB",S18 < 4.25, "G5 Starter RB",S18 < 4.5, "P4 Spot Starting RB",S18 >= 4.5, "P4 Starter RB" ) -> G5 Starter RB | E18: =if(S18=0, "",ifs(AC18>AD18, "Gap Scheme ", AC18<AD18, "Zone Scheme ", AC18=AD18, "Combo Scheme ")&if(T18>-0.05, "RB", "3DRB")) -> Zone Scheme RB | G18: =IFS(S18 = 0, "", T18<-1.5, "Impact Receiver", T18<0, "More Dynamic As Receiver", T18<1.5, "More Dynamic As Runner", T18>1.5, "Impact Runner") -> Impact Runner | I18: Understands Defender Leverage, Movement Isn't Synchronized | J18: Can't Separate vs Off Coverage | K18: Body Catcher | L18: Solid Vision, Can Still Break Thru Contact | M18: Bad Technique; Bad Play Strength | N18: Inconsistent at Seeing Hole and Blocker Leverage | O18: Sees Hole; Inconsistent At Reading Blocker Leverage | P18: Run Through Defender In Backfield | Q18: Forces Bad Pursuit Angles In The Box | R18: Vision Can Disrupt His Ability To Break Loose | S18: =iferror((AB18+sum(AC18:AG18))/6,"") -> 4.0833333 | T18: =sum(AC18:AG18)-sum(X18:AB18) -> 3.6 | X18: =XLOOKUP(I18, $AI$2:$AI$8, $AJ$2:$AJ$8) -> 4.6 | Y18: =XLOOKUP(J18, $AK$2:$AK$8, $AL$2:$AL$8) -> 4.6 | Z18: =XLOOKUP(K18, $AM$2:$AM$8, $AN$2:$AN$8) -> 2.6 | AA18: =XLOOKUP(L18, $AO$2:$AO$8, $AP$2:$AP$8) -> 5.6 | AB18: =XLOOKUP(M18, $AQ$2:$AQ$8, $AR$2:$AR$8) -> 1.75 | AC18: =XLOOKUP(N18, $AS$2:$AS$8, $AT$2:$AT$8) -> 3.5 | AD18: =XLOOKUP(O18, $AS$2:$AS$8, $AT$2:$AT$8) -> 5.25 | AE18: =XLOOKUP(P18, $AU$2:$AU$8, $AV$2:$AV$8) -> 3.5 | AF18: =XLOOKUP(Q18, $AW$2:$AW$8, $AX$2:$AX$8) -> 7 | AG18: =XLOOKUP(R18, $AY$2:$AY$8, $AZ$2:$AZ$8) -> 3.5
A19: Greg Burrell | B19: Texas State | C19: N | D19: =ifs(S19 = 0, "",S19<3, "G5 Backup RB", S19<3.75, "G5 Spot Starting RB",S19 < 4.25, "G5 Starter RB",S19 < 4.5, "P4 Spot Starting RB",S19 >= 4.5, "P4 Starter RB" ) -> P4 Starter RB | E19: =if(S19=0, "",ifs(AC19>AD19, "Gap Scheme ", AC19<AD19, "Zone Scheme ", AC19=AD19, "Combo Scheme ")&if(T19>-0.05, "RB", "3DRB")) -> Gap Scheme RB | G19: =IFS(S19 = 0, "", T19<-1.5, "Impact Receiver", T19<0, "More Dynamic As Receiver", T19<1.5, "More Dynamic As Runner", T19>1.5, "Impact Runner") -> Impact Runner | I19: Understands Defender Leverage, Movement Isn't Synchronized | J19: Can't Separate vs Off Coverage | K19: Body Catcher | L19: Solid Vision, Below Average Elusiveness | M19: Good Technique; Bad Play Strength | N19: Sees Hole; Immediately Read/Reacts To Blocker Leverage | O19: Sees Hole; Inconsistent At Reading Blocker Leverage | P19: Run Through Defender In Backfield | Q19: Can Drive For Yards After Initial Contact | R19: Vision Can Disrupt His Ability To Break Loose | S19: =iferror((AB19*0.9+sum(AC19:AG19)*1.1)/6,"") -> 4.6958333 | T19: =sum(AC19:AG19)-sum(X19:AB19) -> 3.25 | X19: =XLOOKUP(I19, $AI$2:$AI$8, $AJ$2:$AJ$8) -> 4.6 | Y19: =XLOOKUP(J19, $AK$2:$AK$8, $AL$2:$AL$8) -> 4.6 | Z19: =XLOOKUP(K19, $AM$2:$AM$8, $AN$2:$AN$8) -> 2.6 | AA19: =XLOOKUP(L19, $AO$2:$AO$8, $AP$2:$AP$8) -> 4.2 | AB19: =XLOOKUP(M19, $AQ$2:$AQ$8, $AR$2:$AR$8) -> 3.5 | AC19: =XLOOKUP(N19, $AS$2:$AS$8, $AT$2:$AT$8) -> 7 | AD19: =XLOOKUP(O19, $AS$2:$AS$8, $AT$2:$AT$8) -> 5.25 | AE19: =XLOOKUP(P19, $AU$2:$AU$8, $AV$2:$AV$8) -> 3.5 | AF19: =XLOOKUP(Q19, $AW$2:$AW$8, $AX$2:$AX$8) -> 3.5 | AG19: =XLOOKUP(R19, $AY$2:$AY$8, $AZ$2:$AZ$8) -> 3.5
A20: Zylan Perry | B20: Lousiana Lafayette | C20: N | D20: =ifs(S20 = 0, "",S20<3, "G5 Backup RB", S20<3.75, "G5 Spot Starting RB",S20 < 4.25, "G5 Starter RB",S20 < 4.5, "P4 Spot Starting RB",S20 >= 4.5, "P4 Starter RB" ) -> P4 Starter RB | E20: =if(S20=0, "",ifs(AC20>AD20, "Gap Scheme ", AC20<AD20, "Zone Scheme ", AC20=AD20, "Combo Scheme ")&if(T20>-0.05, "RB", "3DRB")) -> Combo Scheme RB | G20: =IFS(S20 = 0, "", T20<-1.5, "Impact Receiver", T20<0, "More Dynamic As Receiver", T20<1.5, "More Dynamic As Runner", T20>1.5, "Impact Runner") -> More Dynamic As Runner | I20: Understands Defender Leverage, Movement Isn't Synchronized | J20: LBs Match Him Vertically | K20: Body Catcher, Thru Traffic | L20: Solid Vision, Below Average Elusiveness | M20: Sturdy; Developing Technique | N20: Sees Hole; Inconsistent At Reading Blocker Leverage | O20: Sees Hole; Inconsistent At Reading Blocker Leverage | P20: Gets Stopped In Backfield Regularly | Q20: Forces Bad Pursuit Angles In The Alley | R20: Vision Can Disrupt His Ability To Break Loose | S20: =iferror((AB20*0.9+sum(AC20:AG20)*1.1)/6,"") -> 4.6375 | T20: =sum(AC20:AG20)-sum(X20:AB20) -> 0.9167 | X20: =XLOOKUP(I20, $AI$2:$AI$8, $AJ$2:$AJ$8) -> 4.6 | Y20: =XLOOKUP(J20, $AK$2:$AK$8, $AL$2:$AL$8) -> 2.3333 | Z20: =XLOOKUP(K20, $AM$2:$AM$8, $AN$2:$AN$8) -> 3.7 | AA20: =XLOOKUP(L20, $AO$2:$AO$8, $AP$2:$AP$8) -> 4.2 | AB20: =XLOOKUP(M20, $AQ$2:$AQ$8, $AR$2:$AR$8) -> 5.25 | AC20: =XLOOKUP(N20, $AS$2:$AS$8, $AT$2:$AT$8) -> 5.25 | AD20: =XLOOKUP(O20, $AS$2:$AS$8, $AT$2:$AT$8) -> 5.25 | AE20: =XLOOKUP(P20, $AU$2:$AU$8, $AV$2:$AV$8) -> 1.75 | AF20: =XLOOKUP(Q20, $AW$2:$AW$8, $AX$2:$AX$8) -> 5.25 | AG20: =XLOOKUP(R20, $AY$2:$AY$8, $AZ$2:$AZ$8) -> 3.5
A21: Wayne Knight | B21: James Madison | C21: N | D21: =ifs(S21 = 0, "",S21<3, "G5 Backup RB", S21<3.75, "G5 Spot Starting RB",S21 < 4.25, "G5 Starter RB",S21 < 4.5, "P4 Spot Starting RB",S21 >= 4.5, "P4 Starter RB" ) -> P4 Spot Starting RB | E21: =if(S21=0, "",ifs(AC21>AD21, "Gap Scheme ", AC21<AD21, "Zone Scheme ", AC21=AD21, "Combo Scheme ")&if(T21>-0.05, "RB", "3DRB")) -> Combo Scheme RB | G21: =IFS(S21 = 0, "", T21<-1.5, "Impact Receiver", T21<0, "More Dynamic As Receiver", T21<1.5, "More Dynamic As Runner", T21>1.5, "Impact Runner") -> Impact Runner | I21: Gets Swallowed Up By LB | J21: LBs Match Him Vertically | K21: Body Catcher | L21: Solid Vision, Can Still Break Thru Contact | M21: Good Technique; Bad Play Strength | N21: Sees Hole; Inconsistent At Reading Blocker Leverage | O21: Sees Hole; Inconsistent At Reading Blocker Leverage | P21: Run Through Defender In Backfield | Q21: Gets Stopped Upon Initial Contact | R21: Consistently Breaks Loose From 2nd Level | S21: =iferror((AB21*0.9+sum(AC21:AG21)*1.1)/6,"") -> 4.375 | T21: =sum(AC21:AG21)-sum(X21:AB21) -> 4.6334 | X21: =XLOOKUP(I21, $AI$2:$AI$8, $AJ$2:$AJ$8) -> 2.3333 | Y21: =XLOOKUP(J21, $AK$2:$AK$8, $AL$2:$AL$8) -> 2.3333 | Z21: =XLOOKUP(K21, $AM$2:$AM$8, $AN$2:$AN$8) -> 2.6 | AA21: =XLOOKUP(L21, $AO$2:$AO$8, $AP$2:$AP$8) -> 5.6 | AB21: =XLOOKUP(M21, $AQ$2:$AQ$8, $AR$2:$AR$8) -> 3.5 | AC21: =XLOOKUP(N21, $AS$2:$AS$8, $AT$2:$AT$8) -> 5.25 | AD21: =XLOOKUP(O21, $AS$2:$AS$8, $AT$2:$AT$8) -> 5.25 | AE21: =XLOOKUP(P21, $AU$2:$AU$8, $AV$2:$AV$8) -> 3.5 | AF21: =XLOOKUP(Q21, $AW$2:$AW$8, $AX$2:$AX$8) -> 1.75 | AG21: =XLOOKUP(R21, $AY$2:$AY$8, $AZ$2:$AZ$8) -> 5.25
A22: Maurki James | B22: Old Dominion | C22: N | D22: =ifs(S22 = 0, "",S22<3, "G5 Backup RB", S22<3.75, "G5 Spot Starting RB",S22 < 4.25, "G5 Starter RB",S22 < 4.5, "P4 Spot Starting RB",S22 >= 4.5, "P4 Starter RB" ) -> G5 Spot Starting RB | E22: =if(S22=0, "",ifs(AC22>AD22, "Gap Scheme ", AC22<AD22, "Zone Scheme ", AC22=AD22, "Combo Scheme ")&if(T22>-0.05, "RB", "3DRB")) -> Combo Scheme 3DRB | G22: =IFS(S22 = 0, "", T22<-1.5, "Impact Receiver", T22<0, "More Dynamic As Receiver", T22<1.5, "More Dynamic As Runner", T22>1.5, "Impact Runner") -> Impact Receiver | I22: Gets Swallowed Up By LB | J22: LBs Match Him Vertically | K22: Body Catcher | L22: Solid Vision, Below Average Elusiveness | M22: Sturdy; Developing Technique | N22: Inconsistent at Seeing Hole and Blocker Leverage | O22: Inconsistent at Seeing Hole and Blocker Leverage | P22: Gets Stopped In Backfield Regularly | Q22: Can Drive For Yards After Initial Contact | R22: Lacking Speed To Get To 3rd Level | S22: =iferror((AB22*0.9+sum(AC22:AG22)*1.1)/6,"") -> 3.3541667 | T22: =sum(AC22:AG22)-sum(X22:AB22) -> -2.7166 | X22: =XLOOKUP(I22, $AI$2:$AI$8, $AJ$2:$AJ$8) -> 2.3333 | Y22: =XLOOKUP(J22, $AK$2:$AK$8, $AL$2:$AL$8) -> 2.3333 | Z22: =XLOOKUP(K22, $AM$2:$AM$8, $AN$2:$AN$8) -> 2.6 | AA22: =XLOOKUP(L22, $AO$2:$AO$8, $AP$2:$AP$8) -> 4.2 | AB22: =XLOOKUP(M22, $AQ$2:$AQ$8, $AR$2:$AR$8) -> 5.25 | AC22: =XLOOKUP(N22, $AS$2:$AS$8, $AT$2:$AT$8) -> 3.5 | AD22: =XLOOKUP(O22, $AS$2:$AS$8, $AT$2:$AT$8) -> 3.5 | AE22: =XLOOKUP(P22, $AU$2:$AU$8, $AV$2:$AV$8) -> 1.75 | AF22: =XLOOKUP(Q22, $AW$2:$AW$8, $AX$2:$AX$8) -> 3.5 | AG22: =XLOOKUP(R22, $AY$2:$AY$8, $AZ$2:$AZ$8) -> 1.75
A23: Jeffery Pittman | B23: Southern Miss | C23: N | D23: =ifs(S23 = 0, "",S23<3, "G5 Backup RB", S23<3.75, "G5 Spot Starting RB",S23 < 4.25, "G5 Starter RB",S23 < 4.5, "P4 Spot Starting RB",S23 >= 4.5, "P4 Starter RB" ) -> P4 Starter RB | E23: =if(S23=0, "",ifs(AC23>AD23, "Gap Scheme ", AC23<AD23, "Zone Scheme ", AC23=AD23, "Combo Scheme ")&if(T23>-0.05, "RB", "3DRB")) -> Gap Scheme RB | G23: =IFS(S23 = 0, "", T23<-1.5, "Impact Receiver", T23<0, "More Dynamic As Receiver", T23<1.5, "More Dynamic As Runner", T23>1.5, "Impact Runner") -> Impact Runner | I23: Gets Swallowed Up By LB | J23: LBs Match Him Vertically | K23: Body Catcher, Thru Traffic | L23: Solid Vision, Below Average Elusiveness | M23: Good Technique; Bad Play Strength | N23: Sees Hole; Immediately Read/Reacts To Blocker Leverage | O23: Sees Hole; Inconsistent At Reading Blocker Leverage | P23: Occasionally Makes Defenders Miss In Backfield | Q23: Can Drive For Yards After Initial Contact | R23: Lacking Speed To Get To 3rd Level | S23: =iferror((AB23*0.9+sum(AC23:AG23)*1.1)/6,"") -> 4.6958333 | T23: =sum(AC23:AG23)-sum(X23:AB23) -> 6.6834 | X23: =XLOOKUP(I23, $AI$2:$AI$8, $AJ$2:$AJ$8) -> 2.3333 | Y23: =XLOOKUP(J23, $AK$2:$AK$8, $AL$2:$AL$8) -> 2.3333 | Z23: =XLOOKUP(K23, $AM$2:$AM$8, $AN$2:$AN$8) -> 3.7 | AA23: =XLOOKUP(L23, $AO$2:$AO$8, $AP$2:$AP$8) -> 4.2 | AB23: =XLOOKUP(M23, $AQ$2:$AQ$8, $AR$2:$AR$8) -> 3.5 | AC23: =XLOOKUP(N23, $AS$2:$AS$8, $AT$2:$AT$8) -> 7 | AD23: =XLOOKUP(O23, $AS$2:$AS$8, $AT$2:$AT$8) -> 5.25 | AE23: =XLOOKUP(P23, $AU$2:$AU$8, $AV$2:$AV$8) -> 5.25 | AF23: =XLOOKUP(Q23, $AW$2:$AW$8, $AX$2:$AX$8) -> 3.5 | AG23: =XLOOKUP(R23, $AY$2:$AY$8, $AZ$2:$AZ$8) -> 1.75
A24: Cornell Hatcher Jr | B24: Oregon State | C24: N | D24: =ifs(S24 = 0, "",S24<3, "G5 Backup RB", S24<3.75, "G5 Spot Starting RB",S24 < 4.25, "G5 Starter RB",S24 < 4.5, "P4 Spot Starting RB",S24 >= 4.5, "P4 Starter RB" ) -> P4 Starter RB | E24: =if(S24=0, "",ifs(AC24>AD24, "Gap Scheme ", AC24<AD24, "Zone Scheme ", AC24=AD24, "Combo Scheme ")&if(T24>-0.05, "RB", "3DRB")) -> Combo Scheme RB | G24: =IFS(S24 = 0, "", T24<-1.5, "Impact Receiver", T24<0, "More Dynamic As Receiver", T24<1.5, "More Dynamic As Runner", T24>1.5, "Impact Runner") -> Impact Runner | I24: Gets Swallowed Up By LB | J24: LBs Match Him Vertically | K24: Body Catcher | L24: Solid Vision, Can Still Break Thru Contact | M24: Good Technique; Bad Play Strength | N24: Sees Hole; Inconsistent At Reading Blocker Leverage | O24: Sees Hole; Inconsistent At Reading Blocker Leverage | P24: Occasionally Makes Defenders Miss In Backfield | Q24: Can Drive For Yards After Initial Contact | R24: Vision Can Disrupt His Ability To Break Loose | S24: =iferror((AB24*0.9+sum(AC24:AG24)*1.1)/6,"") -> 4.6958333 | T24: =sum(AC24:AG24)-sum(X24:AB24) -> 6.3834 | X24: =XLOOKUP(I24, $AI$2:$AI$8, $AJ$2:$AJ$8) -> 2.3333 | Y24: =XLOOKUP(J24, $AK$2:$AK$8, $AL$2:$AL$8) -> 2.3333 | Z24: =XLOOKUP(K24, $AM$2:$AM$8, $AN$2:$AN$8) -> 2.6 | AA24: =XLOOKUP(L24, $AO$2:$AO$8, $AP$2:$AP$8) -> 5.6 | AB24: =XLOOKUP(M24, $AQ$2:$AQ$8, $AR$2:$AR$8) -> 3.5 | AC24: =XLOOKUP(N24, $AS$2:$AS$8, $AT$2:$AT$8) -> 5.25 | AD24: =XLOOKUP(O24, $AS$2:$AS$8, $AT$2:$AT$8) -> 5.25 | AE24: =XLOOKUP(P24, $AU$2:$AU$8, $AV$2:$AV$8) -> 5.25 | AF24: =XLOOKUP(Q24, $AW$2:$AW$8, $AX$2:$AX$8) -> 3.5 | AG24: =XLOOKUP(R24, $AY$2:$AY$8, $AZ$2:$AZ$8) -> 3.5
A25: Lucky Sutton | B25: San Diego State | C25: N | D25: =ifs(S25 = 0, "",S25<3, "G5 Backup RB", S25<3.75, "G5 Spot Starting RB",S25 < 4.25, "G5 Starter RB",S25 < 4.5, "P4 Spot Starting RB",S25 >= 4.5, "P4 Starter RB" ) -> P4 Spot Starting RB | E25: =if(S25=0, "",ifs(AC25>AD25, "Gap Scheme ", AC25<AD25, "Zone Scheme ", AC25=AD25, "Combo Scheme ")&if(T25>-0.05, "RB", "3DRB")) -> Combo Scheme RB | G25: =IFS(S25 = 0, "", T25<-1.5, "Impact Receiver", T25<0, "More Dynamic As Receiver", T25<1.5, "More Dynamic As Runner", T25>1.5, "Impact Runner") -> Impact Runner | I25: Gets Swallowed Up By LB | J25: LBs Match Him Vertically | K25: Inconsistent Body Catcher | L25: Solid Vision, Below Average Elusiveness | M25: Good Technique; Bad Play Strength | N25: Sees Hole; Inconsistent At Reading Blocker Leverage | O25: Sees Hole; Inconsistent At Reading Blocker Leverage | P25: Occasionally Makes Defenders Miss In Backfield | Q25: Can Drive For Yards After Initial Contact | R25: Lacking Speed To Get To 3rd Level | S25: =iferror((AB25*0.9+sum(AC25:AG25)*1.1)/6,"") -> 4.375 | T25: =sum(AC25:AG25)-sum(X25:AB25) -> 7.1334 | X25: =XLOOKUP(I25, $AI$2:$AI$8, $AJ$2:$AJ$8) -> 2.3333 | Y25: =XLOOKUP(J25, $AK$2:$AK$8, $AL$2:$AL$8) -> 2.3333 | Z25: =XLOOKUP(K25, $AM$2:$AM$8, $AN$2:$AN$8) -> 1.5 | AA25: =XLOOKUP(L25, $AO$2:$AO$8, $AP$2:$AP$8) -> 4.2 | AB25: =XLOOKUP(M25, $AQ$2:$AQ$8, $AR$2:$AR$8) -> 3.5 | AC25: =XLOOKUP(N25, $AS$2:$AS$8, $AT$2:$AT$8) -> 5.25 | AD25: =XLOOKUP(O25, $AS$2:$AS$8, $AT$2:$AT$8) -> 5.25 | AE25: =XLOOKUP(P25, $AU$2:$AU$8, $AV$2:$AV$8) -> 5.25 | AF25: =XLOOKUP(Q25, $AW$2:$AW$8, $AX$2:$AX$8) -> 3.5 | AG25: =XLOOKUP(R25, $AY$2:$AY$8, $AZ$2:$AZ$8) -> 1.75
